Workbook

Sheet Как читать
A1: Расчёт отработанной части аванса и сальдо расчётов
A3: Что этот файл делает
A4: От вас требуют вернуть аванс. В требовании почти всегда стоит вся полученная сумма — так его пишут по умолчанию, независимо от того, сколько работ вы успели выполнить. Предмет разговора — разница между этой суммой и тем, что подтверждено вашими документами. Какая часть аванса подлежит возврату именно в вашем случае, зависит от договора и от основания прекращения и оценивается юристом; файл считает разницу и показывает, из чего она сложилась.
A5: Считаете её вы, и это не фигура речи: перечисление аванса доказывает тот, кто требует его назад, а то, что аванс отработан, — подрядчик. Так распределяется бремя доказывания по устоявшейся практике (процессуальное правило — статья 65 Арбитражного процессуального кодекса РФ, а не норма о подряде); как оно ляжет в вашем деле, оценивает юрист. Пока цифры нет на бумаге, ваше письмо остаётся просьбой войти в положение.
A6: Файл собирает эту цифру из документов, которые у вас уже есть, и показывает, из чего она сложилась. Именно этого расчёта обычно не хватает к первой встрече с юристом, и на его составление уходят первые оплаченные часы.
A7: Чего он не делает
A8: Не квалифицирует отношения сторон, не оценивает перспективу спора и не предсказывает, чем кончится дело. Не заменяет юриста и не является юридической консультацией. Основание прекращения договора вы вводите как факт из документов, а не как правовую позицию: какие последствия оно влечёт, оценивает юрист по вашему договору и вашей переписке.
A9: Не считает проценты, неустойку и убытки. Это отдельные требования со своими основаниями, и в сальдо расчётов они не входят.
A10: Порядок работы
A11: 1. Лист «Договор и аванс» — реквизиты, сумма договора, сколько аванса получено по платёжным поручениям, что и когда от вас потребовали.
A12: 2. Лист «Выполнено» — все акты по объекту, включая те, которые вторая сторона не подписала. Неподписанный акт вносится наравне с подписанным: суммы, подтверждённой обеими сторонами, он не даёт, но и молчать о нём нельзя.
A13: 3. Лист «Встречное» — материалы, затраты и удержанное гарантийное. Акты сюда не переносятся: они уже посчитаны на листе «Выполнено», а одна и та же сумма, попавшая в расчёт дважды, обесценивает весь расчёт целиком.
... A26: Ни одного срока и ни одной ставки числом в файле нет намеренно. Срок ответа на требование берётся из вашего договора, сроки исковой давности и порядок их исчисления — вопрос к юристу на дату обращения. Скачанный файл не обновляется, а зашитое в нём число выглядит проверенным.

Sheet Договор и аванс
A1: Договор, аванс и предъявленное требование
A3: Заполняется по документам, а не по памяти. Сумма аванса — по платёжным поручениям, а не по пункту договора: договором могло быть предусмотрено одно, перечислено другое.
A5: Цена работ по договору с учётом всех допсоглашений | C5: договор и все допсоглашения на изменение цены
A6: Аванс получен всего | C6: платёжные поручения с назначением «аванс». Складывайте все, включая доплаты
A7: Дата последнего платежа аванса | C7: платёжное поручение
A8: Основание прекращения договора | C8: выберите из списка по документу: уведомление, соглашение, решение суда
A9: Дата, с которой договор считается прекращённым | C9: уведомление об отказе, соглашение сторон. Если дата спорная — впишите ту, что назвала вторая сторона, и отметьте это для юриста
A10: Дата получения требования о возврате | C10: конверт, отчёт об отслеживании, входящий штамп, дата письма на почте
A11: Сумма, которую требуют вернуть | C11: текст требования
A12: Срок ответа на требование | C12: дословно из договора или из самого требования. Числом в файле не задан намеренно: он у всех свой
A15: Считается по листам «Выполнено» и «Встречное»
A16: Зачтено в счёт аванса подписанными обеими сторонами актами | B16: =SUMIFS('Выполнено'!I6:I45,'Выполнено'!F6:F45,"подписан обеими сторонами") | C16: сумма столбцы «Зачтено в счёт аванса» по актам со статусом «подписан обеими сторонами»
A17: Аванс, не закрытый двусторонними актами | B17: =MAX(0,B6-B16) | C17: аванс минус то, что закрыто подписанными актами. Эта часть аванса не подтверждена двусторонними документами, и с неё начинается разговор; подлежит ли она возврату и в каком объёме — зависит от основания прекращения договора и от его условий
A18: Доля аванса, оставшаяся неотработанной | B18: =IFERROR(B17/B6,"") | C18: для понимания масштаба: сравните с долей выполнения по факту
A19: Проверка заполнения | B19: =IF(B5="","не заполнена цена договора",IF(B6="","не заполнена сумма полученного аванса",IF(B8="","не выбрано основание прекращения договора",IF(B11="","не заполнена сумма требования",IF(B6>B5,"ПРОВЕРЬТЕ: аванс больше цены договора","заполнено")))))
A21: Справочник оснований прекращения договора
A22: генподрядчик отказался от исполнения, о наших нарушениях не заявлено
A23: генподрядчик отказался от исполнения, ссылаясь на наши нарушения
A24: договор расторгнут по решению суда
A25: мы отказались от исполнения
A26: соглашение сторон
A27: договор не расторгнут, требование заявлено
A29: Основание вводится как факт из документа. Оно влияет на то, какие встречные суммы вообще имеет смысл заявлять, но вывод об этом делает юрист: таблица подсказывает, а не решает.

Sheet Выполнено
A1: Что выполнено по объекту: все акты, включая неподписанные
A3: Неподписанный акт вносится наравне с подписанным. Суммы, подтверждённой обеими сторонами, он не даёт, но он показывает, что работы передавались, и без него расчёт выглядит так, будто вы ничего не сделали. Дата передачи и чем она подтверждена — здесь самые важные столбцы: без них акт не считается переданным.
A5: № | B5: Документ | C5: № и дата | D5: Период работ | E5: Стоимость по акту | F5: Статус | G5: Дата передачи | H5: Чем подтверждена передача | I5: Зачтено в счёт аванса | J5: Оплачено деньгами | K5: Не оплачено | L5: Проверка
A6: =IF(C6="","",ROW()-5) | K6: =IF(E6="","",ROUND(E6-I6-J6,2)) | L6: =IF(E6="","",IF(F6="","не выбран статус",IF(I6+J6>E6+0.01,"ОШИБКА: зачтено и оплачено больше стоимости акта",IF(AND(F6<>"подписан обеими сторонами",I6>0),"ОШИБКА: зачёт аванса по неподписанному акту",IF(AND(F6="подписан обеими сторонами",I6+J6=0),"акт подписан, но по нему ничего не зачтено и не оплачено — проверьте",IF(AND(F6<>"подписан обеими сторонами",G6=""),"акт не подписан: без даты передачи он в расчёте не работает",IF(AND(F6<>"подписан обеими сторонами",H6=""),"акт не подписан: нечем подтвердить передачу","строка заполнена")))))))
A7: =IF(C7="","",ROW()-5) | K7: =IF(E7="","",ROUND(E7-I7-J7,2)) | L7: =IF(E7="","",IF(F7="","не выбран статус",IF(I7+J7>E7+0.01,"ОШИБКА: зачтено и оплачено больше стоимости акта",IF(AND(F7<>"подписан обеими сторонами",I7>0),"ОШИБКА: зачёт аванса по неподписанному акту",IF(AND(F7="подписан обеими сторонами",I7+J7=0),"акт подписан, но по нему ничего не зачтено и не оплачено — проверьте",IF(AND(F7<>"подписан обеими сторонами",G7=""),"акт не подписан: без даты передачи он в расчёте не работает",IF(AND(F7<>"подписан обеими сторонами",H7=""),"акт не подписан: нечем подтвердить передачу","строка заполнена")))))))
A8: =IF(C8="","",ROW()-5) | K8: =IF(E8="","",ROUND(E8-I8-J8,2)) | L8: =IF(E8="","",IF(F8="","не выбран статус",IF(I8+J8>E8+0.01,"ОШИБКА: зачтено и оплачено больше стоимости акта",IF(AND(F8<>"подписан обеими сторонами",I8>0),"ОШИБКА: зачёт аванса по неподписанному акту",IF(AND(F8="подписан обеими сторонами",I8+J8=0),"акт подписан, но по нему ничего не зачтено и не оплачено — проверьте",IF(AND(F8<>"подписан обеими сторонами",G8=""),"акт не подписан: без даты передачи он в расчёте не работает",IF(AND(F8<>"подписан обеими сторонами",H8=""),"акт не подписан: нечем подтвердить передачу","строка заполнена")))))))
A9: =IF(C9="","",ROW()-5) | K9: =IF(E9="","",ROUND(E9-I9-J9,2)) | L9: =IF(E9="","",IF(F9="","не выбран статус",IF(I9+J9>E9+0.01,"ОШИБКА: зачтено и оплачено больше стоимости акта",IF(AND(F9<>"подписан обеими сторонами",I9>0),"ОШИБКА: зачёт аванса по неподписанному акту",IF(AND(F9="подписан обеими сторонами",I9+J9=0),"акт подписан, но по нему ничего не зачтено и не оплачено — проверьте",IF(AND(F9<>"подписан обеими сторонами",G9=""),"акт не подписан: без даты передачи он в расчёте не работает",IF(AND(F9<>"подписан обеими сторонами",H9=""),"акт не подписан: нечем подтвердить передачу","строка заполнена")))))))
A10: =IF(C10="","",ROW()-5) | K10: =IF(E10="","",ROUND(E10-I10-J10,2)) | L10: =IF(E10="","",IF(F10="","не выбран статус",IF(I10+J10>E10+0.01,"ОШИБКА: зачтено и оплачено больше стоимости акта",IF(AND(F10<>"подписан обеими сторонами",I10>0),"ОШИБКА: зачёт аванса по неподписанному акту",IF(AND(F10="подписан обеими сторонами",I10+J10=0),"акт подписан, но по нему ничего не зачтено и не оплачено — проверьте",IF(AND(F10<>"подписан обеими сторонами",G10=""),"акт не подписан: без даты передачи он в расчёте не работает",IF(AND(F10<>"подписан обеими сторонами",H10=""),"акт не подписан: нечем подтвердить передачу","строка заполнена")))))))
A11: =IF(C11="","",ROW()-5) | K11: =IF(E11="","",ROUND(E11-I11-J11,2)) | L11: =IF(E11="","",IF(F11="","не выбран статус",IF(I11+J11>E11+0.01,"ОШИБКА: зачтено и оплачено больше стоимости акта",IF(AND(F11<>"подписан обеими сторонами",I11>0),"ОШИБКА: зачёт аванса по неподписанному акту",IF(AND(F11="подписан обеими сторонами",I11+J11=0),"акт подписан, но по нему ничего не зачтено и не оплачено — проверьте",IF(AND(F11<>"подписан обеими сторонами",G11=""),"акт не подписан: без даты передачи он в расчёте не работает",IF(AND(F11<>"подписан обеими сторонами",H11=""),"акт не подписан: нечем подтвердить передачу","строка заполнена")))))))
A12: =IF(C12="","",ROW()-5) | K12: =IF(E12="","",ROUND(E12-I12-J12,2)) | L12: =IF(E12="","",IF(F12="","не выбран статус",IF(I12+J12>E12+0.01,"ОШИБКА: зачтено и оплачено больше стоимости акта",IF(AND(F12<>"подписан обеими сторонами",I12>0),"ОШИБКА: зачёт аванса по неподписанному акту",IF(AND(F12="подписан обеими сторонами",I12+J12=0),"акт подписан, но по нему ничего не зачтено и не оплачено — проверьте",IF(AND(F12<>"подписан обеими сторонами",G12=""),"акт не подписан: без даты передачи он в расчёте не работает",IF(AND(F12<>"подписан обеими сторонами",H12=""),"акт не подписан: нечем подтвердить передачу","строка заполнена")))))))
A13: =IF(C13="","",ROW()-5) | K13: =IF(E13="","",ROUND(E13-I13-J13,2)) | L13: =IF(E13="","",IF(F13="","не выбран статус",IF(I13+J13>E13+0.01,"ОШИБКА: зачтено и оплачено больше стоимости акта",IF(AND(F13<>"подписан обеими сторонами",I13>0),"ОШИБКА: зачёт аванса по неподписанному акту",IF(AND(F13="подписан обеими сторонами",I13+J13=0),"акт подписан, но по нему ничего не зачтено и не оплачено — проверьте",IF(AND(F13<>"подписан обеими сторонами",G13=""),"акт не подписан: без даты передачи он в расчёте не работает",IF(AND(F13<>"подписан обеими сторонами",H13=""),"акт не подписан: нечем подтвердить передачу","строка заполнена")))))))
A14: =IF(C14="","",ROW()-5) | K14: =IF(E14="","",ROUND(E14-I14-J14,2)) | L14: =IF(E14="","",IF(F14="","не выбран статус",IF(I14+J14>E14+0.01,"ОШИБКА: зачтено и оплачено больше стоимости акта",IF(AND(F14<>"подписан обеими сторонами",I14>0),"ОШИБКА: зачёт аванса по неподписанному акту",IF(AND(F14="подписан обеими сторонами",I14+J14=0),"акт подписан, но по нему ничего не зачтено и не оплачено — проверьте",IF(AND(F14<>"подписан обеими сторонами",G14=""),"акт не подписан: без даты передачи он в расчёте не работает",IF(AND(F14<>"подписан обеими сторонами",H14=""),"акт не подписан: нечем подтвердить передачу","строка заполнена")))))))
A15: =IF(C15="","",ROW()-5) | K15: =IF(E15="","",ROUND(E15-I15-J15,2)) | L15: =IF(E15="","",IF(F15="","не выбран статус",IF(I15+J15>E15+0.01,"ОШИБКА: зачтено и оплачено больше стоимости акта",IF(AND(F15<>"подписан обеими сторонами",I15>0),"ОШИБКА: зачёт аванса по неподписанному акту",IF(AND(F15="подписан обеими сторонами",I15+J15=0),"акт подписан, но по нему ничего не зачтено и не оплачено — проверьте",IF(AND(F15<>"подписан обеими сторонами",G15=""),"акт не подписан: без даты передачи он в расчёте не работает",IF(AND(F15<>"подписан обеими сторонами",H15=""),"акт не подписан: нечем подтвердить передачу","строка заполнена")))))))
A16: =IF(C16="","",ROW()-5) | K16: =IF(E16="","",ROUND(E16-I16-J16,2)) | L16: =IF(E16="","",IF(F16="","не выбран статус",IF(I16+J16>E16+0.01,"ОШИБКА: зачтено и оплачено больше стоимости акта",IF(AND(F16<>"подписан обеими сторонами",I16>0),"ОШИБКА: зачёт аванса по неподписанному акту",IF(AND(F16="подписан обеими сторонами",I16+J16=0),"акт подписан, но по нему ничего не зачтено и не оплачено — проверьте",IF(AND(F16<>"подписан обеими сторонами",G16=""),"акт не подписан: без даты передачи он в расчёте не работает",IF(AND(F16<>"подписан обеими сторонами",H16=""),"акт не подписан: нечем подтвердить передачу","строка заполнена")))))))
A17: =IF(C17="","",ROW()-5) | K17: =IF(E17="","",ROUND(E17-I17-J17,2)) | L17: =IF(E17="","",IF(F17="","не выбран статус",IF(I17+J17>E17+0.01,"ОШИБКА: зачтено и оплачено больше стоимости акта",IF(AND(F17<>"подписан обеими сторонами",I17>0),"ОШИБКА: зачёт аванса по неподписанному акту",IF(AND(F17="подписан обеими сторонами",I17+J17=0),"акт подписан, но по нему ничего не зачтено и не оплачено — проверьте",IF(AND(F17<>"подписан обеими сторонами",G17=""),"акт не подписан: без даты передачи он в расчёте не работает",IF(AND(F17<>"подписан обеими сторонами",H17=""),"акт не подписан: нечем подтвердить передачу","строка заполнена")))))))
... A45: =IF(C45="","",ROW()-5) | K45: =IF(E45="","",ROUND(E45-I45-J45,2)) | L45: =IF(E45="","",IF(F45="","не выбран статус",IF(I45+J45>E45+0.01,"ОШИБКА: зачтено и оплачено больше стоимости акта",IF(AND(F45<>"подписан обеими сторонами",I45>0),"ОШИБКА: зачёт аванса по неподписанному акту",IF(AND(F45="подписан обеими сторонами",I45+J45=0),"акт подписан, но по нему ничего не зачтено и не оплачено — проверьте",IF(AND(F45<>"подписан обеими сторонами",G45=""),"акт не подписан: без даты передачи он в расчёте не работает",IF(AND(F45<>"подписан обеими сторонами",H45=""),"акт не подписан: нечем подтвердить передачу","строка заполнена")))))))
A46: Итоги
A47: Всего актов внесено | E47: =COUNTIF(E6:E45,">0")
A48: Стоимость по актам, подписанным обеими сторонами | E48: =SUMIF(F6:F45,"подписан обеими сторонами",E6:E45)
A49: Стоимость по актам переданным, но не подписанным | E49: =SUMIF(F6:F45,"передан, не подписан",E6:E45)
A50: Стоимость по актам, подписанным односторонне | E50: =SUMIF(F6:F45,"подписан односторонне",E6:E45)
A51: Стоимость по актам, на которые получен мотивированный отказ | E51: =SUMIF(F6:F45,"получен мотивированный отказ",E6:E45)
A52: Зачтено в счёт аванса подписанными актами | E52: =SUMIFS(I6:I45,F6:F45,"подписан обеими сторонами")
A53: Оплачено деньгами по всем актам | E53: =SUM(J6:J45)
A54: Не оплачено по подписанным актам | E54: =SUMIFS(K6:K45,F6:F45,"подписан обеими сторонами")
A55: Строк с ошибкой в столбце «Проверка» | E55: =COUNTIF(L6:L45,"ОШИБКА*")
A57: Столбец «Не оплачено» считается как стоимость акта минус зачтённое в счёт аванса минус оплаченное деньгами. По подписанным актам это задолженность генподрядчика перед вами, и она уменьшает сумму к возврату — но требованием о возврате аванса она не закрывается автоматически: зачёт встречных требований — самостоятельная сделка (для зачёта достаточно заявления одной стороны, статья 410 Гражданского кодекса РФ), и он допускается не во всех случаях (статья 411 того же кодекса). Порядок оформления обсуждайте с юристом.

Sheet Встречное
A1: Что стоит против возврата: материалы, затраты, удержанное
A3: Акты сюда не переносятся — они посчитаны на листе «Выполнено». Одна и та же сумма, попавшая в расчёт дважды, обесценивает расчёт целиком: вторая сторона найдёт повтор, и дальше обсуждать будут его, а не ваши деньги. Каждая строка здесь обязана опираться на документ; строка без документа в переписке работает против вас.
A5: № | B5: Основание | C5: Что именно | D5: Сумма | E5: Чем подтверждено | F5: Документ подписан второй стороной | G5: Проверка
A6: =IF(C6="","",ROW()-5) | G6: =IF(D6="","",IF(B6="","не выбрано основание",IF(E6="","ОШИБКА: сумма без подтверждающего документа",IF(F6="","не указано, подписан ли документ второй стороной",IF(F6="нет","заявлять можно, но обосновывать придётся отдельно","строка заполнена")))))
A7: =IF(C7="","",ROW()-5) | G7: =IF(D7="","",IF(B7="","не выбрано основание",IF(E7="","ОШИБКА: сумма без подтверждающего документа",IF(F7="","не указано, подписан ли документ второй стороной",IF(F7="нет","заявлять можно, но обосновывать придётся отдельно","строка заполнена")))))
A8: =IF(C8="","",ROW()-5) | G8: =IF(D8="","",IF(B8="","не выбрано основание",IF(E8="","ОШИБКА: сумма без подтверждающего документа",IF(F8="","не указано, подписан ли документ второй стороной",IF(F8="нет","заявлять можно, но обосновывать придётся отдельно","строка заполнена")))))
A9: =IF(C9="","",ROW()-5) | G9: =IF(D9="","",IF(B9="","не выбрано основание",IF(E9="","ОШИБКА: сумма без подтверждающего документа",IF(F9="","не указано, подписан ли документ второй стороной",IF(F9="нет","заявлять можно, но обосновывать придётся отдельно","строка заполнена")))))
A10: =IF(C10="","",ROW()-5) | G10: =IF(D10="","",IF(B10="","не выбрано основание",IF(E10="","ОШИБКА: сумма без подтверждающего документа",IF(F10="","не указано, подписан ли документ второй стороной",IF(F10="нет","заявлять можно, но обосновывать придётся отдельно","строка заполнена")))))
A11: =IF(C11="","",ROW()-5) | G11: =IF(D11="","",IF(B11="","не выбрано основание",IF(E11="","ОШИБКА: сумма без подтверждающего документа",IF(F11="","не указано, подписан ли документ второй стороной",IF(F11="нет","заявлять можно, но обосновывать придётся отдельно","строка заполнена")))))
A12: =IF(C12="","",ROW()-5) | G12: =IF(D12="","",IF(B12="","не выбрано основание",IF(E12="","ОШИБКА: сумма без подтверждающего документа",IF(F12="","не указано, подписан ли документ второй стороной",IF(F12="нет","заявлять можно, но обосновывать придётся отдельно","строка заполнена")))))
A13: =IF(C13="","",ROW()-5) | G13: =IF(D13="","",IF(B13="","не выбрано основание",IF(E13="","ОШИБКА: сумма без подтверждающего документа",IF(F13="","не указано, подписан ли документ второй стороной",IF(F13="нет","заявлять можно, но обосновывать придётся отдельно","строка заполнена")))))
A14: =IF(C14="","",ROW()-5) | G14: =IF(D14="","",IF(B14="","не выбрано основание",IF(E14="","ОШИБКА: сумма без подтверждающего документа",IF(F14="","не указано, подписан ли документ второй стороной",IF(F14="нет","заявлять можно, но обосновывать придётся отдельно","строка заполнена")))))
A15: =IF(C15="","",ROW()-5) | G15: =IF(D15="","",IF(B15="","не выбрано основание",IF(E15="","ОШИБКА: сумма без подтверждающего документа",IF(F15="","не указано, подписан ли документ второй стороной",IF(F15="нет","заявлять можно, но обосновывать придётся отдельно","строка заполнена")))))
A16: =IF(C16="","",ROW()-5) | G16: =IF(D16="","",IF(B16="","не выбрано основание",IF(E16="","ОШИБКА: сумма без подтверждающего документа",IF(F16="","не указано, подписан ли документ второй стороной",IF(F16="нет","заявлять можно, но обосновывать придётся отдельно","строка заполнена")))))
A17: =IF(C17="","",ROW()-5) | G17: =IF(D17="","",IF(B17="","не выбрано основание",IF(E17="","ОШИБКА: сумма без подтверждающего документа",IF(F17="","не указано, подписан ли документ второй стороной",IF(F17="нет","заявлять можно, но обосновывать придётся отдельно","строка заполнена")))))
... A30: =IF(C30="","",ROW()-5) | G30: =IF(D30="","",IF(B30="","не выбрано основание",IF(E30="","ОШИБКА: сумма без подтверждающего документа",IF(F30="","не указано, подписан ли документ второй стороной",IF(F30="нет","заявлять можно, но обосновывать придётся отдельно","строка заполнена")))))
A31: Итоги по основаниям
A32: материалы переданы генподрядчику | D32: =SUMIF(B6:B30,"материалы переданы генподрядчику",D6:D30)
A33: материалы и оборудование остались на объекте | D33: =SUMIF(B6:B30,"материалы и оборудование остались на объекте",D6:D30)
A34: затраты на мобилизацию и демобилизацию | D34: =SUMIF(B6:B30,"затраты на мобилизацию и демобилизацию",D6:D30)
A35: гарантийное удержание из оплаченных актов | D35: =SUMIF(B6:B30,"гарантийное удержание из оплаченных актов",D6:D30)
A36: иное | D36: =SUMIF(B6:B30,"иное",D6:D30)
A37: Итого заявляется встречного | D37: =SUM(D6:D30)
A38: Строк с ошибкой в столбце «Проверка» | D38: =COUNTIF(G6:G30,"ОШИБКА*")
A40: Гарантийное удержание, уже удержанное генподрядчиком из оплаченных актов, вносится сюда: это удержанная им часть оплаты по вашим актам, и в сальдо расчётов она на вашей стороне. Чем именно является удержание по вашему договору — частью цены с отложенным сроком, обеспечением или чем-то ещё — определяет формулировка договора, и от неё же зависит, когда его возвращают. Срок и событие возврата берите из договора — может оказаться, что срок ещё не наступил, и тогда это надо назвать в письме прямо, а не умолчать.
A41: Затраты на мобилизацию и демобилизацию, закупку под объект и содержание площадки — самая спорная часть расчёта. Вопрос о том, подлежат ли они возмещению, зависит от основания прекращения договора и решается юристом. Вносите их с документами и не считайте включёнными в сальдо заранее: на листе «Сальдо» они видны отдельной строкой именно поэтому.

Sheet Сальдо
A1: Сальдо расчётов по договору
A3: Читайте снизу вверх: сначала блок «Проверки». Если там есть строка, начинающаяся со слова ПРОВЕРЬТЕ, итог считать рано.
A5: Поступило от генподрядчика
A6: Аванс получен всего | B6: ='Договор и аванс'!B6 | C6: лист «Договор и аванс»
A7: Оплачено деньгами по актам | B7: =SUM('Выполнено'!J6:J45) | C7: лист «Выполнено», столбец «Оплачено деньгами», все строки
A8: Итого поступило | B8: =ROUND(B6+B7,2)
A10: Принято работ
A11: Стоимость работ по актам, подписанным обеими сторонами | B11: =SUMIF('Выполнено'!F6:F45,"подписан обеими сторонами",'Выполнено'!E6:E45) | C11: часть выполненного, подтверждённая обеими сторонами
A12: в том числе зачтено в счёт аванса | B12: =SUMIFS('Выполнено'!I6:I45,'Выполнено'!F6:F45,"подписан обеими сторонами")
A13: в том числе оплачено деньгами | B13: =SUMIFS('Выполнено'!J6:J45,'Выполнено'!F6:F45,"подписан обеими сторонами")
A14: не оплачено по подписанным актам | B14: =ROUND(B11-B12-B13,2) | C14: задолженность генподрядчика перед вами по документам, подписанным обеими сторонами
A16: Не закрытая актами часть
A17: Аванс, не закрытый двусторонними актами | B17: ='Договор и аванс'!B17 | C17: аванс минус закрытое подписанными актами. Именно эту сумму, а не весь аванс, имеет смысл обсуждать как отправную точку; подлежит ли она возврату целиком — отдельный вопрос
A19: Что заявляется против возврата
A20: Работы переданы, акты не подписаны | B20: =SUMIF('Выполнено'!F6:F45,"передан, не подписан",'Выполнено'!E6:E45) | C20: спорная часть. Работает только вместе с доказательством передачи
A21: Работы переданы, акты подписаны односторонне | B21: =SUMIF('Выполнено'!F6:F45,"подписан односторонне",'Выполнено'!E6:E45) | C21: отдельно от предыдущей строки: по пункту 4 статьи 753 ГК РФ это документы разного веса. Что даёт односторонний акт в вашем деле, оценивает юрист — см. лист «Как читать»
A22: Материалы и оборудование | B22: =SUMIF('Встречное'!B6:B30,"материалы переданы генподрядчику",'Встречное'!D6:D30)+SUMIF('Встречное'!B6:B30,"материалы и оборудование остались на объекте",'Встречное'!D6:D30)
A23: Затраты на мобилизацию и демобилизацию | B23: =SUMIF('Встречное'!B6:B30,"затраты на мобилизацию и демобилизацию",'Встречное'!D6:D30) | C23: самая спорная строка расчёта: зависит от основания прекращения договора, оценивает юрист
A24: Гарантийное удержание из оплаченных актов | B24: =SUMIF('Встречное'!B6:B30,"гарантийное удержание из оплаченных актов",'Встречное'!D6:D30) | C24: ваши деньги у генподрядчика. Проверьте по договору, наступил ли срок возврата
A25: Иное | B25: =SUMIF('Встречное'!B6:B30,"иное",'Встречное'!D6:D30)
A26: Задолженность по принятым и не оплаченным работам | B26: =B14 | C26: из блока «Принято работ»
A27: Итого заявляется против возврата | B27: =ROUND(SUM(B20:B26),2)
A29: Итог
A30: Требуют вернуть | B30: ='Договор и аванс'!B11 | C30: из требования
A31: Не закрыто двусторонними актами | B31: =B17 | C31: с этой суммы начинается разговор. Что из неё подлежит возврату — вопрос основания прекращения договора и его условий, не арифметики
A32: Сальдо с учётом заявленного встречного | B32: =ROUND(B17-B27,2) | C32: положительное — к возврату, отрицательное — в вашу пользу. Это ваша позиция, а не результат: встречное надо обосновать документами
A33: Направление сальдо | B33: =IF(B32>0,"к возврату генподрядчику",IF(B32<0,"в вашу пользу","ноль"))
A34: Расхождение между требованием и незакрытой частью | B34: =ROUND(B30-B31,2) | C34: ровно эта сумма требуется с вас сверх незакрытого актами. Она и есть предмет вашего ответа
A36: Проверки
A37: Сальдо сходится двумя способами | B37: =IF(ROUND(B11-B8,2)=ROUND(B14-B17,2),"сходится","ПРОВЕРЬТЕ: деньги приходили под акты, которые не подписаны обеими сторонами — расхождение "&ROUND((B11-B8)-(B14-B17),2)) | C37: обороты (принято минус поступило) сверяются с расчётом от аванса. Расхождение — не поломка, а находка: платёж лёг на неподписанный акт
A38: Ошибки в реестре «Выполнено» | B38: =IF(COUNTIF('Выполнено'!L6:L45,"ОШИБКА*")=0,"нет","ПРОВЕРЬТЕ: строк с ошибкой — "&COUNTIF('Выполнено'!L6:L45,"ОШИБКА*")) | C38: столбец «Проверка» на листе «Выполнено»
A39: Ошибки в реестре «Встречное» | B39: =IF(COUNTIF('Встречное'!G6:G30,"ОШИБКА*")=0,"нет","ПРОВЕРЬТЕ: сумм без подтверждающего документа — "&COUNTIF('Встречное'!G6:G30,"ОШИБКА*")) | C39: сумма без документа в письме работает против вас
A40: Заполнение листа «Договор и аванс» | B40: ='Договор и аванс'!B19
A41: Требование больше полученного аванса | B41: =IF(B30>B6+0.01,"ПРОВЕРЬТЕ: требуют больше, чем было получено авансом","нет") | C41: типовая ошибка второй стороны: в требование попадают суммы, авансом не являющиеся
A42: Есть акты, переданные без подтверждения передачи | B42: =IF(COUNTIFS('Выполнено'!F6:F45,"передан, не подписан",'Выполнено'!H6:H45,"")=0,"нет","ПРОВЕРЬТЕ: неподписанных актов без доказательства передачи — "&COUNTIFS('Выполнено'!F6:F45,"передан, не подписан",'Выполнено'!H6:H45,"")) | C42: такой акт в переписке не работает: передача доказывается описью, отчётом об отслеживании, входящим штампом
A44: Сальдо — это ваша позиция, посчитанная по вашим документам, а не решение по спору. Вторая сторона посчитает своё, и разница между двумя расчётами и есть то, о чём пойдёт разговор. Ценность этого листа в том, что ваша цифра появляется раньше и опирается на перечень документов, а не на слова.

Sheet Акт сверки
A1: Акт сверки взаимных расчётов — печатная форма
A3: Ни одно число в этой форме не вводится руками: все они — ссылки на листы расчёта. Правьте расчёт, а не форму. Форма, разошедшаяся с расчётом, подписывается быстрее, чем обнаруживается.
A4: Не подписывайте акт сверки, присланный второй стороной, пока ваш расчёт не готов и суммы не сошлись. Какое значение подписанный вами документ будет иметь в вашем деле, оценивает юрист — и оценивает уже по факту, изменить который нельзя.
A6: АКТ СВЕРКИ ВЗАИМНЫХ РАСЧЁТОВ
A7: по договору субподряда № ________ от __________ по состоянию на __________
A9: По данным Субподрядчика
A10: Основание | B10: Дебет (за генподрядчиком) | C10: Кредит (за субподрядчиком) | D10: Откуда число
A11: Сальдо на начало расчётов | B11: 0 | C11: 0 | D11: принято равным нулю: расчёты по договору начинаются с аванса
A12: Работы приняты по актам, подписанным обеими сторонами | B12: ='Сальдо'!B11 | C12: 0 | D12: лист «Сальдо», блок «Принято работ»
A13: Получен аванс | B13: 0 | C13: ='Сальдо'!B6 | D13: лист «Сальдо»
A14: Оплачено деньгами по актам | B14: 0 | C14: ='Сальдо'!B7 | D14: лист «Сальдо»
A15: Обороты за период | B15: =ROUND(SUM(B11:B14),2) | C15: =ROUND(SUM(C11:C14),2)
A16: Сальдо на конец периода | B16: =ROUND(B15-C15,2) | D16: положительное — задолженность генподрядчика перед вами; отрицательное — за вами
A18: =IF(B16<0,"По данным Субподрядчика на указанную дату за Субподрядчиком числится задолженность в размере, руб.:","По данным Субподрядчика на указанную дату за Генподрядчиком числится задолженность в размере, руб.:") | D18: =ROUND(MAX(B16,-B16),2)
A19: Отдельно, вне сальдо настоящего акта, Субподрядчик заявляет о наличии выполненных и переданных работ, акты по которым Генподрядчиком не подписаны, а также о затратах и удержаниях, перечисленных в приложении к настоящему акту. Настоящий акт составлен по данным одной стороны и не является признанием сумм, в нём не отражённых.
A21: От Субподрядчика | C21: От Генподрядчика
A22: _______________ / ______________ / | C22: _______________ / ______________ /
A23: М.П. | C23: М.П.
A25: Направляйте акт тем каналом, который назван в договоре как порядок обмена юридически значимыми сообщениями, и сохраняйте доказательство отправки. Неподписанный второй стороной акт всё равно имеет смысл: он фиксирует, что ваш расчёт был направлен и когда.

Sheet Пример заполнения
A1: Пример заполнения — цифры условные
A3: Переносить отсюда нечего. Пример показывает формат и порядок, а не значения: цифры в нём выдуманы для наглядности, и ни одна из них не является типовой, рекомендуемой или взятой из нормы.
A5: Лист «Договор и аванс»
A6: Цена работ по договору | B6: 12 000 000,00
A7: Аванс получен всего | B7: 3 600 000,00
A8: Основание прекращения договора | B8: генподрядчик отказался от исполнения, о наших нарушениях не заявлено
A9: Сумма, которую требуют вернуть | B9: 3 600 000,00
A10: Требуют весь аванс целиком — это и есть типовая формулировка, ради которой файл существует.
A11: Лист «Выполнено»
A12: КС-2 № 1, подписан обеими сторонами | B12: 2 000 000,00, зачтено в счёт аванса 600 000,00, оплачено деньгами 1 400 000,00
A13: КС-2 № 2, подписан обеими сторонами | B13: 1 500 000,00, зачтено 450 000,00, оплачено 950 000,00
A14: КС-2 № 3, передан, не подписан | B14: 1 100 000,00, дата передачи есть, подтверждение — опись и трек
A15: Лист «Встречное»
A16: Материалы оставлены на объекте | B16: 480 000,00, накладная подписана прорабом генподрядчика
A17: Гарантийное удержание из оплаченных актов | B17: 175 000,00
A18: Что получится на листе «Сальдо»
A19: Зачтено в счёт аванса подписанными актами | B19: 1 050 000,00
A20: Аванс, не закрытый двусторонними актами | B20: 2 550 000,00
A21: Не оплачено по подписанным актам | B21: 100 000,00
A22: Итого заявляется против возврата | B22: 1 100 000 + 480 000 + 175 000 + 100 000 = 1 855 000,00
A23: Сальдо с учётом заявленного встречного | B23: 695 000,00 к возврату
A24: Расхождение между требованием и незакрытой частью | B24: 1 050 000,00
A25: Разница между «вернуть 3 600 000» и «вернуть 695 000» — это и есть предмет письма. Ни одна из этих сумм не является решением по спору: встречное надо обосновать, и часть обоснования вторая сторона оспорит. Но разговор теперь идёт о разнице, а не о всей сумме.
