Workbook

Sheet Условия
A1: Калькулятор условий аванса
A2: Заполните жёлтые ячейки в двух колонках. Синим — то, что вводите вы; чёрным — то, что считают формулы. Сценарий А — условия, которые вам предлагают. Сценарий Б — условия, которые вы просите. Разницу между ними покажет лист «Сравнение»: она и есть предмет переговоров.
A4: Условие | B4: Сценарий А | C4: Сценарий Б | D4: Что это и откуда взять
A5: Сумма договора, руб. | D5: Цена работ по вашему договору субподряда. С НДС или без — как угодно, важно одно: все поля этого листа в одной базе.
A6: Размер аванса, % от суммы договора | D6: Сколько процентов цены выплачивается авансом. Нулевой аванс — это тоже сценарий, и его полезно посчитать: он показывает цену вопроса целиком.
A7: Месяц поступления аванса | D7: Номер месяца от старта объекта, в котором деньги реально приходят на счёт, а не в котором подписан договор. Разница обычно и есть месяц-два своих денег.
A8: Порядок погашения аванса | D8: Выберите из списка одно из трёх значений. Список — внизу этого листа.
A9: Доля выполнения, с которой начинается погашение, % | D9: Только для порядка «с отсрочкой до доли выполнения». Для двух других порядков поле не используется.
A10: Ставка обеспечения аванса, % годовых | D10: Банковская гарантия или страхование возврата аванса. Ставку берите из предложения банка или страховщика на сегодня. Если обеспечение не требуется — 0.
A11: Срок действия обеспечения, мес. | D11: Из требования генподрядчика: обычно срок объекта плюс запас. Ставка годовая, поэтому длина срока прямо умножает стоимость.
A12: Месяц оплаты обеспечения | D12: Комиссия чаще всего платится вперёд, до выдачи аванса. Поставьте месяц, в котором вы её фактически платите.
A13: Гарантийное удержание, % от каждой КС | D13: Сколько генподрядчик удерживает из каждого акта. Удержание вычитается из той же КС, из которой гасится аванс: два изъятия из одного платежа складываются.
A14: Месяц возврата гарантийного удержания | D14: Из договора. Если возврат наступает за пределами горизонта расчёта — поставьте 0, и удержанные деньги останутся замороженными до конца расчёта.
A15: Доля возвращаемого удержания, % | D15: Если договор возвращает удержание частями, укажите долю той части, которая приходит в указанный месяц.
A16: Срок объекта, мес. | D16: Продолжительность работ по графику. Используется для проверки: объём в графике КС за пределами срока — признак ошибки ввода.
... A20: Стартовые затраты до первой КС, руб. | D20: Мобилизация, бытовки, залоги, первый завоз — то, что тратится до первого акта.
A22: Считается по введённому
A23: Сумма аванса, руб. | B23: =IF('Условия'!$B$5="",0,ROUND('Условия'!$B$5*'Условия'!$B$6/100,2)) | C23: =IF('Условия'!$C$5="",0,ROUND('Условия'!$C$5*'Условия'!$C$6/100,2))
A24: Стоимость обеспечения аванса, руб. | B24: =ROUND('Условия'!$B$23*'Условия'!$B$10/100*'Условия'!$B$11/12,2) | C24: =ROUND('Условия'!$C$23*'Условия'!$C$10/100*'Условия'!$C$11/12,2)
A25: Код порядка погашения (1, 2 или 3) | B25: =IFERROR(MATCH('Условия'!$B$8,'Условия'!$A$29:$A$31,0),0) | C25: =IFERROR(MATCH('Условия'!$C$8,'Условия'!$A$29:$A$31,0),0)
A26: Проверка условий | B26: =IF('Условия'!$B$5="","Не заполнена сумма договора",IF('Условия'!$B$25=0,"Порядок погашения не выбран из списка",IF(AND('Условия'!$B$25=3,'Условия'!$B$9=""),"Для порядка с отсрочкой укажите долю выполнения",IF('Условия'!$B$16="","Не заполнен срок объекта",IF('Условия'!$B$10>0,"Условия заполнены. Обеспечение платное — его стоимость уже вычтена из кассы","Условия заполнены"))))) | C26: =IF('Условия'!$C$5="","Не заполнена сумма договора",IF('Условия'!$C$25=0,"Порядок погашения не выбран из списка",IF(AND('Условия'!$C$25=3,'Условия'!$C$9=""),"Для порядка с отсрочкой укажите долю выполнения",IF('Условия'!$C$16="","Не заполнен срок объекта",IF('Условия'!$C$10>0,"Условия заполнены. Обеспечение платное — его стоимость уже вычтена из кассы","Условия заполнены")))))
A28: Справочник: допустимые значения порядка погашения
A29: пропорционально из каждой КС | B29: 1 | D29: Погашение равными долями от каждой КС: удержали процент — и дальше по тому же проценту.
A30: единовременно из последней КС | B30: 2 | D30: Весь аванс удерживается из последнего акта. До него касса выглядит лучше, в конце — резко хуже.
A31: с отсрочкой до доли выполнения | B31: 3 | D31: Погашение не начинается, пока не выполнена указанная доля; дальше догоняет на оставшемся объёме.
A34: Чего в этом файле нет намеренно
A35: Ни одной ставки и ни одного срока законодательства числом. Ставка обеспечения, гарантийное удержание, отсрочка оплаты, сроки — всё вводится вами из вашего договора и предложения банка на дату расчёта. Зашитое число в скачанном файле опаснее его отсутствия: файл выглядит готовым и даёт неверную цифру, с которой вы пойдёте на переговоры.
A37: Важно, прочитайте до использования
A38: Это расчётный и переговорный инструмент, а не юридическая консультация и не гарантия того, что условия аванса удастся изменить. Генподрядчик вправе не согласиться ни на один пункт: файл даёт аргумент и цифру, а не рычаг. Расчёт рассчитан на типовую ситуацию: договор обсуждается либо уже подписан, спора о выполненных объёмах и качестве нет. Сюда не применять: возврат неотработанного аванса при расторжении, требование генподрядчика вернуть аванс, зачёт, дело о банкротстве генподрядчика, налоговые последствия аванса — НДС и момент признания дохода. Это не расчёт, а спор или учёт: там нужен юрист или бухгалтер, а не таблица.

Sheet График КС
A1: График КС: сколько процентов объёма закрывается в каждом месяце
A2: Заполните жёлтые колонки: доля объёма месяца в процентах от суммы договора. Сумма долей по сценарию должна быть 100. Если вы сравниваете только условия аванса, а не график, колонки А и Б заполняются одинаково.
A4: Месяц | B4: Доля объёма, % — сценарий А | C4: Доля объёма, % — сценарий Б | D4: Проверка
A5: 1 | D5: =IF(AND($B5="",$C5=""),"",IF(OR($B5<0,$C5<0),"Доля не может быть отрицательной",""))
A6: 2 | D6: =IF(AND($B6="",$C6=""),"",IF(OR($B6<0,$C6<0),"Доля не может быть отрицательной",""))
A7: 3 | D7: =IF(AND($B7="",$C7=""),"",IF(OR($B7<0,$C7<0),"Доля не может быть отрицательной",""))
A8: 4 | D8: =IF(AND($B8="",$C8=""),"",IF(OR($B8<0,$C8<0),"Доля не может быть отрицательной",""))
A9: 5 | D9: =IF(AND($B9="",$C9=""),"",IF(OR($B9<0,$C9<0),"Доля не может быть отрицательной",""))
A10: 6 | D10: =IF(AND($B10="",$C10=""),"",IF(OR($B10<0,$C10<0),"Доля не может быть отрицательной",""))
A11: 7 | D11: =IF(AND($B11="",$C11=""),"",IF(OR($B11<0,$C11<0),"Доля не может быть отрицательной",""))
A12: 8 | D12: =IF(AND($B12="",$C12=""),"",IF(OR($B12<0,$C12<0),"Доля не может быть отрицательной",""))
A13: 9 | D13: =IF(AND($B13="",$C13=""),"",IF(OR($B13<0,$C13<0),"Доля не может быть отрицательной",""))
A14: 10 | D14: =IF(AND($B14="",$C14=""),"",IF(OR($B14<0,$C14<0),"Доля не может быть отрицательной",""))
A15: 11 | D15: =IF(AND($B15="",$C15=""),"",IF(OR($B15<0,$C15<0),"Доля не может быть отрицательной",""))
A16: 12 | D16: =IF(AND($B16="",$C16=""),"",IF(OR($B16<0,$C16<0),"Доля не может быть отрицательной",""))
... A40: 36 | D40: =IF(AND($B40="",$C40=""),"",IF(OR($B40<0,$C40<0),"Доля не может быть отрицательной",""))
A42: Итого | B42: =ROUND(SUM($B$5:$B$40),4) | C42: =ROUND(SUM($C$5:$C$40),4) | D42: =IF(AND(ROUND($B42,2)=100,ROUND($C42,2)=100),"Оба графика закрывают 100% объёма","Сумма долей не равна 100: расчёт закроет не весь договор")
A44: Горизонт расчёта — 36 месяцев. Если объект длиннее, укрупните шаг: считайте два месяца одной строкой. Если после расчёта на листе «Сравнение» строка «Начислено, но не поступило» больше нуля — деньги за последние акты приходят за горизонтом, и график стоит сдвинуть на несколько месяцев к началу.

Sheet Профиль А
A1: Кассовый профиль по объекту — сценарий А
A2: Здесь не заполняется ничего: всё считается из листов «Условия» и «График КС». Читать слева направо: сколько выполнено, сколько из этого удержали, сколько дошло до счёта, сколько потрачено и что осталось накопленным итогом. Колонка «Накопленный остаток» — это и есть ваши деньги в объекте: минус в ней означает, что объект финансируется вами.
A4: Месяц | B4: Выполнено за месяц, руб. | C4: Накопленный объём, руб. | D4: Накопленная доля, % | E4: Погашено аванса нарастающим, руб. | F4: Погашение аванса за месяц, руб. | G4: Гарантийное удержание за месяц, руб. | H4: Начислено к оплате за месяц, руб. | I4: Поступление аванса, руб. | J4: Оплата КС с отсрочкой, руб. | K4: Возврат гарантийного удержания, руб. | L4: Расходы за месяц, руб. | M4: Сальдо месяца, руб. | N4: Накопленный остаток, руб. | O4: Месяц в минусе | P4: Проверка
A5: 1 | B5: =ROUND(IFERROR('Условия'!$B$5*INDEX('График КС'!$B$5:$B$40,MATCH($A5,'График КС'!$A$5:$A$40,0))/100,0),2) | C5: =SUMIFS($B$5:$B$40,$A$5:$A$40,"<="&$A5) | D5: =SUMIFS('График КС'!$B$5:$B$40,'График КС'!$A$5:$A$40,"<="&$A5) | E5: =IF('Условия'!$B$25=0,0,IFERROR(MAX(0,MIN('Условия'!$B$23,IF('Условия'!$B$25=1,ROUND('Условия'!$B$23*$D5/'График КС'!$B$42,2),IF('Условия'!$B$25=2,IF($D5>='График КС'!$B$42,'Условия'!$B$23,0),ROUND('Условия'!$B$23*($D5-'Условия'!$B$9)/('График КС'!$B$42-'Условия'!$B$9),2))))),0)) | F5: =ROUND($E5,2) | G5: =ROUND($B5*'Условия'!$B$13/100,2) | H5: =ROUND($B5-$F5-$G5,2) | I5: =IF($A5='Условия'!$B$7,'Условия'!$B$23,0) | J5: =IFERROR(INDEX($H$5:$H$40,MATCH($A5-'Условия'!$B$17,$A$5:$A$40,0)),0) | K5: =IF(AND('Условия'!$B$14>0,$A5='Условия'!$B$14),ROUND(SUM($G$5:$G$40)*'Условия'!$B$15/100,2),0) | L5: =ROUND(SUMIFS($B$5:$B$40,$A$5:$A$40,"<="&($A5+'Условия'!$B$19))*'Условия'!$B$18/100,2)+IF($A5=1,'Условия'!$B$20,0)+IF($A5='Условия'!$B$12,'Условия'!$B$24,0) | M5: =ROUND($I5+$J5+$K5-$L5,2) | N5: =ROUND($M5,2) | O5: =IF($N5<0,$A5,"") | P5: =IF($H5<0,"Из КС этого месяца удерживают больше, чем она стоит: погашение аванса и гарантийное удержание вместе больше объёма",IF(AND($B5>0,'Условия'!$B$16<>"",$A5>'Условия'!$B$16),"Месяц за пределами срока объекта, а объём в графике есть",""))
A6: 2 | B6: =ROUND(IFERROR('Условия'!$B$5*INDEX('График КС'!$B$5:$B$40,MATCH($A6,'График КС'!$A$5:$A$40,0))/100,0),2) | C6: =SUMIFS($B$5:$B$40,$A$5:$A$40,"<="&$A6) | D6: =SUMIFS('График КС'!$B$5:$B$40,'График КС'!$A$5:$A$40,"<="&$A6) | E6: =IF('Условия'!$B$25=0,0,IFERROR(MAX(0,MIN('Условия'!$B$23,IF('Условия'!$B$25=1,ROUND('Условия'!$B$23*$D6/'График КС'!$B$42,2),IF('Условия'!$B$25=2,IF($D6>='График КС'!$B$42,'Условия'!$B$23,0),ROUND('Условия'!$B$23*($D6-'Условия'!$B$9)/('График КС'!$B$42-'Условия'!$B$9),2))))),0)) | F6: =ROUND($E6-$E5,2) | G6: =ROUND($B6*'Условия'!$B$13/100,2) | H6: =ROUND($B6-$F6-$G6,2) | I6: =IF($A6='Условия'!$B$7,'Условия'!$B$23,0) | J6: =IFERROR(INDEX($H$5:$H$40,MATCH($A6-'Условия'!$B$17,$A$5:$A$40,0)),0) | K6: =IF(AND('Условия'!$B$14>0,$A6='Условия'!$B$14),ROUND(SUM($G$5:$G$40)*'Условия'!$B$15/100,2),0) | L6: =ROUND(IFERROR(INDEX($B$5:$B$40,MATCH($A6+'Условия'!$B$19,$A$5:$A$40,0)),0)*'Условия'!$B$18/100,2)+IF($A6=1,'Условия'!$B$20,0)+IF($A6='Условия'!$B$12,'Условия'!$B$24,0) | M6: =ROUND($I6+$J6+$K6-$L6,2) | N6: =ROUND($N5+$M6,2) | O6: =IF($N6<0,$A6,"") | P6: =IF($H6<0,"Из КС этого месяца удерживают больше, чем она стоит: погашение аванса и гарантийное удержание вместе больше объёма",IF(AND($B6>0,'Условия'!$B$16<>"",$A6>'Условия'!$B$16),"Месяц за пределами срока объекта, а объём в графике есть",""))
A7: 3 | B7: =ROUND(IFERROR('Условия'!$B$5*INDEX('График КС'!$B$5:$B$40,MATCH($A7,'График КС'!$A$5:$A$40,0))/100,0),2) | C7: =SUMIFS($B$5:$B$40,$A$5:$A$40,"<="&$A7) | D7: =SUMIFS('График КС'!$B$5:$B$40,'График КС'!$A$5:$A$40,"<="&$A7) | E7: =IF('Условия'!$B$25=0,0,IFERROR(MAX(0,MIN('Условия'!$B$23,IF('Условия'!$B$25=1,ROUND('Условия'!$B$23*$D7/'График КС'!$B$42,2),IF('Условия'!$B$25=2,IF($D7>='График КС'!$B$42,'Условия'!$B$23,0),ROUND('Условия'!$B$23*($D7-'Условия'!$B$9)/('График КС'!$B$42-'Условия'!$B$9),2))))),0)) | F7: =ROUND($E7-$E6,2) | G7: =ROUND($B7*'Условия'!$B$13/100,2) | H7: =ROUND($B7-$F7-$G7,2) | I7: =IF($A7='Условия'!$B$7,'Условия'!$B$23,0) | J7: =IFERROR(INDEX($H$5:$H$40,MATCH($A7-'Условия'!$B$17,$A$5:$A$40,0)),0) | K7: =IF(AND('Условия'!$B$14>0,$A7='Условия'!$B$14),ROUND(SUM($G$5:$G$40)*'Условия'!$B$15/100,2),0) | L7: =ROUND(IFERROR(INDEX($B$5:$B$40,MATCH($A7+'Условия'!$B$19,$A$5:$A$40,0)),0)*'Условия'!$B$18/100,2)+IF($A7=1,'Условия'!$B$20,0)+IF($A7='Условия'!$B$12,'Условия'!$B$24,0) | M7: =ROUND($I7+$J7+$K7-$L7,2) | N7: =ROUND($N6+$M7,2) | O7: =IF($N7<0,$A7,"") | P7: =IF($H7<0,"Из КС этого месяца удерживают больше, чем она стоит: погашение аванса и гарантийное удержание вместе больше объёма",IF(AND($B7>0,'Условия'!$B$16<>"",$A7>'Условия'!$B$16),"Месяц за пределами срока объекта, а объём в графике есть",""))
A8: 4 | B8: =ROUND(IFERROR('Условия'!$B$5*INDEX('График КС'!$B$5:$B$40,MATCH($A8,'График КС'!$A$5:$A$40,0))/100,0),2) | C8: =SUMIFS($B$5:$B$40,$A$5:$A$40,"<="&$A8) | D8: =SUMIFS('График КС'!$B$5:$B$40,'График КС'!$A$5:$A$40,"<="&$A8) | E8: =IF('Условия'!$B$25=0,0,IFERROR(MAX(0,MIN('Условия'!$B$23,IF('Условия'!$B$25=1,ROUND('Условия'!$B$23*$D8/'График КС'!$B$42,2),IF('Условия'!$B$25=2,IF($D8>='График КС'!$B$42,'Условия'!$B$23,0),ROUND('Условия'!$B$23*($D8-'Условия'!$B$9)/('График КС'!$B$42-'Условия'!$B$9),2))))),0)) | F8: =ROUND($E8-$E7,2) | G8: =ROUND($B8*'Условия'!$B$13/100,2) | H8: =ROUND($B8-$F8-$G8,2) | I8: =IF($A8='Условия'!$B$7,'Условия'!$B$23,0) | J8: =IFERROR(INDEX($H$5:$H$40,MATCH($A8-'Условия'!$B$17,$A$5:$A$40,0)),0) | K8: =IF(AND('Условия'!$B$14>0,$A8='Условия'!$B$14),ROUND(SUM($G$5:$G$40)*'Условия'!$B$15/100,2),0) | L8: =ROUND(IFERROR(INDEX($B$5:$B$40,MATCH($A8+'Условия'!$B$19,$A$5:$A$40,0)),0)*'Условия'!$B$18/100,2)+IF($A8=1,'Условия'!$B$20,0)+IF($A8='Условия'!$B$12,'Условия'!$B$24,0) | M8: =ROUND($I8+$J8+$K8-$L8,2) | N8: =ROUND($N7+$M8,2) | O8: =IF($N8<0,$A8,"") | P8: =IF($H8<0,"Из КС этого месяца удерживают больше, чем она стоит: погашение аванса и гарантийное удержание вместе больше объёма",IF(AND($B8>0,'Условия'!$B$16<>"",$A8>'Условия'!$B$16),"Месяц за пределами срока объекта, а объём в графике есть",""))
A9: 5 | B9: =ROUND(IFERROR('Условия'!$B$5*INDEX('График КС'!$B$5:$B$40,MATCH($A9,'График КС'!$A$5:$A$40,0))/100,0),2) | C9: =SUMIFS($B$5:$B$40,$A$5:$A$40,"<="&$A9) | D9: =SUMIFS('График КС'!$B$5:$B$40,'График КС'!$A$5:$A$40,"<="&$A9) | E9: =IF('Условия'!$B$25=0,0,IFERROR(MAX(0,MIN('Условия'!$B$23,IF('Условия'!$B$25=1,ROUND('Условия'!$B$23*$D9/'График КС'!$B$42,2),IF('Условия'!$B$25=2,IF($D9>='График КС'!$B$42,'Условия'!$B$23,0),ROUND('Условия'!$B$23*($D9-'Условия'!$B$9)/('График КС'!$B$42-'Условия'!$B$9),2))))),0)) | F9: =ROUND($E9-$E8,2) | G9: =ROUND($B9*'Условия'!$B$13/100,2) | H9: =ROUND($B9-$F9-$G9,2) | I9: =IF($A9='Условия'!$B$7,'Условия'!$B$23,0) | J9: =IFERROR(INDEX($H$5:$H$40,MATCH($A9-'Условия'!$B$17,$A$5:$A$40,0)),0) | K9: =IF(AND('Условия'!$B$14>0,$A9='Условия'!$B$14),ROUND(SUM($G$5:$G$40)*'Условия'!$B$15/100,2),0) | L9: =ROUND(IFERROR(INDEX($B$5:$B$40,MATCH($A9+'Условия'!$B$19,$A$5:$A$40,0)),0)*'Условия'!$B$18/100,2)+IF($A9=1,'Условия'!$B$20,0)+IF($A9='Условия'!$B$12,'Условия'!$B$24,0) | M9: =ROUND($I9+$J9+$K9-$L9,2) | N9: =ROUND($N8+$M9,2) | O9: =IF($N9<0,$A9,"") | P9: =IF($H9<0,"Из КС этого месяца удерживают больше, чем она стоит: погашение аванса и гарантийное удержание вместе больше объёма",IF(AND($B9>0,'Условия'!$B$16<>"",$A9>'Условия'!$B$16),"Месяц за пределами срока объекта, а объём в графике есть",""))
A10: 6 | B10: =ROUND(IFERROR('Условия'!$B$5*INDEX('График КС'!$B$5:$B$40,MATCH($A10,'График КС'!$A$5:$A$40,0))/100,0),2) | C10: =SUMIFS($B$5:$B$40,$A$5:$A$40,"<="&$A10) | D10: =SUMIFS('График КС'!$B$5:$B$40,'График КС'!$A$5:$A$40,"<="&$A10) | E10: =IF('Условия'!$B$25=0,0,IFERROR(MAX(0,MIN('Условия'!$B$23,IF('Условия'!$B$25=1,ROUND('Условия'!$B$23*$D10/'График КС'!$B$42,2),IF('Условия'!$B$25=2,IF($D10>='График КС'!$B$42,'Условия'!$B$23,0),ROUND('Условия'!$B$23*($D10-'Условия'!$B$9)/('График КС'!$B$42-'Условия'!$B$9),2))))),0)) | F10: =ROUND($E10-$E9,2) | G10: =ROUND($B10*'Условия'!$B$13/100,2) | H10: =ROUND($B10-$F10-$G10,2) | I10: =IF($A10='Условия'!$B$7,'Условия'!$B$23,0) | J10: =IFERROR(INDEX($H$5:$H$40,MATCH($A10-'Условия'!$B$17,$A$5:$A$40,0)),0) | K10: =IF(AND('Условия'!$B$14>0,$A10='Условия'!$B$14),ROUND(SUM($G$5:$G$40)*'Условия'!$B$15/100,2),0) | L10: =ROUND(IFERROR(INDEX($B$5:$B$40,MATCH($A10+'Условия'!$B$19,$A$5:$A$40,0)),0)*'Условия'!$B$18/100,2)+IF($A10=1,'Условия'!$B$20,0)+IF($A10='Условия'!$B$12,'Условия'!$B$24,0) | M10: =ROUND($I10+$J10+$K10-$L10,2) | N10: =ROUND($N9+$M10,2) | O10: =IF($N10<0,$A10,"") | P10: =IF($H10<0,"Из КС этого месяца удерживают больше, чем она стоит: погашение аванса и гарантийное удержание вместе больше объёма",IF(AND($B10>0,'Условия'!$B$16<>"",$A10>'Условия'!$B$16),"Месяц за пределами срока объекта, а объём в графике есть",""))
A11: 7 | B11: =ROUND(IFERROR('Условия'!$B$5*INDEX('График КС'!$B$5:$B$40,MATCH($A11,'График КС'!$A$5:$A$40,0))/100,0),2) | C11: =SUMIFS($B$5:$B$40,$A$5:$A$40,"<="&$A11) | D11: =SUMIFS('График КС'!$B$5:$B$40,'График КС'!$A$5:$A$40,"<="&$A11) | E11: =IF('Условия'!$B$25=0,0,IFERROR(MAX(0,MIN('Условия'!$B$23,IF('Условия'!$B$25=1,ROUND('Условия'!$B$23*$D11/'График КС'!$B$42,2),IF('Условия'!$B$25=2,IF($D11>='График КС'!$B$42,'Условия'!$B$23,0),ROUND('Условия'!$B$23*($D11-'Условия'!$B$9)/('График КС'!$B$42-'Условия'!$B$9),2))))),0)) | F11: =ROUND($E11-$E10,2) | G11: =ROUND($B11*'Условия'!$B$13/100,2) | H11: =ROUND($B11-$F11-$G11,2) | I11: =IF($A11='Условия'!$B$7,'Условия'!$B$23,0) | J11: =IFERROR(INDEX($H$5:$H$40,MATCH($A11-'Условия'!$B$17,$A$5:$A$40,0)),0) | K11: =IF(AND('Условия'!$B$14>0,$A11='Условия'!$B$14),ROUND(SUM($G$5:$G$40)*'Условия'!$B$15/100,2),0) | L11: =ROUND(IFERROR(INDEX($B$5:$B$40,MATCH($A11+'Условия'!$B$19,$A$5:$A$40,0)),0)*'Условия'!$B$18/100,2)+IF($A11=1,'Условия'!$B$20,0)+IF($A11='Условия'!$B$12,'Условия'!$B$24,0) | M11: =ROUND($I11+$J11+$K11-$L11,2) | N11: =ROUND($N10+$M11,2) | O11: =IF($N11<0,$A11,"") | P11: =IF($H11<0,"Из КС этого месяца удерживают больше, чем она стоит: погашение аванса и гарантийное удержание вместе больше объёма",IF(AND($B11>0,'Условия'!$B$16<>"",$A11>'Условия'!$B$16),"Месяц за пределами срока объекта, а объём в графике есть",""))
A12: 8 | B12: =ROUND(IFERROR('Условия'!$B$5*INDEX('График КС'!$B$5:$B$40,MATCH($A12,'График КС'!$A$5:$A$40,0))/100,0),2) | C12: =SUMIFS($B$5:$B$40,$A$5:$A$40,"<="&$A12) | D12: =SUMIFS('График КС'!$B$5:$B$40,'График КС'!$A$5:$A$40,"<="&$A12) | E12: =IF('Условия'!$B$25=0,0,IFERROR(MAX(0,MIN('Условия'!$B$23,IF('Условия'!$B$25=1,ROUND('Условия'!$B$23*$D12/'График КС'!$B$42,2),IF('Условия'!$B$25=2,IF($D12>='График КС'!$B$42,'Условия'!$B$23,0),ROUND('Условия'!$B$23*($D12-'Условия'!$B$9)/('График КС'!$B$42-'Условия'!$B$9),2))))),0)) | F12: =ROUND($E12-$E11,2) | G12: =ROUND($B12*'Условия'!$B$13/100,2) | H12: =ROUND($B12-$F12-$G12,2) | I12: =IF($A12='Условия'!$B$7,'Условия'!$B$23,0) | J12: =IFERROR(INDEX($H$5:$H$40,MATCH($A12-'Условия'!$B$17,$A$5:$A$40,0)),0) | K12: =IF(AND('Условия'!$B$14>0,$A12='Условия'!$B$14),ROUND(SUM($G$5:$G$40)*'Условия'!$B$15/100,2),0) | L12: =ROUND(IFERROR(INDEX($B$5:$B$40,MATCH($A12+'Условия'!$B$19,$A$5:$A$40,0)),0)*'Условия'!$B$18/100,2)+IF($A12=1,'Условия'!$B$20,0)+IF($A12='Условия'!$B$12,'Условия'!$B$24,0) | M12: =ROUND($I12+$J12+$K12-$L12,2) | N12: =ROUND($N11+$M12,2) | O12: =IF($N12<0,$A12,"") | P12: =IF($H12<0,"Из КС этого месяца удерживают больше, чем она стоит: погашение аванса и гарантийное удержание вместе больше объёма",IF(AND($B12>0,'Условия'!$B$16<>"",$A12>'Условия'!$B$16),"Месяц за пределами срока объекта, а объём в графике есть",""))
A13: 9 | B13: =ROUND(IFERROR('Условия'!$B$5*INDEX('График КС'!$B$5:$B$40,MATCH($A13,'График КС'!$A$5:$A$40,0))/100,0),2) | C13: =SUMIFS($B$5:$B$40,$A$5:$A$40,"<="&$A13) | D13: =SUMIFS('График КС'!$B$5:$B$40,'График КС'!$A$5:$A$40,"<="&$A13) | E13: =IF('Условия'!$B$25=0,0,IFERROR(MAX(0,MIN('Условия'!$B$23,IF('Условия'!$B$25=1,ROUND('Условия'!$B$23*$D13/'График КС'!$B$42,2),IF('Условия'!$B$25=2,IF($D13>='График КС'!$B$42,'Условия'!$B$23,0),ROUND('Условия'!$B$23*($D13-'Условия'!$B$9)/('График КС'!$B$42-'Условия'!$B$9),2))))),0)) | F13: =ROUND($E13-$E12,2) | G13: =ROUND($B13*'Условия'!$B$13/100,2) | H13: =ROUND($B13-$F13-$G13,2) | I13: =IF($A13='Условия'!$B$7,'Условия'!$B$23,0) | J13: =IFERROR(INDEX($H$5:$H$40,MATCH($A13-'Условия'!$B$17,$A$5:$A$40,0)),0) | K13: =IF(AND('Условия'!$B$14>0,$A13='Условия'!$B$14),ROUND(SUM($G$5:$G$40)*'Условия'!$B$15/100,2),0) | L13: =ROUND(IFERROR(INDEX($B$5:$B$40,MATCH($A13+'Условия'!$B$19,$A$5:$A$40,0)),0)*'Условия'!$B$18/100,2)+IF($A13=1,'Условия'!$B$20,0)+IF($A13='Условия'!$B$12,'Условия'!$B$24,0) | M13: =ROUND($I13+$J13+$K13-$L13,2) | N13: =ROUND($N12+$M13,2) | O13: =IF($N13<0,$A13,"") | P13: =IF($H13<0,"Из КС этого месяца удерживают больше, чем она стоит: погашение аванса и гарантийное удержание вместе больше объёма",IF(AND($B13>0,'Условия'!$B$16<>"",$A13>'Условия'!$B$16),"Месяц за пределами срока объекта, а объём в графике есть",""))
A14: 10 | B14: =ROUND(IFERROR('Условия'!$B$5*INDEX('График КС'!$B$5:$B$40,MATCH($A14,'График КС'!$A$5:$A$40,0))/100,0),2) | C14: =SUMIFS($B$5:$B$40,$A$5:$A$40,"<="&$A14) | D14: =SUMIFS('График КС'!$B$5:$B$40,'График КС'!$A$5:$A$40,"<="&$A14) | E14: =IF('Условия'!$B$25=0,0,IFERROR(MAX(0,MIN('Условия'!$B$23,IF('Условия'!$B$25=1,ROUND('Условия'!$B$23*$D14/'График КС'!$B$42,2),IF('Условия'!$B$25=2,IF($D14>='График КС'!$B$42,'Условия'!$B$23,0),ROUND('Условия'!$B$23*($D14-'Условия'!$B$9)/('График КС'!$B$42-'Условия'!$B$9),2))))),0)) | F14: =ROUND($E14-$E13,2) | G14: =ROUND($B14*'Условия'!$B$13/100,2) | H14: =ROUND($B14-$F14-$G14,2) | I14: =IF($A14='Условия'!$B$7,'Условия'!$B$23,0) | J14: =IFERROR(INDEX($H$5:$H$40,MATCH($A14-'Условия'!$B$17,$A$5:$A$40,0)),0) | K14: =IF(AND('Условия'!$B$14>0,$A14='Условия'!$B$14),ROUND(SUM($G$5:$G$40)*'Условия'!$B$15/100,2),0) | L14: =ROUND(IFERROR(INDEX($B$5:$B$40,MATCH($A14+'Условия'!$B$19,$A$5:$A$40,0)),0)*'Условия'!$B$18/100,2)+IF($A14=1,'Условия'!$B$20,0)+IF($A14='Условия'!$B$12,'Условия'!$B$24,0) | M14: =ROUND($I14+$J14+$K14-$L14,2) | N14: =ROUND($N13+$M14,2) | O14: =IF($N14<0,$A14,"") | P14: =IF($H14<0,"Из КС этого месяца удерживают больше, чем она стоит: погашение аванса и гарантийное удержание вместе больше объёма",IF(AND($B14>0,'Условия'!$B$16<>"",$A14>'Условия'!$B$16),"Месяц за пределами срока объекта, а объём в графике есть",""))
A15: 11 | B15: =ROUND(IFERROR('Условия'!$B$5*INDEX('График КС'!$B$5:$B$40,MATCH($A15,'График КС'!$A$5:$A$40,0))/100,0),2) | C15: =SUMIFS($B$5:$B$40,$A$5:$A$40,"<="&$A15) | D15: =SUMIFS('График КС'!$B$5:$B$40,'График КС'!$A$5:$A$40,"<="&$A15) | E15: =IF('Условия'!$B$25=0,0,IFERROR(MAX(0,MIN('Условия'!$B$23,IF('Условия'!$B$25=1,ROUND('Условия'!$B$23*$D15/'График КС'!$B$42,2),IF('Условия'!$B$25=2,IF($D15>='График КС'!$B$42,'Условия'!$B$23,0),ROUND('Условия'!$B$23*($D15-'Условия'!$B$9)/('График КС'!$B$42-'Условия'!$B$9),2))))),0)) | F15: =ROUND($E15-$E14,2) | G15: =ROUND($B15*'Условия'!$B$13/100,2) | H15: =ROUND($B15-$F15-$G15,2) | I15: =IF($A15='Условия'!$B$7,'Условия'!$B$23,0) | J15: =IFERROR(INDEX($H$5:$H$40,MATCH($A15-'Условия'!$B$17,$A$5:$A$40,0)),0) | K15: =IF(AND('Условия'!$B$14>0,$A15='Условия'!$B$14),ROUND(SUM($G$5:$G$40)*'Условия'!$B$15/100,2),0) | L15: =ROUND(IFERROR(INDEX($B$5:$B$40,MATCH($A15+'Условия'!$B$19,$A$5:$A$40,0)),0)*'Условия'!$B$18/100,2)+IF($A15=1,'Условия'!$B$20,0)+IF($A15='Условия'!$B$12,'Условия'!$B$24,0) | M15: =ROUND($I15+$J15+$K15-$L15,2) | N15: =ROUND($N14+$M15,2) | O15: =IF($N15<0,$A15,"") | P15: =IF($H15<0,"Из КС этого месяца удерживают больше, чем она стоит: погашение аванса и гарантийное удержание вместе больше объёма",IF(AND($B15>0,'Условия'!$B$16<>"",$A15>'Условия'!$B$16),"Месяц за пределами срока объекта, а объём в графике есть",""))
A16: 12 | B16: =ROUND(IFERROR('Условия'!$B$5*INDEX('График КС'!$B$5:$B$40,MATCH($A16,'График КС'!$A$5:$A$40,0))/100,0),2) | C16: =SUMIFS($B$5:$B$40,$A$5:$A$40,"<="&$A16) | D16: =SUMIFS('График КС'!$B$5:$B$40,'График КС'!$A$5:$A$40,"<="&$A16) | E16: =IF('Условия'!$B$25=0,0,IFERROR(MAX(0,MIN('Условия'!$B$23,IF('Условия'!$B$25=1,ROUND('Условия'!$B$23*$D16/'График КС'!$B$42,2),IF('Условия'!$B$25=2,IF($D16>='График КС'!$B$42,'Условия'!$B$23,0),ROUND('Условия'!$B$23*($D16-'Условия'!$B$9)/('График КС'!$B$42-'Условия'!$B$9),2))))),0)) | F16: =ROUND($E16-$E15,2) | G16: =ROUND($B16*'Условия'!$B$13/100,2) | H16: =ROUND($B16-$F16-$G16,2) | I16: =IF($A16='Условия'!$B$7,'Условия'!$B$23,0) | J16: =IFERROR(INDEX($H$5:$H$40,MATCH($A16-'Условия'!$B$17,$A$5:$A$40,0)),0) | K16: =IF(AND('Условия'!$B$14>0,$A16='Условия'!$B$14),ROUND(SUM($G$5:$G$40)*'Условия'!$B$15/100,2),0) | L16: =ROUND(IFERROR(INDEX($B$5:$B$40,MATCH($A16+'Условия'!$B$19,$A$5:$A$40,0)),0)*'Условия'!$B$18/100,2)+IF($A16=1,'Условия'!$B$20,0)+IF($A16='Условия'!$B$12,'Условия'!$B$24,0) | M16: =ROUND($I16+$J16+$K16-$L16,2) | N16: =ROUND($N15+$M16,2) | O16: =IF($N16<0,$A16,"") | P16: =IF($H16<0,"Из КС этого месяца удерживают больше, чем она стоит: погашение аванса и гарантийное удержание вместе больше объёма",IF(AND($B16>0,'Условия'!$B$16<>"",$A16>'Условия'!$B$16),"Месяц за пределами срока объекта, а объём в графике есть",""))
A17: 13 | B17: =ROUND(IFERROR('Условия'!$B$5*INDEX('График КС'!$B$5:$B$40,MATCH($A17,'График КС'!$A$5:$A$40,0))/100,0),2) | C17: =SUMIFS($B$5:$B$40,$A$5:$A$40,"<="&$A17) | D17: =SUMIFS('График КС'!$B$5:$B$40,'График КС'!$A$5:$A$40,"<="&$A17) | E17: =IF('Условия'!$B$25=0,0,IFERROR(MAX(0,MIN('Условия'!$B$23,IF('Условия'!$B$25=1,ROUND('Условия'!$B$23*$D17/'График КС'!$B$42,2),IF('Условия'!$B$25=2,IF($D17>='График КС'!$B$42,'Условия'!$B$23,0),ROUND('Условия'!$B$23*($D17-'Условия'!$B$9)/('График КС'!$B$42-'Условия'!$B$9),2))))),0)) | F17: =ROUND($E17-$E16,2) | G17: =ROUND($B17*'Условия'!$B$13/100,2) | H17: =ROUND($B17-$F17-$G17,2) | I17: =IF($A17='Условия'!$B$7,'Условия'!$B$23,0) | J17: =IFERROR(INDEX($H$5:$H$40,MATCH($A17-'Условия'!$B$17,$A$5:$A$40,0)),0) | K17: =IF(AND('Условия'!$B$14>0,$A17='Условия'!$B$14),ROUND(SUM($G$5:$G$40)*'Условия'!$B$15/100,2),0) | L17: =ROUND(IFERROR(INDEX($B$5:$B$40,MATCH($A17+'Условия'!$B$19,$A$5:$A$40,0)),0)*'Условия'!$B$18/100,2)+IF($A17=1,'Условия'!$B$20,0)+IF($A17='Условия'!$B$12,'Условия'!$B$24,0) | M17: =ROUND($I17+$J17+$K17-$L17,2) | N17: =ROUND($N16+$M17,2) | O17: =IF($N17<0,$A17,"") | P17: =IF($H17<0,"Из КС этого месяца удерживают больше, чем она стоит: погашение аванса и гарантийное удержание вместе больше объёма",IF(AND($B17>0,'Условия'!$B$16<>"",$A17>'Условия'!$B$16),"Месяц за пределами срока объекта, а объём в графике есть",""))
... A40: 36 | B40: =ROUND(IFERROR('Условия'!$B$5*INDEX('График КС'!$B$5:$B$40,MATCH($A40,'График КС'!$A$5:$A$40,0))/100,0),2) | C40: =SUMIFS($B$5:$B$40,$A$5:$A$40,"<="&$A40) | D40: =SUMIFS('График КС'!$B$5:$B$40,'График КС'!$A$5:$A$40,"<="&$A40) | E40: =IF('Условия'!$B$25=0,0,IFERROR(MAX(0,MIN('Условия'!$B$23,IF('Условия'!$B$25=1,ROUND('Условия'!$B$23*$D40/'График КС'!$B$42,2),IF('Условия'!$B$25=2,IF($D40>='График КС'!$B$42,'Условия'!$B$23,0),ROUND('Условия'!$B$23*($D40-'Условия'!$B$9)/('График КС'!$B$42-'Условия'!$B$9),2))))),0)) | F40: =ROUND($E40-$E39,2) | G40: =ROUND($B40*'Условия'!$B$13/100,2) | H40: =ROUND($B40-$F40-$G40,2) | I40: =IF($A40='Условия'!$B$7,'Условия'!$B$23,0) | J40: =IFERROR(INDEX($H$5:$H$40,MATCH($A40-'Условия'!$B$17,$A$5:$A$40,0)),0) | K40: =IF(AND('Условия'!$B$14>0,$A40='Условия'!$B$14),ROUND(SUM($G$5:$G$40)*'Условия'!$B$15/100,2),0) | L40: =ROUND(IFERROR(INDEX($B$5:$B$40,MATCH($A40+'Условия'!$B$19,$A$5:$A$40,0)),0)*'Условия'!$B$18/100,2)+IF($A40=1,'Условия'!$B$20,0)+IF($A40='Условия'!$B$12,'Условия'!$B$24,0) | M40: =ROUND($I40+$J40+$K40-$L40,2) | N40: =ROUND($N39+$M40,2) | O40: =IF($N40<0,$A40,"") | P40: =IF($H40<0,"Из КС этого месяца удерживают больше, чем она стоит: погашение аванса и гарантийное удержание вместе больше объёма",IF(AND($B40>0,'Условия'!$B$16<>"",$A40>'Условия'!$B$16),"Месяц за пределами срока объекта, а объём в графике есть",""))
A42: Итого | B42: =ROUND(SUM($B$5:$B$40),2) | F42: =ROUND(SUM($F$5:$F$40),2) | G42: =ROUND(SUM($G$5:$G$40),2) | H42: =ROUND(SUM($H$5:$H$40),2) | I42: =ROUND(SUM($I$5:$I$40),2) | J42: =ROUND(SUM($J$5:$J$40),2) | K42: =ROUND(SUM($K$5:$K$40),2) | L42: =ROUND(SUM($L$5:$L$40),2) | M42: =ROUND(SUM($M$5:$M$40),2) | N42: =$N$40 | P42: Итог колонки «Накопленный остаток» — это остаток последнего месяца, а не сумма колонки.

Sheet Профиль Б
A1: Кассовый профиль по объекту — сценарий Б
A2: Здесь не заполняется ничего: всё считается из листов «Условия» и «График КС». Читать слева направо: сколько выполнено, сколько из этого удержали, сколько дошло до счёта, сколько потрачено и что осталось накопленным итогом. Колонка «Накопленный остаток» — это и есть ваши деньги в объекте: минус в ней означает, что объект финансируется вами.
A4: Месяц | B4: Выполнено за месяц, руб. | C4: Накопленный объём, руб. | D4: Накопленная доля, % | E4: Погашено аванса нарастающим, руб. | F4: Погашение аванса за месяц, руб. | G4: Гарантийное удержание за месяц, руб. | H4: Начислено к оплате за месяц, руб. | I4: Поступление аванса, руб. | J4: Оплата КС с отсрочкой, руб. | K4: Возврат гарантийного удержания, руб. | L4: Расходы за месяц, руб. | M4: Сальдо месяца, руб. | N4: Накопленный остаток, руб. | O4: Месяц в минусе | P4: Проверка
A5: 1 | B5: =ROUND(IFERROR('Условия'!$C$5*INDEX('График КС'!$C$5:$C$40,MATCH($A5,'График КС'!$A$5:$A$40,0))/100,0),2) | C5: =SUMIFS($B$5:$B$40,$A$5:$A$40,"<="&$A5) | D5: =SUMIFS('График КС'!$C$5:$C$40,'График КС'!$A$5:$A$40,"<="&$A5) | E5: =IF('Условия'!$C$25=0,0,IFERROR(MAX(0,MIN('Условия'!$C$23,IF('Условия'!$C$25=1,ROUND('Условия'!$C$23*$D5/'График КС'!$C$42,2),IF('Условия'!$C$25=2,IF($D5>='График КС'!$C$42,'Условия'!$C$23,0),ROUND('Условия'!$C$23*($D5-'Условия'!$C$9)/('График КС'!$C$42-'Условия'!$C$9),2))))),0)) | F5: =ROUND($E5,2) | G5: =ROUND($B5*'Условия'!$C$13/100,2) | H5: =ROUND($B5-$F5-$G5,2) | I5: =IF($A5='Условия'!$C$7,'Условия'!$C$23,0) | J5: =IFERROR(INDEX($H$5:$H$40,MATCH($A5-'Условия'!$C$17,$A$5:$A$40,0)),0) | K5: =IF(AND('Условия'!$C$14>0,$A5='Условия'!$C$14),ROUND(SUM($G$5:$G$40)*'Условия'!$C$15/100,2),0) | L5: =ROUND(SUMIFS($B$5:$B$40,$A$5:$A$40,"<="&($A5+'Условия'!$C$19))*'Условия'!$C$18/100,2)+IF($A5=1,'Условия'!$C$20,0)+IF($A5='Условия'!$C$12,'Условия'!$C$24,0) | M5: =ROUND($I5+$J5+$K5-$L5,2) | N5: =ROUND($M5,2) | O5: =IF($N5<0,$A5,"") | P5: =IF($H5<0,"Из КС этого месяца удерживают больше, чем она стоит: погашение аванса и гарантийное удержание вместе больше объёма",IF(AND($B5>0,'Условия'!$C$16<>"",$A5>'Условия'!$C$16),"Месяц за пределами срока объекта, а объём в графике есть",""))
A6: 2 | B6: =ROUND(IFERROR('Условия'!$C$5*INDEX('График КС'!$C$5:$C$40,MATCH($A6,'График КС'!$A$5:$A$40,0))/100,0),2) | C6: =SUMIFS($B$5:$B$40,$A$5:$A$40,"<="&$A6) | D6: =SUMIFS('График КС'!$C$5:$C$40,'График КС'!$A$5:$A$40,"<="&$A6) | E6: =IF('Условия'!$C$25=0,0,IFERROR(MAX(0,MIN('Условия'!$C$23,IF('Условия'!$C$25=1,ROUND('Условия'!$C$23*$D6/'График КС'!$C$42,2),IF('Условия'!$C$25=2,IF($D6>='График КС'!$C$42,'Условия'!$C$23,0),ROUND('Условия'!$C$23*($D6-'Условия'!$C$9)/('График КС'!$C$42-'Условия'!$C$9),2))))),0)) | F6: =ROUND($E6-$E5,2) | G6: =ROUND($B6*'Условия'!$C$13/100,2) | H6: =ROUND($B6-$F6-$G6,2) | I6: =IF($A6='Условия'!$C$7,'Условия'!$C$23,0) | J6: =IFERROR(INDEX($H$5:$H$40,MATCH($A6-'Условия'!$C$17,$A$5:$A$40,0)),0) | K6: =IF(AND('Условия'!$C$14>0,$A6='Условия'!$C$14),ROUND(SUM($G$5:$G$40)*'Условия'!$C$15/100,2),0) | L6: =ROUND(IFERROR(INDEX($B$5:$B$40,MATCH($A6+'Условия'!$C$19,$A$5:$A$40,0)),0)*'Условия'!$C$18/100,2)+IF($A6=1,'Условия'!$C$20,0)+IF($A6='Условия'!$C$12,'Условия'!$C$24,0) | M6: =ROUND($I6+$J6+$K6-$L6,2) | N6: =ROUND($N5+$M6,2) | O6: =IF($N6<0,$A6,"") | P6: =IF($H6<0,"Из КС этого месяца удерживают больше, чем она стоит: погашение аванса и гарантийное удержание вместе больше объёма",IF(AND($B6>0,'Условия'!$C$16<>"",$A6>'Условия'!$C$16),"Месяц за пределами срока объекта, а объём в графике есть",""))
A7: 3 | B7: =ROUND(IFERROR('Условия'!$C$5*INDEX('График КС'!$C$5:$C$40,MATCH($A7,'График КС'!$A$5:$A$40,0))/100,0),2) | C7: =SUMIFS($B$5:$B$40,$A$5:$A$40,"<="&$A7) | D7: =SUMIFS('График КС'!$C$5:$C$40,'График КС'!$A$5:$A$40,"<="&$A7) | E7: =IF('Условия'!$C$25=0,0,IFERROR(MAX(0,MIN('Условия'!$C$23,IF('Условия'!$C$25=1,ROUND('Условия'!$C$23*$D7/'График КС'!$C$42,2),IF('Условия'!$C$25=2,IF($D7>='График КС'!$C$42,'Условия'!$C$23,0),ROUND('Условия'!$C$23*($D7-'Условия'!$C$9)/('График КС'!$C$42-'Условия'!$C$9),2))))),0)) | F7: =ROUND($E7-$E6,2) | G7: =ROUND($B7*'Условия'!$C$13/100,2) | H7: =ROUND($B7-$F7-$G7,2) | I7: =IF($A7='Условия'!$C$7,'Условия'!$C$23,0) | J7: =IFERROR(INDEX($H$5:$H$40,MATCH($A7-'Условия'!$C$17,$A$5:$A$40,0)),0) | K7: =IF(AND('Условия'!$C$14>0,$A7='Условия'!$C$14),ROUND(SUM($G$5:$G$40)*'Условия'!$C$15/100,2),0) | L7: =ROUND(IFERROR(INDEX($B$5:$B$40,MATCH($A7+'Условия'!$C$19,$A$5:$A$40,0)),0)*'Условия'!$C$18/100,2)+IF($A7=1,'Условия'!$C$20,0)+IF($A7='Условия'!$C$12,'Условия'!$C$24,0) | M7: =ROUND($I7+$J7+$K7-$L7,2) | N7: =ROUND($N6+$M7,2) | O7: =IF($N7<0,$A7,"") | P7: =IF($H7<0,"Из КС этого месяца удерживают больше, чем она стоит: погашение аванса и гарантийное удержание вместе больше объёма",IF(AND($B7>0,'Условия'!$C$16<>"",$A7>'Условия'!$C$16),"Месяц за пределами срока объекта, а объём в графике есть",""))
A8: 4 | B8: =ROUND(IFERROR('Условия'!$C$5*INDEX('График КС'!$C$5:$C$40,MATCH($A8,'График КС'!$A$5:$A$40,0))/100,0),2) | C8: =SUMIFS($B$5:$B$40,$A$5:$A$40,"<="&$A8) | D8: =SUMIFS('График КС'!$C$5:$C$40,'График КС'!$A$5:$A$40,"<="&$A8) | E8: =IF('Условия'!$C$25=0,0,IFERROR(MAX(0,MIN('Условия'!$C$23,IF('Условия'!$C$25=1,ROUND('Условия'!$C$23*$D8/'График КС'!$C$42,2),IF('Условия'!$C$25=2,IF($D8>='График КС'!$C$42,'Условия'!$C$23,0),ROUND('Условия'!$C$23*($D8-'Условия'!$C$9)/('График КС'!$C$42-'Условия'!$C$9),2))))),0)) | F8: =ROUND($E8-$E7,2) | G8: =ROUND($B8*'Условия'!$C$13/100,2) | H8: =ROUND($B8-$F8-$G8,2) | I8: =IF($A8='Условия'!$C$7,'Условия'!$C$23,0) | J8: =IFERROR(INDEX($H$5:$H$40,MATCH($A8-'Условия'!$C$17,$A$5:$A$40,0)),0) | K8: =IF(AND('Условия'!$C$14>0,$A8='Условия'!$C$14),ROUND(SUM($G$5:$G$40)*'Условия'!$C$15/100,2),0) | L8: =ROUND(IFERROR(INDEX($B$5:$B$40,MATCH($A8+'Условия'!$C$19,$A$5:$A$40,0)),0)*'Условия'!$C$18/100,2)+IF($A8=1,'Условия'!$C$20,0)+IF($A8='Условия'!$C$12,'Условия'!$C$24,0) | M8: =ROUND($I8+$J8+$K8-$L8,2) | N8: =ROUND($N7+$M8,2) | O8: =IF($N8<0,$A8,"") | P8: =IF($H8<0,"Из КС этого месяца удерживают больше, чем она стоит: погашение аванса и гарантийное удержание вместе больше объёма",IF(AND($B8>0,'Условия'!$C$16<>"",$A8>'Условия'!$C$16),"Месяц за пределами срока объекта, а объём в графике есть",""))
A9: 5 | B9: =ROUND(IFERROR('Условия'!$C$5*INDEX('График КС'!$C$5:$C$40,MATCH($A9,'График КС'!$A$5:$A$40,0))/100,0),2) | C9: =SUMIFS($B$5:$B$40,$A$5:$A$40,"<="&$A9) | D9: =SUMIFS('График КС'!$C$5:$C$40,'График КС'!$A$5:$A$40,"<="&$A9) | E9: =IF('Условия'!$C$25=0,0,IFERROR(MAX(0,MIN('Условия'!$C$23,IF('Условия'!$C$25=1,ROUND('Условия'!$C$23*$D9/'График КС'!$C$42,2),IF('Условия'!$C$25=2,IF($D9>='График КС'!$C$42,'Условия'!$C$23,0),ROUND('Условия'!$C$23*($D9-'Условия'!$C$9)/('График КС'!$C$42-'Условия'!$C$9),2))))),0)) | F9: =ROUND($E9-$E8,2) | G9: =ROUND($B9*'Условия'!$C$13/100,2) | H9: =ROUND($B9-$F9-$G9,2) | I9: =IF($A9='Условия'!$C$7,'Условия'!$C$23,0) | J9: =IFERROR(INDEX($H$5:$H$40,MATCH($A9-'Условия'!$C$17,$A$5:$A$40,0)),0) | K9: =IF(AND('Условия'!$C$14>0,$A9='Условия'!$C$14),ROUND(SUM($G$5:$G$40)*'Условия'!$C$15/100,2),0) | L9: =ROUND(IFERROR(INDEX($B$5:$B$40,MATCH($A9+'Условия'!$C$19,$A$5:$A$40,0)),0)*'Условия'!$C$18/100,2)+IF($A9=1,'Условия'!$C$20,0)+IF($A9='Условия'!$C$12,'Условия'!$C$24,0) | M9: =ROUND($I9+$J9+$K9-$L9,2) | N9: =ROUND($N8+$M9,2) | O9: =IF($N9<0,$A9,"") | P9: =IF($H9<0,"Из КС этого месяца удерживают больше, чем она стоит: погашение аванса и гарантийное удержание вместе больше объёма",IF(AND($B9>0,'Условия'!$C$16<>"",$A9>'Условия'!$C$16),"Месяц за пределами срока объекта, а объём в графике есть",""))
A10: 6 | B10: =ROUND(IFERROR('Условия'!$C$5*INDEX('График КС'!$C$5:$C$40,MATCH($A10,'График КС'!$A$5:$A$40,0))/100,0),2) | C10: =SUMIFS($B$5:$B$40,$A$5:$A$40,"<="&$A10) | D10: =SUMIFS('График КС'!$C$5:$C$40,'График КС'!$A$5:$A$40,"<="&$A10) | E10: =IF('Условия'!$C$25=0,0,IFERROR(MAX(0,MIN('Условия'!$C$23,IF('Условия'!$C$25=1,ROUND('Условия'!$C$23*$D10/'График КС'!$C$42,2),IF('Условия'!$C$25=2,IF($D10>='График КС'!$C$42,'Условия'!$C$23,0),ROUND('Условия'!$C$23*($D10-'Условия'!$C$9)/('График КС'!$C$42-'Условия'!$C$9),2))))),0)) | F10: =ROUND($E10-$E9,2) | G10: =ROUND($B10*'Условия'!$C$13/100,2) | H10: =ROUND($B10-$F10-$G10,2) | I10: =IF($A10='Условия'!$C$7,'Условия'!$C$23,0) | J10: =IFERROR(INDEX($H$5:$H$40,MATCH($A10-'Условия'!$C$17,$A$5:$A$40,0)),0) | K10: =IF(AND('Условия'!$C$14>0,$A10='Условия'!$C$14),ROUND(SUM($G$5:$G$40)*'Условия'!$C$15/100,2),0) | L10: =ROUND(IFERROR(INDEX($B$5:$B$40,MATCH($A10+'Условия'!$C$19,$A$5:$A$40,0)),0)*'Условия'!$C$18/100,2)+IF($A10=1,'Условия'!$C$20,0)+IF($A10='Условия'!$C$12,'Условия'!$C$24,0) | M10: =ROUND($I10+$J10+$K10-$L10,2) | N10: =ROUND($N9+$M10,2) | O10: =IF($N10<0,$A10,"") | P10: =IF($H10<0,"Из КС этого месяца удерживают больше, чем она стоит: погашение аванса и гарантийное удержание вместе больше объёма",IF(AND($B10>0,'Условия'!$C$16<>"",$A10>'Условия'!$C$16),"Месяц за пределами срока объекта, а объём в графике есть",""))
A11: 7 | B11: =ROUND(IFERROR('Условия'!$C$5*INDEX('График КС'!$C$5:$C$40,MATCH($A11,'График КС'!$A$5:$A$40,0))/100,0),2) | C11: =SUMIFS($B$5:$B$40,$A$5:$A$40,"<="&$A11) | D11: =SUMIFS('График КС'!$C$5:$C$40,'График КС'!$A$5:$A$40,"<="&$A11) | E11: =IF('Условия'!$C$25=0,0,IFERROR(MAX(0,MIN('Условия'!$C$23,IF('Условия'!$C$25=1,ROUND('Условия'!$C$23*$D11/'График КС'!$C$42,2),IF('Условия'!$C$25=2,IF($D11>='График КС'!$C$42,'Условия'!$C$23,0),ROUND('Условия'!$C$23*($D11-'Условия'!$C$9)/('График КС'!$C$42-'Условия'!$C$9),2))))),0)) | F11: =ROUND($E11-$E10,2) | G11: =ROUND($B11*'Условия'!$C$13/100,2) | H11: =ROUND($B11-$F11-$G11,2) | I11: =IF($A11='Условия'!$C$7,'Условия'!$C$23,0) | J11: =IFERROR(INDEX($H$5:$H$40,MATCH($A11-'Условия'!$C$17,$A$5:$A$40,0)),0) | K11: =IF(AND('Условия'!$C$14>0,$A11='Условия'!$C$14),ROUND(SUM($G$5:$G$40)*'Условия'!$C$15/100,2),0) | L11: =ROUND(IFERROR(INDEX($B$5:$B$40,MATCH($A11+'Условия'!$C$19,$A$5:$A$40,0)),0)*'Условия'!$C$18/100,2)+IF($A11=1,'Условия'!$C$20,0)+IF($A11='Условия'!$C$12,'Условия'!$C$24,0) | M11: =ROUND($I11+$J11+$K11-$L11,2) | N11: =ROUND($N10+$M11,2) | O11: =IF($N11<0,$A11,"") | P11: =IF($H11<0,"Из КС этого месяца удерживают больше, чем она стоит: погашение аванса и гарантийное удержание вместе больше объёма",IF(AND($B11>0,'Условия'!$C$16<>"",$A11>'Условия'!$C$16),"Месяц за пределами срока объекта, а объём в графике есть",""))
A12: 8 | B12: =ROUND(IFERROR('Условия'!$C$5*INDEX('График КС'!$C$5:$C$40,MATCH($A12,'График КС'!$A$5:$A$40,0))/100,0),2) | C12: =SUMIFS($B$5:$B$40,$A$5:$A$40,"<="&$A12) | D12: =SUMIFS('График КС'!$C$5:$C$40,'График КС'!$A$5:$A$40,"<="&$A12) | E12: =IF('Условия'!$C$25=0,0,IFERROR(MAX(0,MIN('Условия'!$C$23,IF('Условия'!$C$25=1,ROUND('Условия'!$C$23*$D12/'График КС'!$C$42,2),IF('Условия'!$C$25=2,IF($D12>='График КС'!$C$42,'Условия'!$C$23,0),ROUND('Условия'!$C$23*($D12-'Условия'!$C$9)/('График КС'!$C$42-'Условия'!$C$9),2))))),0)) | F12: =ROUND($E12-$E11,2) | G12: =ROUND($B12*'Условия'!$C$13/100,2) | H12: =ROUND($B12-$F12-$G12,2) | I12: =IF($A12='Условия'!$C$7,'Условия'!$C$23,0) | J12: =IFERROR(INDEX($H$5:$H$40,MATCH($A12-'Условия'!$C$17,$A$5:$A$40,0)),0) | K12: =IF(AND('Условия'!$C$14>0,$A12='Условия'!$C$14),ROUND(SUM($G$5:$G$40)*'Условия'!$C$15/100,2),0) | L12: =ROUND(IFERROR(INDEX($B$5:$B$40,MATCH($A12+'Условия'!$C$19,$A$5:$A$40,0)),0)*'Условия'!$C$18/100,2)+IF($A12=1,'Условия'!$C$20,0)+IF($A12='Условия'!$C$12,'Условия'!$C$24,0) | M12: =ROUND($I12+$J12+$K12-$L12,2) | N12: =ROUND($N11+$M12,2) | O12: =IF($N12<0,$A12,"") | P12: =IF($H12<0,"Из КС этого месяца удерживают больше, чем она стоит: погашение аванса и гарантийное удержание вместе больше объёма",IF(AND($B12>0,'Условия'!$C$16<>"",$A12>'Условия'!$C$16),"Месяц за пределами срока объекта, а объём в графике есть",""))
A13: 9 | B13: =ROUND(IFERROR('Условия'!$C$5*INDEX('График КС'!$C$5:$C$40,MATCH($A13,'График КС'!$A$5:$A$40,0))/100,0),2) | C13: =SUMIFS($B$5:$B$40,$A$5:$A$40,"<="&$A13) | D13: =SUMIFS('График КС'!$C$5:$C$40,'График КС'!$A$5:$A$40,"<="&$A13) | E13: =IF('Условия'!$C$25=0,0,IFERROR(MAX(0,MIN('Условия'!$C$23,IF('Условия'!$C$25=1,ROUND('Условия'!$C$23*$D13/'График КС'!$C$42,2),IF('Условия'!$C$25=2,IF($D13>='График КС'!$C$42,'Условия'!$C$23,0),ROUND('Условия'!$C$23*($D13-'Условия'!$C$9)/('График КС'!$C$42-'Условия'!$C$9),2))))),0)) | F13: =ROUND($E13-$E12,2) | G13: =ROUND($B13*'Условия'!$C$13/100,2) | H13: =ROUND($B13-$F13-$G13,2) | I13: =IF($A13='Условия'!$C$7,'Условия'!$C$23,0) | J13: =IFERROR(INDEX($H$5:$H$40,MATCH($A13-'Условия'!$C$17,$A$5:$A$40,0)),0) | K13: =IF(AND('Условия'!$C$14>0,$A13='Условия'!$C$14),ROUND(SUM($G$5:$G$40)*'Условия'!$C$15/100,2),0) | L13: =ROUND(IFERROR(INDEX($B$5:$B$40,MATCH($A13+'Условия'!$C$19,$A$5:$A$40,0)),0)*'Условия'!$C$18/100,2)+IF($A13=1,'Условия'!$C$20,0)+IF($A13='Условия'!$C$12,'Условия'!$C$24,0) | M13: =ROUND($I13+$J13+$K13-$L13,2) | N13: =ROUND($N12+$M13,2) | O13: =IF($N13<0,$A13,"") | P13: =IF($H13<0,"Из КС этого месяца удерживают больше, чем она стоит: погашение аванса и гарантийное удержание вместе больше объёма",IF(AND($B13>0,'Условия'!$C$16<>"",$A13>'Условия'!$C$16),"Месяц за пределами срока объекта, а объём в графике есть",""))
A14: 10 | B14: =ROUND(IFERROR('Условия'!$C$5*INDEX('График КС'!$C$5:$C$40,MATCH($A14,'График КС'!$A$5:$A$40,0))/100,0),2) | C14: =SUMIFS($B$5:$B$40,$A$5:$A$40,"<="&$A14) | D14: =SUMIFS('График КС'!$C$5:$C$40,'График КС'!$A$5:$A$40,"<="&$A14) | E14: =IF('Условия'!$C$25=0,0,IFERROR(MAX(0,MIN('Условия'!$C$23,IF('Условия'!$C$25=1,ROUND('Условия'!$C$23*$D14/'График КС'!$C$42,2),IF('Условия'!$C$25=2,IF($D14>='График КС'!$C$42,'Условия'!$C$23,0),ROUND('Условия'!$C$23*($D14-'Условия'!$C$9)/('График КС'!$C$42-'Условия'!$C$9),2))))),0)) | F14: =ROUND($E14-$E13,2) | G14: =ROUND($B14*'Условия'!$C$13/100,2) | H14: =ROUND($B14-$F14-$G14,2) | I14: =IF($A14='Условия'!$C$7,'Условия'!$C$23,0) | J14: =IFERROR(INDEX($H$5:$H$40,MATCH($A14-'Условия'!$C$17,$A$5:$A$40,0)),0) | K14: =IF(AND('Условия'!$C$14>0,$A14='Условия'!$C$14),ROUND(SUM($G$5:$G$40)*'Условия'!$C$15/100,2),0) | L14: =ROUND(IFERROR(INDEX($B$5:$B$40,MATCH($A14+'Условия'!$C$19,$A$5:$A$40,0)),0)*'Условия'!$C$18/100,2)+IF($A14=1,'Условия'!$C$20,0)+IF($A14='Условия'!$C$12,'Условия'!$C$24,0) | M14: =ROUND($I14+$J14+$K14-$L14,2) | N14: =ROUND($N13+$M14,2) | O14: =IF($N14<0,$A14,"") | P14: =IF($H14<0,"Из КС этого месяца удерживают больше, чем она стоит: погашение аванса и гарантийное удержание вместе больше объёма",IF(AND($B14>0,'Условия'!$C$16<>"",$A14>'Условия'!$C$16),"Месяц за пределами срока объекта, а объём в графике есть",""))
A15: 11 | B15: =ROUND(IFERROR('Условия'!$C$5*INDEX('График КС'!$C$5:$C$40,MATCH($A15,'График КС'!$A$5:$A$40,0))/100,0),2) | C15: =SUMIFS($B$5:$B$40,$A$5:$A$40,"<="&$A15) | D15: =SUMIFS('График КС'!$C$5:$C$40,'График КС'!$A$5:$A$40,"<="&$A15) | E15: =IF('Условия'!$C$25=0,0,IFERROR(MAX(0,MIN('Условия'!$C$23,IF('Условия'!$C$25=1,ROUND('Условия'!$C$23*$D15/'График КС'!$C$42,2),IF('Условия'!$C$25=2,IF($D15>='График КС'!$C$42,'Условия'!$C$23,0),ROUND('Условия'!$C$23*($D15-'Условия'!$C$9)/('График КС'!$C$42-'Условия'!$C$9),2))))),0)) | F15: =ROUND($E15-$E14,2) | G15: =ROUND($B15*'Условия'!$C$13/100,2) | H15: =ROUND($B15-$F15-$G15,2) | I15: =IF($A15='Условия'!$C$7,'Условия'!$C$23,0) | J15: =IFERROR(INDEX($H$5:$H$40,MATCH($A15-'Условия'!$C$17,$A$5:$A$40,0)),0) | K15: =IF(AND('Условия'!$C$14>0,$A15='Условия'!$C$14),ROUND(SUM($G$5:$G$40)*'Условия'!$C$15/100,2),0) | L15: =ROUND(IFERROR(INDEX($B$5:$B$40,MATCH($A15+'Условия'!$C$19,$A$5:$A$40,0)),0)*'Условия'!$C$18/100,2)+IF($A15=1,'Условия'!$C$20,0)+IF($A15='Условия'!$C$12,'Условия'!$C$24,0) | M15: =ROUND($I15+$J15+$K15-$L15,2) | N15: =ROUND($N14+$M15,2) | O15: =IF($N15<0,$A15,"") | P15: =IF($H15<0,"Из КС этого месяца удерживают больше, чем она стоит: погашение аванса и гарантийное удержание вместе больше объёма",IF(AND($B15>0,'Условия'!$C$16<>"",$A15>'Условия'!$C$16),"Месяц за пределами срока объекта, а объём в графике есть",""))
A16: 12 | B16: =ROUND(IFERROR('Условия'!$C$5*INDEX('График КС'!$C$5:$C$40,MATCH($A16,'График КС'!$A$5:$A$40,0))/100,0),2) | C16: =SUMIFS($B$5:$B$40,$A$5:$A$40,"<="&$A16) | D16: =SUMIFS('График КС'!$C$5:$C$40,'График КС'!$A$5:$A$40,"<="&$A16) | E16: =IF('Условия'!$C$25=0,0,IFERROR(MAX(0,MIN('Условия'!$C$23,IF('Условия'!$C$25=1,ROUND('Условия'!$C$23*$D16/'График КС'!$C$42,2),IF('Условия'!$C$25=2,IF($D16>='График КС'!$C$42,'Условия'!$C$23,0),ROUND('Условия'!$C$23*($D16-'Условия'!$C$9)/('График КС'!$C$42-'Условия'!$C$9),2))))),0)) | F16: =ROUND($E16-$E15,2) | G16: =ROUND($B16*'Условия'!$C$13/100,2) | H16: =ROUND($B16-$F16-$G16,2) | I16: =IF($A16='Условия'!$C$7,'Условия'!$C$23,0) | J16: =IFERROR(INDEX($H$5:$H$40,MATCH($A16-'Условия'!$C$17,$A$5:$A$40,0)),0) | K16: =IF(AND('Условия'!$C$14>0,$A16='Условия'!$C$14),ROUND(SUM($G$5:$G$40)*'Условия'!$C$15/100,2),0) | L16: =ROUND(IFERROR(INDEX($B$5:$B$40,MATCH($A16+'Условия'!$C$19,$A$5:$A$40,0)),0)*'Условия'!$C$18/100,2)+IF($A16=1,'Условия'!$C$20,0)+IF($A16='Условия'!$C$12,'Условия'!$C$24,0) | M16: =ROUND($I16+$J16+$K16-$L16,2) | N16: =ROUND($N15+$M16,2) | O16: =IF($N16<0,$A16,"") | P16: =IF($H16<0,"Из КС этого месяца удерживают больше, чем она стоит: погашение аванса и гарантийное удержание вместе больше объёма",IF(AND($B16>0,'Условия'!$C$16<>"",$A16>'Условия'!$C$16),"Месяц за пределами срока объекта, а объём в графике есть",""))
A17: 13 | B17: =ROUND(IFERROR('Условия'!$C$5*INDEX('График КС'!$C$5:$C$40,MATCH($A17,'График КС'!$A$5:$A$40,0))/100,0),2) | C17: =SUMIFS($B$5:$B$40,$A$5:$A$40,"<="&$A17) | D17: =SUMIFS('График КС'!$C$5:$C$40,'График КС'!$A$5:$A$40,"<="&$A17) | E17: =IF('Условия'!$C$25=0,0,IFERROR(MAX(0,MIN('Условия'!$C$23,IF('Условия'!$C$25=1,ROUND('Условия'!$C$23*$D17/'График КС'!$C$42,2),IF('Условия'!$C$25=2,IF($D17>='График КС'!$C$42,'Условия'!$C$23,0),ROUND('Условия'!$C$23*($D17-'Условия'!$C$9)/('График КС'!$C$42-'Условия'!$C$9),2))))),0)) | F17: =ROUND($E17-$E16,2) | G17: =ROUND($B17*'Условия'!$C$13/100,2) | H17: =ROUND($B17-$F17-$G17,2) | I17: =IF($A17='Условия'!$C$7,'Условия'!$C$23,0) | J17: =IFERROR(INDEX($H$5:$H$40,MATCH($A17-'Условия'!$C$17,$A$5:$A$40,0)),0) | K17: =IF(AND('Условия'!$C$14>0,$A17='Условия'!$C$14),ROUND(SUM($G$5:$G$40)*'Условия'!$C$15/100,2),0) | L17: =ROUND(IFERROR(INDEX($B$5:$B$40,MATCH($A17+'Условия'!$C$19,$A$5:$A$40,0)),0)*'Условия'!$C$18/100,2)+IF($A17=1,'Условия'!$C$20,0)+IF($A17='Условия'!$C$12,'Условия'!$C$24,0) | M17: =ROUND($I17+$J17+$K17-$L17,2) | N17: =ROUND($N16+$M17,2) | O17: =IF($N17<0,$A17,"") | P17: =IF($H17<0,"Из КС этого месяца удерживают больше, чем она стоит: погашение аванса и гарантийное удержание вместе больше объёма",IF(AND($B17>0,'Условия'!$C$16<>"",$A17>'Условия'!$C$16),"Месяц за пределами срока объекта, а объём в графике есть",""))
... A40: 36 | B40: =ROUND(IFERROR('Условия'!$C$5*INDEX('График КС'!$C$5:$C$40,MATCH($A40,'График КС'!$A$5:$A$40,0))/100,0),2) | C40: =SUMIFS($B$5:$B$40,$A$5:$A$40,"<="&$A40) | D40: =SUMIFS('График КС'!$C$5:$C$40,'График КС'!$A$5:$A$40,"<="&$A40) | E40: =IF('Условия'!$C$25=0,0,IFERROR(MAX(0,MIN('Условия'!$C$23,IF('Условия'!$C$25=1,ROUND('Условия'!$C$23*$D40/'График КС'!$C$42,2),IF('Условия'!$C$25=2,IF($D40>='График КС'!$C$42,'Условия'!$C$23,0),ROUND('Условия'!$C$23*($D40-'Условия'!$C$9)/('График КС'!$C$42-'Условия'!$C$9),2))))),0)) | F40: =ROUND($E40-$E39,2) | G40: =ROUND($B40*'Условия'!$C$13/100,2) | H40: =ROUND($B40-$F40-$G40,2) | I40: =IF($A40='Условия'!$C$7,'Условия'!$C$23,0) | J40: =IFERROR(INDEX($H$5:$H$40,MATCH($A40-'Условия'!$C$17,$A$5:$A$40,0)),0) | K40: =IF(AND('Условия'!$C$14>0,$A40='Условия'!$C$14),ROUND(SUM($G$5:$G$40)*'Условия'!$C$15/100,2),0) | L40: =ROUND(IFERROR(INDEX($B$5:$B$40,MATCH($A40+'Условия'!$C$19,$A$5:$A$40,0)),0)*'Условия'!$C$18/100,2)+IF($A40=1,'Условия'!$C$20,0)+IF($A40='Условия'!$C$12,'Условия'!$C$24,0) | M40: =ROUND($I40+$J40+$K40-$L40,2) | N40: =ROUND($N39+$M40,2) | O40: =IF($N40<0,$A40,"") | P40: =IF($H40<0,"Из КС этого месяца удерживают больше, чем она стоит: погашение аванса и гарантийное удержание вместе больше объёма",IF(AND($B40>0,'Условия'!$C$16<>"",$A40>'Условия'!$C$16),"Месяц за пределами срока объекта, а объём в графике есть",""))
A42: Итого | B42: =ROUND(SUM($B$5:$B$40),2) | F42: =ROUND(SUM($F$5:$F$40),2) | G42: =ROUND(SUM($G$5:$G$40),2) | H42: =ROUND(SUM($H$5:$H$40),2) | I42: =ROUND(SUM($I$5:$I$40),2) | J42: =ROUND(SUM($J$5:$J$40),2) | K42: =ROUND(SUM($K$5:$K$40),2) | L42: =ROUND(SUM($L$5:$L$40),2) | M42: =ROUND(SUM($M$5:$M$40),2) | N42: =$N$40 | P42: Итог колонки «Накопленный остаток» — это остаток последнего месяца, а не сумма колонки.

Sheet Сравнение
A1: Сравнение двух сценариев: что меняет условие
A2: Здесь не заполняется ничего. Главная строка — «Максимальная заморозка собственных денег»: столько ваших денег стоит в объекте в худший месяц. Разница между сценариями и есть цена условия, о котором идёт разговор.
A4: Показатель | B4: Сценарий А | C4: Сценарий Б | D4: Разница (Б минус А) | E4: Как читать
A5: Аванс получен, руб. | B5: ='Профиль А'!$I$42 | C5: ='Профиль Б'!$I$42 | D5: =ROUND($C5-$B5,2) | E5: Сколько чужих денег зашло в объект.
A6: Стоимость обеспечения аванса, руб. | B6: ='Условия'!$B$24 | C6: ='Условия'!$C$24 | D6: =ROUND($C6-$B6,2) | E6: Прямой вычет из маржи. Считается от суммы аванса, ставки и срока обеспечения.
A7: Максимальная заморозка собственных денег, руб. | B7: =IF(MIN('Профиль А'!$N$5:$N$40)<0,-MIN('Профиль А'!$N$5:$N$40),0) | C7: =IF(MIN('Профиль Б'!$N$5:$N$40)<0,-MIN('Профиль Б'!$N$5:$N$40),0) | D7: =ROUND($C7-$B7,2) | E7: Худшая точка кассы. Столько денег нужно иметь или занять, чтобы объект не встал. Это и есть главная цифра файла.
A8: Месяц максимальной заморозки | B8: =IF(MIN('Профиль А'!$N$5:$N$40)<0,INDEX('Профиль А'!$A$5:$A$40,MATCH(MIN('Профиль А'!$N$5:$N$40),'Профиль А'!$N$5:$N$40,0)),"минуса нет") | C8: =IF(MIN('Профиль Б'!$N$5:$N$40)<0,INDEX('Профиль Б'!$A$5:$A$40,MATCH(MIN('Профиль Б'!$N$5:$N$40),'Профиль Б'!$N$5:$N$40,0)),"минуса нет") | D8: — | E8: Когда наступает худшая точка. Если она приходится на пик работ — риск срыва сроков, а не только процентов по кредиту.
A9: Первый месяц в минусе | B9: =IF(COUNT('Профиль А'!$O$5:$O$40)=0,"минуса нет",MIN('Профиль А'!$O$5:$O$40)) | C9: =IF(COUNT('Профиль Б'!$O$5:$O$40)=0,"минуса нет",MIN('Профиль Б'!$O$5:$O$40)) | D9: — | E9: С какого месяца объект финансируется вами.
A10: Месяцев в минусе | B10: =SUMPRODUCT(('Профиль А'!$N$5:$N$40<0)*('Профиль А'!$A$5:$A$40<>"")) | C10: =SUMPRODUCT(('Профиль Б'!$N$5:$N$40<0)*('Профиль Б'!$A$5:$A$40<>"")) | D10: — | E10: Длина ямы. Стоимость денег считается от неё, а не от глубины.
A11: Погашено аванса, руб. | B11: ='Профиль А'!$F$42 | C11: ='Профиль Б'!$F$42 | D11: =ROUND($C11-$B11,2) | E11: К концу горизонта должно совпасть с полученным авансом. Если меньше — часть погашения приходится на месяцы за горизонтом расчёта.
A12: Удержано гарантийным удержанием и не возвращено, руб. | B12: =ROUND('Профиль А'!$G$42-'Профиль А'!$K$42,2) | C12: =ROUND('Профиль Б'!$G$42-'Профиль Б'!$K$42,2) | D12: =ROUND($C12-$B12,2) | E12: Ваши деньги, оставшиеся у генподрядчика на конец расчёта.
A13: Начислено, но не поступило до конца горизонта, руб. | B13: =ROUND('Профиль А'!$H$42-'Профиль А'!$J$42,2) | C13: =ROUND('Профиль Б'!$H$42-'Профиль Б'!$J$42,2) | D13: =ROUND($C13-$B13,2) | E13: Акты подписаны, деньги ещё идут. Если больше нуля — горизонт короче, чем объект плюс отсрочка оплаты.
A14: Израсходовано на объекте, руб. | B14: ='Профиль А'!$L$42 | C14: ='Профиль Б'!$L$42 | D14: =ROUND($C14-$B14,2) | E14: Себестоимость, стартовые затраты и стоимость обеспечения вместе.
A15: Накопленный остаток на конец расчёта, руб. | B15: ='Профиль А'!$N$42 | C15: ='Профиль Б'!$N$42 | D15: =ROUND($C15-$B15,2) | E15: Денежный результат объекта на конец горизонта. Не прибыль по учёту: часть денег может быть ещё в пути.
A17: Что изменилось между сценариями | B17: =IF(OR($B7="",$C7=""),"",IF(ROUND($C7-$B7,2)<0,"Сценарий Б замораживает меньше ваших денег в худшей точке",IF(ROUND($C7-$B7,2)>0,"Сценарий Б замораживает больше ваших денег в худшей точке","Оба сценария дают одинаковую худшую точку")))
A19: Чего эта таблица не считает
A20: — Стоимость денег. Заморозка показана суммой и длиной, а не процентами по кредиту: ставку по своему кредиту или овердрафту вы знаете сами, и она меняется. Умножьте заморозку на свою ставку и на число месяцев в минусе — это и будет цена условия в рублях.
A21: — Налоги. НДС с полученного аванса и момент признания дохода здесь не считаются вообще: это другой расчёт и другой специалист.
A22: — Возврат неотработанного аванса при расторжении. Это спор о квалификации отношений и объёме выполненного, а не расчёт кассы. Ситуацию надо назвать и остановиться: дальше юрист по вашему делу.
A23: — Вероятность согласия. Генподрядчик может не согласиться ни на один пункт. Файл даёт цифру для разговора, а не рычаг.

Sheet Как читать
A1: Как пользоваться калькулятором
A3: Шаг 1 | B3: На листе «Условия» заполните колонку «Сценарий А» — то, что вам предлагают сейчас. Всё из вашего договора или из проекта договора.
A4: Шаг 2 | B4: На листе «График КС» проставьте доли объёма по месяцам. Сумма долей должна быть 100. Колонку Б заполните так же, если сравниваете только условия аванса.
A5: Шаг 3 | B5: Скопируйте колонку А в колонку Б на листе «Условия» и измените в ней ровно одно условие: размер аванса, порядок погашения, ставку обеспечения или гарантийное удержание. По одному условию за раз — иначе непонятно, что именно дало разницу.
A6: Шаг 4 | B6: Откройте лист «Сравнение». Строка «Максимальная заморозка собственных денег» — цена этого условия для вас. Строка «Месяц максимальной заморозки» — когда вам понадобятся деньги.
A7: Шаг 5 | B7: Повторите для остальных условий. Получится список из четырёх цифр — это и есть повестка переговоров, отсортированная по деньгам.
A8: Шаг 6 | B8: Договорённость закрывается документом: до подписания — протоколом разногласий, после подписания — дополнительным соглашением. Оба есть в этом комплекте.
A10: Цвета
A11: Жёлтая ячейка | B11: заполняете вы
A12: Синий шрифт | B12: введённое значение
A13: Чёрный шрифт | B13: считает формула, менять не нужно
A14: Зелёный шрифт | B14: ссылка на другой лист
A15: Красный текст | B15: проверка: если что-то написано, читайте и исправляйте
A17: Почему файл открывается и в LibreOffice
A18: В расчёте использованы только функции, которые вычисляют и Excel, и LibreOffice: IF, AND, OR, SUM, SUMIFS, MIN, MAX, COUNT, INDEX, MATCH, IFERROR, SUMPRODUCT, ROUND. Новых функций поиска здесь нет намеренно — в LibreOffice они дают ошибку вместо результата, и файл выглядел бы сломанным.
A20: Проверьте себя перед переговорами
A21: Посчитайте сценарий с нулевым авансом. Разница с вашим сценарием по строке «Максимальная заморозка» — это то, сколько аванс стоит для вас на самом деле. Если она меньше стоимости обеспечения, аванс под платную гарантию вам невыгоден, и об этом стоит знать до подписания, а не после.

Sheet Пример заполнения
A1: Пример: как выглядят заполненные условия
A2: Здесь показан формат ввода, а не ваш расчёт. Цифры условные и взяты для наглядности. Ничего отсюда не переносите в рабочие листы: считайте по своему договору.
A4: Лист «Условия» | B4: Сценарий А | C4: Сценарий Б
A5: Сумма договора, руб. | B5: 10 000 000,00 | C5: 10 000 000,00
A6: Размер аванса, % от суммы договора | B6: 30,00 | C6: 0,00
A7: Месяц поступления аванса | B7: 1 | C7: 1
A8: Порядок погашения аванса | B8: пропорционально из каждой КС | C8: —
A9: Доля выполнения, с которой начинается погашение, % | B9: — | C9: —
A10: Ставка обеспечения аванса, % годовых | B10: из предложения банка | C10: 0,00
A11: Срок действия обеспечения, мес. | B11: 12 | C11: 0
A12: Месяц оплаты обеспечения | B12: 1 | C12: 0
A13: Гарантийное удержание, % от каждой КС | B13: 5,00 | C13: 5,00
A14: Месяц возврата гарантийного удержания | B14: 0 | C14: 0
A15: Доля возвращаемого удержания, % | B15: 0,00 | C15: 0,00
... A20: Стартовые затраты до первой КС, руб. | B20: 500 000,00 | C20: 500 000,00
A22: Лист «График КС»
A23: Десять месяцев по 10% в каждом, колонки А и Б одинаковые: сравниваются условия аванса, а не график.
A25: Что покажет лист «Сравнение» на таких условиях
A26: Сценарий А получает аванс в первом месяце и гасит его равными долями из каждой КС; сценарий Б не получает ничего и живёт на своих с первого дня. Разница по строке «Максимальная заморозка собственных денег» — это цена аванса в вашу сторону; из неё надо вычесть стоимость обеспечения, если гарантия платная. Точные числа посчитает файл: здесь их нет намеренно, чтобы никто не переписал пример вместо своего расчёта.
