Workbook
Name Print_Area: 'Итог для документа'!$A$1:$B$19

Sheet Входные данные
A1: Расчёт процентов по ст. 395 ГК РФ
A2: Заполните ячейки со светло-золотистой заливкой. Остальные ячейки содержат подписи и формулы.
A4: Сумма долга, руб. | B4: 1000000 | C4: Долг на дату начала просрочки, после вычета авансов и оплат до этой даты. Оплаты в периоде расчёта вносите только в таблицу «Частичные оплаты». Остаток для документа берите с листа «Итог для документа».
A5: Дата начала просрочки | B5: 45658 | C5: День, следующий за последним днём срока оплаты по договору. Если этот последний день пришёлся на нерабочий, срок оплаты по ст. 193 ГК РФ истекает в ближайший следующий рабочий день, и просрочка начинается со дня после него.
A6: Дата окончания расчёта | B6: 45667 | C6: Дата претензии или иска. Для требования «по день фактической уплаты» — дата составления документа.
A8: Ключевая ставка Банка России
A9: Заполните с сайта Банка России cbr.ru, раздел «Ключевая ставка Банка России». Внесите ставку, действовавшую на дату начала просрочки, и все её изменения, попадающие в период расчёта. Значений здесь нет намеренно: ставка меняется, а скачанный файл не обновляется.
A11: Действует с | B11: Ставка, % годовых
A12: 45658 | B12: 10
A33: Частичные оплаты
A34: Дата | B34: Сумма, руб.
A46: Предупреждение о частичных оплатах
A47: В этой таблице учитывайте только сумму оплаты, направленную на погашение основного долга. По ст. 319 ГК РФ при недостаточности платежа сначала погашаются издержки кредитора по получению исполнения и проценты, являющиеся платой за пользование денежными средствами, затем основной долг. Проценты за просрочку по ст. 395 ГК РФ погашаются после основного долга (п. 49 постановления Пленума ВС РФ от 24.03.2016 № 7). Соглашением сторон можно изменить очередность только требований, названных в ст. 319 ГК РФ (п. 37 постановления Пленума ВС РФ от 22.11.2016 № 54). Если платёж распределяется между несколькими обязательствами или включает иные требования, выделите сумму погашения основного долга по документам расчётов. База долга уменьшается со дня, следующего за датой оплаты; в день оплаты проценты начисляются на прежнюю сумму.

Sheet Расчёт
A1: Одна строка — один период, в котором неизменны и ставка, и база долга
A2: Заполняются только колонки A и B со светло-золотистой заливкой: разбейте срок просрочки по датам смены ставки и по датам частичных оплат. Остальное считается само. Колонка «Проверка» подскажет, если период разбит неверно.
A3: Начало периода | B3: Конец периода | C3: Дней в периоде | D3: База долга, руб. | E3: Ставка, % годовых | F3: Дней в году | G3: Проценты за период, руб. | H3: Проверка
A4: 45658 | B4: 45667 | C4: =IF(OR($A4="",$B4=""),"",$B4-$A4+1) -> 10 | D4: =IF($A4="","",'Входные данные'!$B$4-SUMIF('Входные данные'!$A$35:$A$44,"<"&$A4,'Входные данные'!$B$35:$B$44)) -> 1000000 | E4: =IF($A4="","",IFERROR(INDEX('Входные данные'!$B$12:$B$31,MATCH($A4,'Входные данные'!$A$12:$A$31,1)),"")) -> 10 | F4: =IF($A4="","",IF(DAY(DATE(YEAR($A4),2,29))=29,366,365)) -> 365 | G4: =IF(OR($A4="",$E4="",$C4=""),"",ROUND($D4*$E4/100*$C4/$F4,2)) -> 2739.73 | H4: =IF($A4="","",IF(YEAR($A4)<>YEAR($B4),"Период пересекает 31 декабря — разбейте на две строки",IF($B4<$A4,"Конец периода раньше начала",IF($A4<>'Входные данные'!$B$5,"Период пропущен или перекрыт — исправьте даты",IF($E4="","Ставка на эту дату не найдена: дополните таблицу ставок","")))))
C5: =IF(OR($A5="",$B5=""),"",$B5-$A5+1) | D5: =IF($A5="","",'Входные данные'!$B$4-SUMIF('Входные данные'!$A$35:$A$44,"<"&$A5,'Входные данные'!$B$35:$B$44)) | E5: =IF($A5="","",IFERROR(INDEX('Входные данные'!$B$12:$B$31,MATCH($A5,'Входные данные'!$A$12:$A$31,1)),"")) | F5: =IF($A5="","",IF(DAY(DATE(YEAR($A5),2,29))=29,366,365)) | G5: =IF(OR($A5="",$E5="",$C5=""),"",ROUND($D5*$E5/100*$C5/$F5,2)) | H5: =IF($A5="","",IF(YEAR($A5)<>YEAR($B5),"Период пересекает 31 декабря — разбейте на две строки",IF($B5<$A5,"Конец периода раньше начала",IF(OR($B4="",$A5<>$B4+1),"Период пропущен или перекрыт — исправьте даты",IF($E5="","Ставка на эту дату не найдена: дополните таблицу ставок","")))))
C6: =IF(OR($A6="",$B6=""),"",$B6-$A6+1) | D6: =IF($A6="","",'Входные данные'!$B$4-SUMIF('Входные данные'!$A$35:$A$44,"<"&$A6,'Входные данные'!$B$35:$B$44)) | E6: =IF($A6="","",IFERROR(INDEX('Входные данные'!$B$12:$B$31,MATCH($A6,'Входные данные'!$A$12:$A$31,1)),"")) | F6: =IF($A6="","",IF(DAY(DATE(YEAR($A6),2,29))=29,366,365)) | G6: =IF(OR($A6="",$E6="",$C6=""),"",ROUND($D6*$E6/100*$C6/$F6,2)) | H6: =IF($A6="","",IF(YEAR($A6)<>YEAR($B6),"Период пересекает 31 декабря — разбейте на две строки",IF($B6<$A6,"Конец периода раньше начала",IF(OR($B5="",$A6<>$B5+1),"Период пропущен или перекрыт — исправьте даты",IF($E6="","Ставка на эту дату не найдена: дополните таблицу ставок","")))))
C7: =IF(OR($A7="",$B7=""),"",$B7-$A7+1) | D7: =IF($A7="","",'Входные данные'!$B$4-SUMIF('Входные данные'!$A$35:$A$44,"<"&$A7,'Входные данные'!$B$35:$B$44)) | E7: =IF($A7="","",IFERROR(INDEX('Входные данные'!$B$12:$B$31,MATCH($A7,'Входные данные'!$A$12:$A$31,1)),"")) | F7: =IF($A7="","",IF(DAY(DATE(YEAR($A7),2,29))=29,366,365)) | G7: =IF(OR($A7="",$E7="",$C7=""),"",ROUND($D7*$E7/100*$C7/$F7,2)) | H7: =IF($A7="","",IF(YEAR($A7)<>YEAR($B7),"Период пересекает 31 декабря — разбейте на две строки",IF($B7<$A7,"Конец периода раньше начала",IF(OR($B6="",$A7<>$B6+1),"Период пропущен или перекрыт — исправьте даты",IF($E7="","Ставка на эту дату не найдена: дополните таблицу ставок","")))))
C8: =IF(OR($A8="",$B8=""),"",$B8-$A8+1) | D8: =IF($A8="","",'Входные данные'!$B$4-SUMIF('Входные данные'!$A$35:$A$44,"<"&$A8,'Входные данные'!$B$35:$B$44)) | E8: =IF($A8="","",IFERROR(INDEX('Входные данные'!$B$12:$B$31,MATCH($A8,'Входные данные'!$A$12:$A$31,1)),"")) | F8: =IF($A8="","",IF(DAY(DATE(YEAR($A8),2,29))=29,366,365)) | G8: =IF(OR($A8="",$E8="",$C8=""),"",ROUND($D8*$E8/100*$C8/$F8,2)) | H8: =IF($A8="","",IF(YEAR($A8)<>YEAR($B8),"Период пересекает 31 декабря — разбейте на две строки",IF($B8<$A8,"Конец периода раньше начала",IF(OR($B7="",$A8<>$B7+1),"Период пропущен или перекрыт — исправьте даты",IF($E8="","Ставка на эту дату не найдена: дополните таблицу ставок","")))))
C9: =IF(OR($A9="",$B9=""),"",$B9-$A9+1) | D9: =IF($A9="","",'Входные данные'!$B$4-SUMIF('Входные данные'!$A$35:$A$44,"<"&$A9,'Входные данные'!$B$35:$B$44)) | E9: =IF($A9="","",IFERROR(INDEX('Входные данные'!$B$12:$B$31,MATCH($A9,'Входные данные'!$A$12:$A$31,1)),"")) | F9: =IF($A9="","",IF(DAY(DATE(YEAR($A9),2,29))=29,366,365)) | G9: =IF(OR($A9="",$E9="",$C9=""),"",ROUND($D9*$E9/100*$C9/$F9,2)) | H9: =IF($A9="","",IF(YEAR($A9)<>YEAR($B9),"Период пересекает 31 декабря — разбейте на две строки",IF($B9<$A9,"Конец периода раньше начала",IF(OR($B8="",$A9<>$B8+1),"Период пропущен или перекрыт — исправьте даты",IF($E9="","Ставка на эту дату не найдена: дополните таблицу ставок","")))))
C10: =IF(OR($A10="",$B10=""),"",$B10-$A10+1) | D10: =IF($A10="","",'Входные данные'!$B$4-SUMIF('Входные данные'!$A$35:$A$44,"<"&$A10,'Входные данные'!$B$35:$B$44)) | E10: =IF($A10="","",IFERROR(INDEX('Входные данные'!$B$12:$B$31,MATCH($A10,'Входные данные'!$A$12:$A$31,1)),"")) | F10: =IF($A10="","",IF(DAY(DATE(YEAR($A10),2,29))=29,366,365)) | G10: =IF(OR($A10="",$E10="",$C10=""),"",ROUND($D10*$E10/100*$C10/$F10,2)) | H10: =IF($A10="","",IF(YEAR($A10)<>YEAR($B10),"Период пересекает 31 декабря — разбейте на две строки",IF($B10<$A10,"Конец периода раньше начала",IF(OR($B9="",$A10<>$B9+1),"Период пропущен или перекрыт — исправьте даты",IF($E10="","Ставка на эту дату не найдена: дополните таблицу ставок","")))))
C11: =IF(OR($A11="",$B11=""),"",$B11-$A11+1) | D11: =IF($A11="","",'Входные данные'!$B$4-SUMIF('Входные данные'!$A$35:$A$44,"<"&$A11,'Входные данные'!$B$35:$B$44)) | E11: =IF($A11="","",IFERROR(INDEX('Входные данные'!$B$12:$B$31,MATCH($A11,'Входные данные'!$A$12:$A$31,1)),"")) | F11: =IF($A11="","",IF(DAY(DATE(YEAR($A11),2,29))=29,366,365)) | G11: =IF(OR($A11="",$E11="",$C11=""),"",ROUND($D11*$E11/100*$C11/$F11,2)) | H11: =IF($A11="","",IF(YEAR($A11)<>YEAR($B11),"Период пересекает 31 декабря — разбейте на две строки",IF($B11<$A11,"Конец периода раньше начала",IF(OR($B10="",$A11<>$B10+1),"Период пропущен или перекрыт — исправьте даты",IF($E11="","Ставка на эту дату не найдена: дополните таблицу ставок","")))))
C12: =IF(OR($A12="",$B12=""),"",$B12-$A12+1) | D12: =IF($A12="","",'Входные данные'!$B$4-SUMIF('Входные данные'!$A$35:$A$44,"<"&$A12,'Входные данные'!$B$35:$B$44)) | E12: =IF($A12="","",IFERROR(INDEX('Входные данные'!$B$12:$B$31,MATCH($A12,'Входные данные'!$A$12:$A$31,1)),"")) | F12: =IF($A12="","",IF(DAY(DATE(YEAR($A12),2,29))=29,366,365)) | G12: =IF(OR($A12="",$E12="",$C12=""),"",ROUND($D12*$E12/100*$C12/$F12,2)) | H12: =IF($A12="","",IF(YEAR($A12)<>YEAR($B12),"Период пересекает 31 декабря — разбейте на две строки",IF($B12<$A12,"Конец периода раньше начала",IF(OR($B11="",$A12<>$B11+1),"Период пропущен или перекрыт — исправьте даты",IF($E12="","Ставка на эту дату не найдена: дополните таблицу ставок","")))))
C13: =IF(OR($A13="",$B13=""),"",$B13-$A13+1) | D13: =IF($A13="","",'Входные данные'!$B$4-SUMIF('Входные данные'!$A$35:$A$44,"<"&$A13,'Входные данные'!$B$35:$B$44)) | E13: =IF($A13="","",IFERROR(INDEX('Входные данные'!$B$12:$B$31,MATCH($A13,'Входные данные'!$A$12:$A$31,1)),"")) | F13: =IF($A13="","",IF(DAY(DATE(YEAR($A13),2,29))=29,366,365)) | G13: =IF(OR($A13="",$E13="",$C13=""),"",ROUND($D13*$E13/100*$C13/$F13,2)) | H13: =IF($A13="","",IF(YEAR($A13)<>YEAR($B13),"Период пересекает 31 декабря — разбейте на две строки",IF($B13<$A13,"Конец периода раньше начала",IF(OR($B12="",$A13<>$B12+1),"Период пропущен или перекрыт — исправьте даты",IF($E13="","Ставка на эту дату не найдена: дополните таблицу ставок","")))))
C14: =IF(OR($A14="",$B14=""),"",$B14-$A14+1) | D14: =IF($A14="","",'Входные данные'!$B$4-SUMIF('Входные данные'!$A$35:$A$44,"<"&$A14,'Входные данные'!$B$35:$B$44)) | E14: =IF($A14="","",IFERROR(INDEX('Входные данные'!$B$12:$B$31,MATCH($A14,'Входные данные'!$A$12:$A$31,1)),"")) | F14: =IF($A14="","",IF(DAY(DATE(YEAR($A14),2,29))=29,366,365)) | G14: =IF(OR($A14="",$E14="",$C14=""),"",ROUND($D14*$E14/100*$C14/$F14,2)) | H14: =IF($A14="","",IF(YEAR($A14)<>YEAR($B14),"Период пересекает 31 декабря — разбейте на две строки",IF($B14<$A14,"Конец периода раньше начала",IF(OR($B13="",$A14<>$B13+1),"Период пропущен или перекрыт — исправьте даты",IF($E14="","Ставка на эту дату не найдена: дополните таблицу ставок","")))))
C15: =IF(OR($A15="",$B15=""),"",$B15-$A15+1) | D15: =IF($A15="","",'Входные данные'!$B$4-SUMIF('Входные данные'!$A$35:$A$44,"<"&$A15,'Входные данные'!$B$35:$B$44)) | E15: =IF($A15="","",IFERROR(INDEX('Входные данные'!$B$12:$B$31,MATCH($A15,'Входные данные'!$A$12:$A$31,1)),"")) | F15: =IF($A15="","",IF(DAY(DATE(YEAR($A15),2,29))=29,366,365)) | G15: =IF(OR($A15="",$E15="",$C15=""),"",ROUND($D15*$E15/100*$C15/$F15,2)) | H15: =IF($A15="","",IF(YEAR($A15)<>YEAR($B15),"Период пересекает 31 декабря — разбейте на две строки",IF($B15<$A15,"Конец периода раньше начала",IF(OR($B14="",$A15<>$B14+1),"Период пропущен или перекрыт — исправьте даты",IF($E15="","Ставка на эту дату не найдена: дополните таблицу ставок","")))))
C16: =IF(OR($A16="",$B16=""),"",$B16-$A16+1) | D16: =IF($A16="","",'Входные данные'!$B$4-SUMIF('Входные данные'!$A$35:$A$44,"<"&$A16,'Входные данные'!$B$35:$B$44)) | E16: =IF($A16="","",IFERROR(INDEX('Входные данные'!$B$12:$B$31,MATCH($A16,'Входные данные'!$A$12:$A$31,1)),"")) | F16: =IF($A16="","",IF(DAY(DATE(YEAR($A16),2,29))=29,366,365)) | G16: =IF(OR($A16="",$E16="",$C16=""),"",ROUND($D16*$E16/100*$C16/$F16,2)) | H16: =IF($A16="","",IF(YEAR($A16)<>YEAR($B16),"Период пересекает 31 декабря — разбейте на две строки",IF($B16<$A16,"Конец периода раньше начала",IF(OR($B15="",$A16<>$B15+1),"Период пропущен или перекрыт — исправьте даты",IF($E16="","Ставка на эту дату не найдена: дополните таблицу ставок","")))))
... C43: =IF(OR($A43="",$B43=""),"",$B43-$A43+1) | D43: =IF($A43="","",'Входные данные'!$B$4-SUMIF('Входные данные'!$A$35:$A$44,"<"&$A43,'Входные данные'!$B$35:$B$44)) | E43: =IF($A43="","",IFERROR(INDEX('Входные данные'!$B$12:$B$31,MATCH($A43,'Входные данные'!$A$12:$A$31,1)),"")) | F43: =IF($A43="","",IF(DAY(DATE(YEAR($A43),2,29))=29,366,365)) | G43: =IF(OR($A43="",$E43="",$C43=""),"",ROUND($D43*$E43/100*$C43/$F43,2)) | H43: =IF($A43="","",IF(YEAR($A43)<>YEAR($B43),"Период пересекает 31 декабря — разбейте на две строки",IF($B43<$A43,"Конец периода раньше начала",IF(OR($B42="",$A43<>$B42+1),"Период пропущен или перекрыт — исправьте даты",IF($E43="","Ставка на эту дату не найдена: дополните таблицу ставок","")))))
F45: Проценты по ст. 395 ГК РФ, всего: | G45: =ROUND(SUM($G$4:$G$43),2) -> 2739.73 | H45: =IF(COUNT($A$4:$A$43)=0,"",IF(MAX($B$4:$B$43)<>'Входные данные'!$B$6,"Последний период не совпадает с датой окончания",""))
F46: Долг плюс проценты: | G46: =ROUND('Входные данные'!$B$4-SUM('Входные данные'!$B$35:$B$44)+$G$45,2) -> 1002739.7
A48: Число дней в году берётся фактическое — 365 или 366. Формула считает по фактическому числу дней; норму, которая устанавливала бы иной знаменатель, этот расчёт не применяет. Если порядок расчёта требует иного знаменателя, зафиксируйте его основание и применимость на дату расчёта.
A50: Проверьте себя перед отправкой
A51: Сверьте итог с независимым расчётом процентов по ст. 395 ГК РФ, например в справочно-правовой системе. При расхождении проверьте ставки, даты, базу долга, разбивку периодов и округление в обоих расчётах. Колонка «Проверка» должна быть пустой во всех заполненных строках.

Sheet Итог для документа
A1: Готовый блок для претензии или иска
A2: Значения подставляются сами. Лист печатается как приложение «Расчёт взыскиваемой суммы» — судьи ждут расчёт в разбивке по периодам, поэтому печатайте вместе с листом «Расчёт».
A4: Сумма долга на начало расчёта, руб. | B4: ='Входные данные'!$B$4 -> 1000000
A5: Учтено частичных оплат, руб. | B5: =ROUND(SUM('Входные данные'!$B$35:$B$44),2) -> 0
A6: Основной долг к взысканию, руб. | B6: =ROUND('Входные данные'!$B$4-SUM('Входные данные'!$B$35:$B$44),2) -> 1000000
A7: Период начисления с | B7: ='Входные данные'!$B$5 -> 45658
A8: Период начисления по | B8: ='Входные данные'!$B$6 -> 45667
A9: Всего дней просрочки | B9: =IF(OR('Входные данные'!$B$5="",'Входные данные'!$B$6=""),"",'Входные данные'!$B$6-'Входные данные'!$B$5+1) -> 10
A10: Проценты по ст. 395 ГК РФ, руб. | B10: =Расчёт!$G$45 -> 2739.73
A11: Итого к взысканию, руб. | B11: =Расчёт!$G$46 -> 1002739.7
A12: Фраза для документа
A13: Проценты подлежат начислению по день фактической уплаты долга (п. 3 ст. 395 ГК РФ).
A15: Условия применения расчёта
A16: — Сопоставьте условия договора об ответственности за просрочку оплаты с п. 4 ст. 395 ГК РФ. Если предусмотрена договорная неустойка, по общему правилу применяется она, если иное не установлено законом или договором.
A17: — Проверьте наличие мораториев, процедур банкротства и иных оснований ограничения начисления; при необходимости скорректируйте расчётный период и исходные данные.
A18: — Подготовьте расчёт и подтверждающие документы: договор, акты, сведения об оплате, период просрочки и применённые ставки.
A19: — Сверьте применимые условия договора, фактические обстоятельства и нормативные основания начисления процентов.

Sheet Пример заполнения
A1: Пример: как выглядят заполненные поля
A2: Здесь показан формат ввода, а не ваш расчёт. Цифры вымышленные, ставки — условные: реальные берите на cbr.ru. Ничего отсюда не переносите в документ.
A4: Входные данные
A5: Сумма долга, руб. | B5: 1 250 000,00
A6: Дата начала просрочки | B6: 15.03.2026
A7: Дата окончания расчёта | B7: 30.07.2026
A9: Таблица ставок
A10: Действует с | B10: Ставка, % годовых
A11: 15.03.2026 | B11: условная 1
A12: 28.04.2026 | B12: условная 2
A14: Строки листа «Расчёт»
A15: Начало периода | B15: Конец периода | C15: Дней в периоде | D15: База долга, руб. | E15: Ставка, % годовых | F15: Дней в году | G15: Проценты за период, руб. | H15: Проверка
A16: 15.03.2026 | B16: 27.04.2026 | C16: считается | D16: считается | E16: подставится | F16: считается | G16: считается | H16: пусто, если всё верно
A17: 28.04.2026 | B17: 30.07.2026 | C17: считается | D17: считается | E17: подставится | F17: считается | G17: считается | H17: пусто, если всё верно
A19: Обратите внимание: период разбит на две строки по дате смены ставки. Если бы просрочка пересекала 31 декабря, разбить пришлось бы и там — колонка «Проверка» об этом напомнит.
