Workbook
Name Print_Area: Итоги!$A$1:$C$19
Name Print_Area: 'Объект и должник'!$A$1:$C$39
Name Print_Area: 'Пример заполнения'!$A$1:$M$22
Name Print_Area: 'Реестр документов'!$A$1:$M$205
Name Print_Titles: 'Объект и должник'!$1:$3
Name Print_Titles: 'Реестр документов'!$1:$3

Sheet Объект и должник
A1: Объект, должник и контрольные даты
A2: Внесите сведения из судебного акта и официальной публикации. Жёлтые ячейки предназначены для ввода, расчётные показатели формируются автоматически.
A4: Ваш объект и договор
A5: Объект | C5: Наименование и адрес объекта строительства
A6: Договор субподряда № и дата | C6: Титульный лист договора
A7: Наименование должника (генподрядчика) | C7: Полное наименование по ЕГРЮЛ
A8: ИНН должника | C8: Используйте ИНН для однозначной идентификации должника в публичных источниках.
A9: ОГРН должника | C9: Выписка ЕГРЮЛ
A11: Дело о банкротстве
A12: Номер дела о банкротстве | C12: Из карточки дела kad.arbitr.ru
A13: Арбитражный суд, рассматривающий дело | C13: Из судебного акта
A14: Дата принятия судом заявления о признании банкротом | C14: Ключевая дата для деления требований на реестровые и текущие (ст. 5 Закона о банкротстве). Лист «Реестр документов» сравнивает с ней дату каждого документа
A15: Введённая процедура | C15: Наблюдение, внешнее управление, конкурсное производство — как названо в судебном акте
A16: Дата введения процедуры | C16: Из судебного акта
A17: Дата публикации сведений | C17: От неё считается срок заявления требования. Сохраните саму публикацию
A18: Источник публикации и ссылка | C18: ЕФРСБ (bankrot.fedresurs.ru) либо официальное издание. Укажите номер сообщения или ссылку
A20: Определение срока заявления требования
A21: Определите применимую процедуру и срок по ст. 71, 100 или 142 Закона № 127-ФЗ; сверьте дату и источник публикации, поставьте контрольную дату.
A23: Норма, по которой проверен срок | C23: Например: ст. 71 Закона о банкротстве, редакция на дату проверки
A24: Дата, до которой требование должно быть заявлено | C24: Укажите предельную дату по применимой процедуре и назначьте дату внутреннего контроля до её истечения.
A25: Кем и когда проверен срок | C25: Фамилия ответственного, дата проверки и ссылка на источник.
A27: Проверка | B27: =IF($B$24="","срок не проверен — заполните строки 23–25",IF($B$25="","дата записана, но не указано, кем и когда проверена",IF($B$24<TODAY(),"Указанная контрольная дата истекла: проверьте срок и процессуальный порядок по файлу 09.","Дней до контрольной даты: "&($B$24-TODAY())))) -> срок не проверен — заполните строки 23–25
A29: Арбитражный управляющий
A30: Фамилия, имя, отчество | C30: Из публикации сведений
A31: Адрес для корреспонденции | C31: Адрес для корреспонденции из официальной публикации или судебного акта. Сохраните подтверждение направления.
A32: Электронная почта | C32: Если указана в публикации
A33: Саморегулируемая организация | C33: Из публикации сведений
A35: Квалификация требования
A36: Сопоставьте даты возникновения обязательств с датой принятия заявления о банкротстве. Квалификацию требования определите по статье 5 Закона № 127-ФЗ и судебным материалам.
A38: Контроль перед заполнением
A39: Сверьте реестр, расчёт и опубликованные сведения с судебными актами. Заявление направляется в суд отдельно.

Sheet Реестр документов
A1: Хронология: что подписано, когда направлено, чем подтверждается
A2: По каждой позиции внесите реквизиты и период. Колонки «Период» и «Проверка» показывают строки для дополнительной сверки.
A3: № | B3: Тип документа | C3: Номер | D3: Дата документа | E3: Сумма, руб. | F3: Подписан обеими сторонами | G3: Направлен: дата | H3: Способ направления | I3: Подтверждение направления | J3: Место хранения оригинала | K3: Копия в пакет | L3: Дата документа / принятие заявления | M3: Проверка
A4: =IF($B4="","",ROW()-3) | L4: =IF($D4="","",IF('Объект и должник'!$B$14="","дата принятия заявления не заполнена",IF($D4<'Объект и должник'!$B$14,"до принятия заявления","после принятия заявления"))) | M4: =IF($B4="",IF(COUNTA($C4:$K4)>0,"НЕ ЗАВЕРШЕНО: укажите тип документа",""),IF(IFERROR(OR($C4="",NOT(ISNUMBER($D4)),$D4<=0,$D4<>INT($D4),AND($K4<>"да",$K4<>"нет")),TRUE),"НЕ ЗАВЕРШЕНО: реквизиты, дата или включение копии",IF(AND($G4<>"",OR(NOT(ISNUMBER($G4)),$H4="",$I4="")),"НЕ ЗАВЕРШЕНО: направление и подтверждение",IF($B4="","",IF(AND($E4>0,LOWER($F4)<>"да"),"Акт не подписан обеими сторонами: проверьте подтверждения выполнения и сдачи.",IF(AND($G4<>"",$I4=""),"направлено, но подтверждение направления не указано",IF($K4="","Отметьте включение копии в перечень приложений.",IF($L4="после принятия заявления","Проверьте признаки текущего платежа по статье 5 Закона № 127-ФЗ.",""))))))))
A5: =IF($B5="","",ROW()-3) | L5: =IF($D5="","",IF('Объект и должник'!$B$14="","дата принятия заявления не заполнена",IF($D5<'Объект и должник'!$B$14,"до принятия заявления","после принятия заявления"))) | M5: =IF($B5="",IF(COUNTA($C5:$K5)>0,"НЕ ЗАВЕРШЕНО: укажите тип документа",""),IF(IFERROR(OR($C5="",NOT(ISNUMBER($D5)),$D5<=0,$D5<>INT($D5),AND($K5<>"да",$K5<>"нет")),TRUE),"НЕ ЗАВЕРШЕНО: реквизиты, дата или включение копии",IF(AND($G5<>"",OR(NOT(ISNUMBER($G5)),$H5="",$I5="")),"НЕ ЗАВЕРШЕНО: направление и подтверждение",IF($B5="","",IF(AND($E5>0,LOWER($F5)<>"да"),"Акт не подписан обеими сторонами: проверьте подтверждения выполнения и сдачи.",IF(AND($G5<>"",$I5=""),"направлено, но подтверждение направления не указано",IF($K5="","Отметьте включение копии в перечень приложений.",IF($L5="после принятия заявления","Проверьте признаки текущего платежа по статье 5 Закона № 127-ФЗ.",""))))))))
A6: =IF($B6="","",ROW()-3) | L6: =IF($D6="","",IF('Объект и должник'!$B$14="","дата принятия заявления не заполнена",IF($D6<'Объект и должник'!$B$14,"до принятия заявления","после принятия заявления"))) | M6: =IF($B6="",IF(COUNTA($C6:$K6)>0,"НЕ ЗАВЕРШЕНО: укажите тип документа",""),IF(IFERROR(OR($C6="",NOT(ISNUMBER($D6)),$D6<=0,$D6<>INT($D6),AND($K6<>"да",$K6<>"нет")),TRUE),"НЕ ЗАВЕРШЕНО: реквизиты, дата или включение копии",IF(AND($G6<>"",OR(NOT(ISNUMBER($G6)),$H6="",$I6="")),"НЕ ЗАВЕРШЕНО: направление и подтверждение",IF($B6="","",IF(AND($E6>0,LOWER($F6)<>"да"),"Акт не подписан обеими сторонами: проверьте подтверждения выполнения и сдачи.",IF(AND($G6<>"",$I6=""),"направлено, но подтверждение направления не указано",IF($K6="","Отметьте включение копии в перечень приложений.",IF($L6="после принятия заявления","Проверьте признаки текущего платежа по статье 5 Закона № 127-ФЗ.",""))))))))
A7: =IF($B7="","",ROW()-3) | L7: =IF($D7="","",IF('Объект и должник'!$B$14="","дата принятия заявления не заполнена",IF($D7<'Объект и должник'!$B$14,"до принятия заявления","после принятия заявления"))) | M7: =IF($B7="",IF(COUNTA($C7:$K7)>0,"НЕ ЗАВЕРШЕНО: укажите тип документа",""),IF(IFERROR(OR($C7="",NOT(ISNUMBER($D7)),$D7<=0,$D7<>INT($D7),AND($K7<>"да",$K7<>"нет")),TRUE),"НЕ ЗАВЕРШЕНО: реквизиты, дата или включение копии",IF(AND($G7<>"",OR(NOT(ISNUMBER($G7)),$H7="",$I7="")),"НЕ ЗАВЕРШЕНО: направление и подтверждение",IF($B7="","",IF(AND($E7>0,LOWER($F7)<>"да"),"Акт не подписан обеими сторонами: проверьте подтверждения выполнения и сдачи.",IF(AND($G7<>"",$I7=""),"направлено, но подтверждение направления не указано",IF($K7="","Отметьте включение копии в перечень приложений.",IF($L7="после принятия заявления","Проверьте признаки текущего платежа по статье 5 Закона № 127-ФЗ.",""))))))))
A8: =IF($B8="","",ROW()-3) | L8: =IF($D8="","",IF('Объект и должник'!$B$14="","дата принятия заявления не заполнена",IF($D8<'Объект и должник'!$B$14,"до принятия заявления","после принятия заявления"))) | M8: =IF($B8="",IF(COUNTA($C8:$K8)>0,"НЕ ЗАВЕРШЕНО: укажите тип документа",""),IF(IFERROR(OR($C8="",NOT(ISNUMBER($D8)),$D8<=0,$D8<>INT($D8),AND($K8<>"да",$K8<>"нет")),TRUE),"НЕ ЗАВЕРШЕНО: реквизиты, дата или включение копии",IF(AND($G8<>"",OR(NOT(ISNUMBER($G8)),$H8="",$I8="")),"НЕ ЗАВЕРШЕНО: направление и подтверждение",IF($B8="","",IF(AND($E8>0,LOWER($F8)<>"да"),"Акт не подписан обеими сторонами: проверьте подтверждения выполнения и сдачи.",IF(AND($G8<>"",$I8=""),"направлено, но подтверждение направления не указано",IF($K8="","Отметьте включение копии в перечень приложений.",IF($L8="после принятия заявления","Проверьте признаки текущего платежа по статье 5 Закона № 127-ФЗ.",""))))))))
A9: =IF($B9="","",ROW()-3) | L9: =IF($D9="","",IF('Объект и должник'!$B$14="","дата принятия заявления не заполнена",IF($D9<'Объект и должник'!$B$14,"до принятия заявления","после принятия заявления"))) | M9: =IF($B9="",IF(COUNTA($C9:$K9)>0,"НЕ ЗАВЕРШЕНО: укажите тип документа",""),IF(IFERROR(OR($C9="",NOT(ISNUMBER($D9)),$D9<=0,$D9<>INT($D9),AND($K9<>"да",$K9<>"нет")),TRUE),"НЕ ЗАВЕРШЕНО: реквизиты, дата или включение копии",IF(AND($G9<>"",OR(NOT(ISNUMBER($G9)),$H9="",$I9="")),"НЕ ЗАВЕРШЕНО: направление и подтверждение",IF($B9="","",IF(AND($E9>0,LOWER($F9)<>"да"),"Акт не подписан обеими сторонами: проверьте подтверждения выполнения и сдачи.",IF(AND($G9<>"",$I9=""),"направлено, но подтверждение направления не указано",IF($K9="","Отметьте включение копии в перечень приложений.",IF($L9="после принятия заявления","Проверьте признаки текущего платежа по статье 5 Закона № 127-ФЗ.",""))))))))
A10: =IF($B10="","",ROW()-3) | L10: =IF($D10="","",IF('Объект и должник'!$B$14="","дата принятия заявления не заполнена",IF($D10<'Объект и должник'!$B$14,"до принятия заявления","после принятия заявления"))) | M10: =IF($B10="",IF(COUNTA($C10:$K10)>0,"НЕ ЗАВЕРШЕНО: укажите тип документа",""),IF(IFERROR(OR($C10="",NOT(ISNUMBER($D10)),$D10<=0,$D10<>INT($D10),AND($K10<>"да",$K10<>"нет")),TRUE),"НЕ ЗАВЕРШЕНО: реквизиты, дата или включение копии",IF(AND($G10<>"",OR(NOT(ISNUMBER($G10)),$H10="",$I10="")),"НЕ ЗАВЕРШЕНО: направление и подтверждение",IF($B10="","",IF(AND($E10>0,LOWER($F10)<>"да"),"Акт не подписан обеими сторонами: проверьте подтверждения выполнения и сдачи.",IF(AND($G10<>"",$I10=""),"направлено, но подтверждение направления не указано",IF($K10="","Отметьте включение копии в перечень приложений.",IF($L10="после принятия заявления","Проверьте признаки текущего платежа по статье 5 Закона № 127-ФЗ.",""))))))))
A11: =IF($B11="","",ROW()-3) | L11: =IF($D11="","",IF('Объект и должник'!$B$14="","дата принятия заявления не заполнена",IF($D11<'Объект и должник'!$B$14,"до принятия заявления","после принятия заявления"))) | M11: =IF($B11="",IF(COUNTA($C11:$K11)>0,"НЕ ЗАВЕРШЕНО: укажите тип документа",""),IF(IFERROR(OR($C11="",NOT(ISNUMBER($D11)),$D11<=0,$D11<>INT($D11),AND($K11<>"да",$K11<>"нет")),TRUE),"НЕ ЗАВЕРШЕНО: реквизиты, дата или включение копии",IF(AND($G11<>"",OR(NOT(ISNUMBER($G11)),$H11="",$I11="")),"НЕ ЗАВЕРШЕНО: направление и подтверждение",IF($B11="","",IF(AND($E11>0,LOWER($F11)<>"да"),"Акт не подписан обеими сторонами: проверьте подтверждения выполнения и сдачи.",IF(AND($G11<>"",$I11=""),"направлено, но подтверждение направления не указано",IF($K11="","Отметьте включение копии в перечень приложений.",IF($L11="после принятия заявления","Проверьте признаки текущего платежа по статье 5 Закона № 127-ФЗ.",""))))))))
A12: =IF($B12="","",ROW()-3) | L12: =IF($D12="","",IF('Объект и должник'!$B$14="","дата принятия заявления не заполнена",IF($D12<'Объект и должник'!$B$14,"до принятия заявления","после принятия заявления"))) | M12: =IF($B12="",IF(COUNTA($C12:$K12)>0,"НЕ ЗАВЕРШЕНО: укажите тип документа",""),IF(IFERROR(OR($C12="",NOT(ISNUMBER($D12)),$D12<=0,$D12<>INT($D12),AND($K12<>"да",$K12<>"нет")),TRUE),"НЕ ЗАВЕРШЕНО: реквизиты, дата или включение копии",IF(AND($G12<>"",OR(NOT(ISNUMBER($G12)),$H12="",$I12="")),"НЕ ЗАВЕРШЕНО: направление и подтверждение",IF($B12="","",IF(AND($E12>0,LOWER($F12)<>"да"),"Акт не подписан обеими сторонами: проверьте подтверждения выполнения и сдачи.",IF(AND($G12<>"",$I12=""),"направлено, но подтверждение направления не указано",IF($K12="","Отметьте включение копии в перечень приложений.",IF($L12="после принятия заявления","Проверьте признаки текущего платежа по статье 5 Закона № 127-ФЗ.",""))))))))
A13: =IF($B13="","",ROW()-3) | L13: =IF($D13="","",IF('Объект и должник'!$B$14="","дата принятия заявления не заполнена",IF($D13<'Объект и должник'!$B$14,"до принятия заявления","после принятия заявления"))) | M13: =IF($B13="",IF(COUNTA($C13:$K13)>0,"НЕ ЗАВЕРШЕНО: укажите тип документа",""),IF(IFERROR(OR($C13="",NOT(ISNUMBER($D13)),$D13<=0,$D13<>INT($D13),AND($K13<>"да",$K13<>"нет")),TRUE),"НЕ ЗАВЕРШЕНО: реквизиты, дата или включение копии",IF(AND($G13<>"",OR(NOT(ISNUMBER($G13)),$H13="",$I13="")),"НЕ ЗАВЕРШЕНО: направление и подтверждение",IF($B13="","",IF(AND($E13>0,LOWER($F13)<>"да"),"Акт не подписан обеими сторонами: проверьте подтверждения выполнения и сдачи.",IF(AND($G13<>"",$I13=""),"направлено, но подтверждение направления не указано",IF($K13="","Отметьте включение копии в перечень приложений.",IF($L13="после принятия заявления","Проверьте признаки текущего платежа по статье 5 Закона № 127-ФЗ.",""))))))))
A14: =IF($B14="","",ROW()-3) | L14: =IF($D14="","",IF('Объект и должник'!$B$14="","дата принятия заявления не заполнена",IF($D14<'Объект и должник'!$B$14,"до принятия заявления","после принятия заявления"))) | M14: =IF($B14="",IF(COUNTA($C14:$K14)>0,"НЕ ЗАВЕРШЕНО: укажите тип документа",""),IF(IFERROR(OR($C14="",NOT(ISNUMBER($D14)),$D14<=0,$D14<>INT($D14),AND($K14<>"да",$K14<>"нет")),TRUE),"НЕ ЗАВЕРШЕНО: реквизиты, дата или включение копии",IF(AND($G14<>"",OR(NOT(ISNUMBER($G14)),$H14="",$I14="")),"НЕ ЗАВЕРШЕНО: направление и подтверждение",IF($B14="","",IF(AND($E14>0,LOWER($F14)<>"да"),"Акт не подписан обеими сторонами: проверьте подтверждения выполнения и сдачи.",IF(AND($G14<>"",$I14=""),"направлено, но подтверждение направления не указано",IF($K14="","Отметьте включение копии в перечень приложений.",IF($L14="после принятия заявления","Проверьте признаки текущего платежа по статье 5 Закона № 127-ФЗ.",""))))))))
A15: =IF($B15="","",ROW()-3) | L15: =IF($D15="","",IF('Объект и должник'!$B$14="","дата принятия заявления не заполнена",IF($D15<'Объект и должник'!$B$14,"до принятия заявления","после принятия заявления"))) | M15: =IF($B15="",IF(COUNTA($C15:$K15)>0,"НЕ ЗАВЕРШЕНО: укажите тип документа",""),IF(IFERROR(OR($C15="",NOT(ISNUMBER($D15)),$D15<=0,$D15<>INT($D15),AND($K15<>"да",$K15<>"нет")),TRUE),"НЕ ЗАВЕРШЕНО: реквизиты, дата или включение копии",IF(AND($G15<>"",OR(NOT(ISNUMBER($G15)),$H15="",$I15="")),"НЕ ЗАВЕРШЕНО: направление и подтверждение",IF($B15="","",IF(AND($E15>0,LOWER($F15)<>"да"),"Акт не подписан обеими сторонами: проверьте подтверждения выполнения и сдачи.",IF(AND($G15<>"",$I15=""),"направлено, но подтверждение направления не указано",IF($K15="","Отметьте включение копии в перечень приложений.",IF($L15="после принятия заявления","Проверьте признаки текущего платежа по статье 5 Закона № 127-ФЗ.",""))))))))
... A203: =IF($B203="","",ROW()-3) | L203: =IF($D203="","",IF('Объект и должник'!$B$14="","дата принятия заявления не заполнена",IF($D203<'Объект и должник'!$B$14,"до принятия заявления","после принятия заявления"))) | M203: =IF($B203="",IF(COUNTA($C203:$K203)>0,"НЕ ЗАВЕРШЕНО: укажите тип документа",""),IF(IFERROR(OR($C203="",NOT(ISNUMBER($D203)),$D203<=0,$D203<>INT($D203),AND($K203<>"да",$K203<>"нет")),TRUE),"НЕ ЗАВЕРШЕНО: реквизиты, дата или включение копии",IF(AND($G203<>"",OR(NOT(ISNUMBER($G203)),$H203="",$I203="")),"НЕ ЗАВЕРШЕНО: направление и подтверждение",IF($B203="","",IF(AND($E203>0,LOWER($F203)<>"да"),"Акт не подписан обеими сторонами: проверьте подтверждения выполнения и сдачи.",IF(AND($G203<>"",$I203=""),"направлено, но подтверждение направления не указано",IF($K203="","Отметьте включение копии в перечень приложений.",IF($L203="после принятия заявления","Проверьте признаки текущего платежа по статье 5 Закона № 127-ФЗ.",""))))))))
A205: Проверьте строки с замечанием в колонке «Проверка» по первичным документам до составления требования.

Sheet Итоги
A1: Итоги комплектования документов
A2: Показатели формируются по листу «Реестр документов». Сверьте их с расчётом требования и перечнем приложений.
A4: Строк заполнено | B4: =SUMPRODUCT(--(LEN('Реестр документов'!$B$4:$B$203)>0)) -> 0 | C4: Каждая строка — один документ
A5: Отмечено «копия в пакет» | B5: =COUNTIF('Реестр документов'!$K$4:$K$203,"да") -> 0 | C5: Сверяйте с файлом «Перечень пакета для заявления требования»
A6: Сумма по документам до принятия заявления, руб. | B6: =ROUND(SUMIF('Реестр документов'!$L$4:$L$203,"до принятия заявления",'Реестр документов'!$E$4:$E$203),2) -> 0 | C6: Группировка по датам документов, а не готовая реестровая часть долга
A7: Сумма по документам после принятия заявления, руб. | B7: =ROUND(SUMIF('Реестр документов'!$L$4:$L$203,"после принятия заявления",'Реестр документов'!$E$4:$E$203),2) -> 0 | C7: Дата документа сама по себе не определяет текущий платёж. Проверьте возникновение обязательства.
A8: Сумма значений документов в пакете, руб. | B8: =ROUND(SUMIF('Реестр документов'!$K$4:$K$203,"да",'Реестр документов'!$E$4:$E$203),2) -> 0 | C8: Не размер долга: КС-2 и КС-3 на одни работы по 100 000 дают здесь 200 000. Долг в этом примере 100 000 до оплат. Не складывайте повторные подтверждения.
A9: Строк с непустой колонкой «Проверка» | B9: =SUMPRODUCT(--(LEN('Реестр документов'!$M$4:$M$203)>0)) -> 0 | C9: Проверьте каждую отмеченную строку и устраните ошибки до подачи заявления.
A10: Направлено, но подтверждение не указано | B10: =SUMPRODUCT(--(LEN('Реестр документов'!$G$4:$G$203)>0),--(LEN('Реестр документов'!$I$4:$I$203)=0)) -> 0 | C10: По каждой отмеченной строке проверьте реквизиты, даты и подтверждающие документы до подачи заявления.
A13: Срок | B13: ='Объект и должник'!$B$27 -> срок не проверен — заполните строки 23–25
A15: Сопоставление с расчётом требования
A16: Основной долг и финансовые санкции рассчитайте раздельно с учётом статьи 137 Закона № 127-ФЗ. Суммы реестра документов используйте для сверки полноты исходных данных.
A17: После установления требования контролируйте расчёты по судебным актам, реестру кредиторов и сообщениям управляющего. Фактическое удовлетворение зависит от процедуры и имущества должника.
A18: Статья 5 п. 1–2 Закона №127-ФЗ: квалификация зависит от возникновения обязательства, а не только даты КС. Модель не решает вопрос за суд. Основание и процедуру сверяйте с файлами 02, 05, 08, 09.
A19: Заявление о включении требования подаётся в арбитражный суд в установленном порядке.

Sheet Пример заполнения
A1: Пример: как выглядят заполненные строки
A2: Учебный пример показывает заполнение реквизитов и строк реестра. Рабочие сведения внесите по документам своего объекта и должника.
A4: Лист «Объект и должник»
A5: Наименование должника (генподрядчика) | B5: ООО «Условный генподрядчик»
A6: Дата принятия судом заявления о признании банкротом | B6: 12.02.2026
A7: Введённая процедура | B7: наблюдение
A8: Дата публикации сведений | B8: 05.03.2026
A9: Норма, по которой проверен срок | B9: ст. 71 Закона о банкротстве, редакция на дату проверки
A10: Дата, до которой требование должно быть заявлено | B10: дата, полученная вашей проверкой
A11: Кем и когда проверен срок | B11: Иванов И. И., 06.03.2026
A13: Предельную дату заявления требования определите по судебному акту, публикации и применимой норме. Зафиксируйте расчёт срока и дату проверки.
A15: Лист «Реестр документов»
A16: № | B16: Тип документа | C16: Номер | D16: Дата документа | E16: Сумма, руб. | F16: Подписан обеими сторонами | G16: Направлен: дата | H16: Способ направления | I16: Подтверждение направления | J16: Место хранения оригинала | K16: Копия в пакет | L16: Период | M16: Проверка
A17: 1 | B17: Договор субподряда | C17: СП-14 | D17: 11.06.2025 | F17: да | J17: папка «Договоры», оригинал | K17: да | L17: считается | M17: считается
A18: 2 | B18: Акт КС-2 | C18: 3 | D18: 31.10.2025 | E18: 1 250 000,00 | F18: да | J18: папка объекта | K18: да | L18: считается | M18: считается
A19: 3 | B19: Претензия | C19: 48 | D19: 20.01.2026 | F19: нет | G19: 21.01.2026 | H19: ценное письмо с описью | I19: опись, трек 000000000000 | J19: папка «Переписка» | K19: да | L19: считается | M19: считается
A20: 4 | B20: Акт КС-2 | C20: 5 | D20: 28.02.2026 | E20: 410 000,00 | F20: да | J20: папка объекта | K20: да | L20: считается | M20: считается
A22: Для документа после принятия заявления отдельно проверьте признаки текущего платежа и основание обязательства.
