Workbook

Sheet Как читать
A1: Расчёт отработанной части аванса и сальдо расчётов
A3: Результат расчёта: аванс, стоимость работ, оплаты и расчётное сальдо.
A4: Запишите фактические суммы аванса, выполненных работ и оплат. Сопоставьте их с требованием о возврате.
A5: Каждую сумму подтвердите платежом, актом и реквизитами передачи; разделяйте подписанные и односторонние документы.
A6: Внесите данные в исходные листы, затем сверьте сальдо и подготовьте проект акта сверки.
A7: Отдельные требования и основания
A8: Основание прекращения договора и спорные суммы фиксируйте по документам; перед ответом проверьте договорный порядок.
A9: Проценты, неустойку и убытки рассчитывайте отдельно с собственными основаниями и периодами.
A10: Порядок работы
A11: 1. На листе «Договор и аванс» укажите реквизиты, цену договора, фактически полученный аванс и сведения о требовании возврата.
A12: 2. Заполните документ, номер, стоимость и статус каждого акта. Оплаты и погашение аванса укажите числами; отсутствие — 0. Для неподписанных актов подтвердите передачу.
A13: 3. На листе «Встречное» укажите документально подтверждённые материалы, расходы и удержания. Исключите повторное включение сумм, учтённых в реестре актов.
... A26: Срок ответа берите из договора и полученного требования. Сохраните доказательства направления ответа.

Sheet Договор и аванс
A1: Договор, аванс и предъявленное требование
A3: Укажите фактически полученный аванс по платёжным поручениям и банковским выпискам. Сумму, предусмотренную договором, сопоставьте с фактическими поступлениями.
A5: Цена работ по договору с учётом всех допсоглашений | C5: договор и все допсоглашения на изменение цены
A6: Аванс получен всего | C6: платёжные поручения с назначением «аванс». Складывайте все, включая доплаты
A7: Дата последнего платежа аванса | C7: платёжное поручение
A8: Основание прекращения договора | C8: выберите из списка по документу: уведомление, соглашение, решение суда
A9: Дата, с которой договор считается прекращённым | C9: Дата прекращения по уведомлению, соглашению или судебному акту. При наличии спора отдельно зафиксируйте позиции сторон и подтверждающие документы.
A10: Дата получения требования о возврате | C10: конверт, отчёт об отслеживании, входящий штамп, дата письма на почте
A11: Сумма, которую требуют вернуть | C11: текст требования
A12: Срок ответа на требование | C12: Срок по договору и полученному требованию. Укажите источник, порядок исчисления и контрольную дату ответа.
A15: Считается по листам «Выполнено» и «Встречное»
A16: Погашение аванса подписанными обеими сторонами актами | B16: =SUMIFS('Выполнено'!I6:I45,'Выполнено'!F6:F45,"подписан обеими сторонами") | C16: сумма колонки «Погашение аванса» по актам со статусом «подписан обеими сторонами»
A17: Аванс, не закрытый двусторонними актами | B17: =IF(OR(NOT(ISNUMBER(B6)),NOT(ISNUMBER(B16))),"",MAX(0,B6-B16)) | C17: Разница между полученным авансом и суммой его погашения по двусторонним актам. Основание и размер возврата проверяются по договору, документам исполнения и прекращения.
A18: Доля аванса, оставшаяся неотработанной | B18: =IFERROR(B17/B6,"") | C18: Сопоставьте показатель с фактическим выполнением и документами о его сдаче.
A19: Проверка заполнения | B19: =IF(OR(LEN(B5)=0,LEN(B6)=0,LEN(B8)=0,LEN(B11)=0),"НЕ ЗАПОЛНЕНО: цена, аванс, основание и сумма требования",IF(OR(NOT(ISNUMBER(B5)),NOT(ISNUMBER(B6)),NOT(ISNUMBER(B11))),"ОШИБКА: суммы договора должны быть числами",IF(OR(B5<=0,B6<0,B11<0),"ОШИБКА: проверьте знак и величину сумм",IF(COUNTIF($A$22:$A$27,B8)<>1,"ОШИБКА: выберите основание из справочника",IF(B6>B5,"ПРОВЕРЬТЕ: аванс больше цены договора","заполнено")))))
A21: Справочник оснований прекращения договора
A22: генподрядчик отказался от исполнения, о наших нарушениях не заявлено
A23: генподрядчик отказался от исполнения, ссылаясь на наши нарушения
A24: договор расторгнут по решению суда
A25: мы отказались от исполнения
A26: соглашение сторон
A27: договор не расторгнут, требование заявлено
A29: Основание прекращения перепишите из документа с номером и датой; отдельно проверьте спорные встречные суммы.

Sheet Выполнено
A1: Реестр актов выполненных работ | N1: Справочник статусов актов
N2: подписан обеими сторонами
A3: Запишите документ, номер, стоимость и выберите статус из списка. Погашение аванса и денежную оплату укажите числами; при отсутствии — 0. Для неподписанных и односторонних актов нужны дата и подтверждение передачи. | N3: передан, не подписан
N4: подписан односторонне
A5: № | B5: Документ | C5: № и дата | D5: Период работ | E5: Стоимость по акту | F5: Статус | G5: Дата передачи | H5: Чем подтверждена передача | I5: Погашение аванса | J5: Оплачено деньгами | K5: Не оплачено | L5: Проверка | N5: получен мотивированный отказ
A6: =IF(C6="","",ROW()-5) | K6: =IF(L6="строка заполнена",ROUND(E6-I6-J6,2),"") | L6: =IF(COUNTA(B6:J6)=0,"",IF(OR(LEN(B6)=0,LEN(C6)=0,LEN(E6)=0,LEN(F6)=0,LEN(I6)=0,LEN(J6)=0),"НЕ ЗАПОЛНЕНО: документ, номер, стоимость, статус и оплаты (ноль числом)",IF(COUNTIF($N$2:$N$5,F6)<>1,"ОШИБКА: неизвестный статус акта",IF(OR(NOT(ISNUMBER(E6)),NOT(ISNUMBER(I6)),NOT(ISNUMBER(J6))),"ОШИБКА: стоимость и оплаты должны быть числами",IF(OR(E6<0,I6<0,J6<0),"ОШИБКА: отрицательная сумма",IF(I6+J6>E6+0.01,"ОШИБКА: погашение аванса и оплата превышают стоимость акта.",IF(AND(F6<>"подписан обеими сторонами",I6>0),"ОШИБКА: погашение аванса отнесено к акту, не подписанному обеими сторонами.",IF(AND(F6<>"подписан обеими сторонами",OR(LEN(G6)=0,LEN(H6)=0)),"НЕ ЗАПОЛНЕНО: дата и подтверждение передачи акта",IF(AND(F6<>"подписан обеими сторонами",OR(NOT(ISNUMBER(G6)),G6<=0)),"ОШИБКА: дата передачи должна быть датой Excel","строка заполнена")))))))))
A7: =IF(C7="","",ROW()-5) | K7: =IF(L7="строка заполнена",ROUND(E7-I7-J7,2),"") | L7: =IF(COUNTA(B7:J7)=0,"",IF(OR(LEN(B7)=0,LEN(C7)=0,LEN(E7)=0,LEN(F7)=0,LEN(I7)=0,LEN(J7)=0),"НЕ ЗАПОЛНЕНО: документ, номер, стоимость, статус и оплаты (ноль числом)",IF(COUNTIF($N$2:$N$5,F7)<>1,"ОШИБКА: неизвестный статус акта",IF(OR(NOT(ISNUMBER(E7)),NOT(ISNUMBER(I7)),NOT(ISNUMBER(J7))),"ОШИБКА: стоимость и оплаты должны быть числами",IF(OR(E7<0,I7<0,J7<0),"ОШИБКА: отрицательная сумма",IF(I7+J7>E7+0.01,"ОШИБКА: погашение аванса и оплата превышают стоимость акта.",IF(AND(F7<>"подписан обеими сторонами",I7>0),"ОШИБКА: погашение аванса отнесено к акту, не подписанному обеими сторонами.",IF(AND(F7<>"подписан обеими сторонами",OR(LEN(G7)=0,LEN(H7)=0)),"НЕ ЗАПОЛНЕНО: дата и подтверждение передачи акта",IF(AND(F7<>"подписан обеими сторонами",OR(NOT(ISNUMBER(G7)),G7<=0)),"ОШИБКА: дата передачи должна быть датой Excel","строка заполнена")))))))))
A8: =IF(C8="","",ROW()-5) | K8: =IF(L8="строка заполнена",ROUND(E8-I8-J8,2),"") | L8: =IF(COUNTA(B8:J8)=0,"",IF(OR(LEN(B8)=0,LEN(C8)=0,LEN(E8)=0,LEN(F8)=0,LEN(I8)=0,LEN(J8)=0),"НЕ ЗАПОЛНЕНО: документ, номер, стоимость, статус и оплаты (ноль числом)",IF(COUNTIF($N$2:$N$5,F8)<>1,"ОШИБКА: неизвестный статус акта",IF(OR(NOT(ISNUMBER(E8)),NOT(ISNUMBER(I8)),NOT(ISNUMBER(J8))),"ОШИБКА: стоимость и оплаты должны быть числами",IF(OR(E8<0,I8<0,J8<0),"ОШИБКА: отрицательная сумма",IF(I8+J8>E8+0.01,"ОШИБКА: погашение аванса и оплата превышают стоимость акта.",IF(AND(F8<>"подписан обеими сторонами",I8>0),"ОШИБКА: погашение аванса отнесено к акту, не подписанному обеими сторонами.",IF(AND(F8<>"подписан обеими сторонами",OR(LEN(G8)=0,LEN(H8)=0)),"НЕ ЗАПОЛНЕНО: дата и подтверждение передачи акта",IF(AND(F8<>"подписан обеими сторонами",OR(NOT(ISNUMBER(G8)),G8<=0)),"ОШИБКА: дата передачи должна быть датой Excel","строка заполнена")))))))))
A9: =IF(C9="","",ROW()-5) | K9: =IF(L9="строка заполнена",ROUND(E9-I9-J9,2),"") | L9: =IF(COUNTA(B9:J9)=0,"",IF(OR(LEN(B9)=0,LEN(C9)=0,LEN(E9)=0,LEN(F9)=0,LEN(I9)=0,LEN(J9)=0),"НЕ ЗАПОЛНЕНО: документ, номер, стоимость, статус и оплаты (ноль числом)",IF(COUNTIF($N$2:$N$5,F9)<>1,"ОШИБКА: неизвестный статус акта",IF(OR(NOT(ISNUMBER(E9)),NOT(ISNUMBER(I9)),NOT(ISNUMBER(J9))),"ОШИБКА: стоимость и оплаты должны быть числами",IF(OR(E9<0,I9<0,J9<0),"ОШИБКА: отрицательная сумма",IF(I9+J9>E9+0.01,"ОШИБКА: погашение аванса и оплата превышают стоимость акта.",IF(AND(F9<>"подписан обеими сторонами",I9>0),"ОШИБКА: погашение аванса отнесено к акту, не подписанному обеими сторонами.",IF(AND(F9<>"подписан обеими сторонами",OR(LEN(G9)=0,LEN(H9)=0)),"НЕ ЗАПОЛНЕНО: дата и подтверждение передачи акта",IF(AND(F9<>"подписан обеими сторонами",OR(NOT(ISNUMBER(G9)),G9<=0)),"ОШИБКА: дата передачи должна быть датой Excel","строка заполнена")))))))))
A10: =IF(C10="","",ROW()-5) | K10: =IF(L10="строка заполнена",ROUND(E10-I10-J10,2),"") | L10: =IF(COUNTA(B10:J10)=0,"",IF(OR(LEN(B10)=0,LEN(C10)=0,LEN(E10)=0,LEN(F10)=0,LEN(I10)=0,LEN(J10)=0),"НЕ ЗАПОЛНЕНО: документ, номер, стоимость, статус и оплаты (ноль числом)",IF(COUNTIF($N$2:$N$5,F10)<>1,"ОШИБКА: неизвестный статус акта",IF(OR(NOT(ISNUMBER(E10)),NOT(ISNUMBER(I10)),NOT(ISNUMBER(J10))),"ОШИБКА: стоимость и оплаты должны быть числами",IF(OR(E10<0,I10<0,J10<0),"ОШИБКА: отрицательная сумма",IF(I10+J10>E10+0.01,"ОШИБКА: погашение аванса и оплата превышают стоимость акта.",IF(AND(F10<>"подписан обеими сторонами",I10>0),"ОШИБКА: погашение аванса отнесено к акту, не подписанному обеими сторонами.",IF(AND(F10<>"подписан обеими сторонами",OR(LEN(G10)=0,LEN(H10)=0)),"НЕ ЗАПОЛНЕНО: дата и подтверждение передачи акта",IF(AND(F10<>"подписан обеими сторонами",OR(NOT(ISNUMBER(G10)),G10<=0)),"ОШИБКА: дата передачи должна быть датой Excel","строка заполнена")))))))))
A11: =IF(C11="","",ROW()-5) | K11: =IF(L11="строка заполнена",ROUND(E11-I11-J11,2),"") | L11: =IF(COUNTA(B11:J11)=0,"",IF(OR(LEN(B11)=0,LEN(C11)=0,LEN(E11)=0,LEN(F11)=0,LEN(I11)=0,LEN(J11)=0),"НЕ ЗАПОЛНЕНО: документ, номер, стоимость, статус и оплаты (ноль числом)",IF(COUNTIF($N$2:$N$5,F11)<>1,"ОШИБКА: неизвестный статус акта",IF(OR(NOT(ISNUMBER(E11)),NOT(ISNUMBER(I11)),NOT(ISNUMBER(J11))),"ОШИБКА: стоимость и оплаты должны быть числами",IF(OR(E11<0,I11<0,J11<0),"ОШИБКА: отрицательная сумма",IF(I11+J11>E11+0.01,"ОШИБКА: погашение аванса и оплата превышают стоимость акта.",IF(AND(F11<>"подписан обеими сторонами",I11>0),"ОШИБКА: погашение аванса отнесено к акту, не подписанному обеими сторонами.",IF(AND(F11<>"подписан обеими сторонами",OR(LEN(G11)=0,LEN(H11)=0)),"НЕ ЗАПОЛНЕНО: дата и подтверждение передачи акта",IF(AND(F11<>"подписан обеими сторонами",OR(NOT(ISNUMBER(G11)),G11<=0)),"ОШИБКА: дата передачи должна быть датой Excel","строка заполнена")))))))))
A12: =IF(C12="","",ROW()-5) | K12: =IF(L12="строка заполнена",ROUND(E12-I12-J12,2),"") | L12: =IF(COUNTA(B12:J12)=0,"",IF(OR(LEN(B12)=0,LEN(C12)=0,LEN(E12)=0,LEN(F12)=0,LEN(I12)=0,LEN(J12)=0),"НЕ ЗАПОЛНЕНО: документ, номер, стоимость, статус и оплаты (ноль числом)",IF(COUNTIF($N$2:$N$5,F12)<>1,"ОШИБКА: неизвестный статус акта",IF(OR(NOT(ISNUMBER(E12)),NOT(ISNUMBER(I12)),NOT(ISNUMBER(J12))),"ОШИБКА: стоимость и оплаты должны быть числами",IF(OR(E12<0,I12<0,J12<0),"ОШИБКА: отрицательная сумма",IF(I12+J12>E12+0.01,"ОШИБКА: погашение аванса и оплата превышают стоимость акта.",IF(AND(F12<>"подписан обеими сторонами",I12>0),"ОШИБКА: погашение аванса отнесено к акту, не подписанному обеими сторонами.",IF(AND(F12<>"подписан обеими сторонами",OR(LEN(G12)=0,LEN(H12)=0)),"НЕ ЗАПОЛНЕНО: дата и подтверждение передачи акта",IF(AND(F12<>"подписан обеими сторонами",OR(NOT(ISNUMBER(G12)),G12<=0)),"ОШИБКА: дата передачи должна быть датой Excel","строка заполнена")))))))))
A13: =IF(C13="","",ROW()-5) | K13: =IF(L13="строка заполнена",ROUND(E13-I13-J13,2),"") | L13: =IF(COUNTA(B13:J13)=0,"",IF(OR(LEN(B13)=0,LEN(C13)=0,LEN(E13)=0,LEN(F13)=0,LEN(I13)=0,LEN(J13)=0),"НЕ ЗАПОЛНЕНО: документ, номер, стоимость, статус и оплаты (ноль числом)",IF(COUNTIF($N$2:$N$5,F13)<>1,"ОШИБКА: неизвестный статус акта",IF(OR(NOT(ISNUMBER(E13)),NOT(ISNUMBER(I13)),NOT(ISNUMBER(J13))),"ОШИБКА: стоимость и оплаты должны быть числами",IF(OR(E13<0,I13<0,J13<0),"ОШИБКА: отрицательная сумма",IF(I13+J13>E13+0.01,"ОШИБКА: погашение аванса и оплата превышают стоимость акта.",IF(AND(F13<>"подписан обеими сторонами",I13>0),"ОШИБКА: погашение аванса отнесено к акту, не подписанному обеими сторонами.",IF(AND(F13<>"подписан обеими сторонами",OR(LEN(G13)=0,LEN(H13)=0)),"НЕ ЗАПОЛНЕНО: дата и подтверждение передачи акта",IF(AND(F13<>"подписан обеими сторонами",OR(NOT(ISNUMBER(G13)),G13<=0)),"ОШИБКА: дата передачи должна быть датой Excel","строка заполнена")))))))))
A14: =IF(C14="","",ROW()-5) | K14: =IF(L14="строка заполнена",ROUND(E14-I14-J14,2),"") | L14: =IF(COUNTA(B14:J14)=0,"",IF(OR(LEN(B14)=0,LEN(C14)=0,LEN(E14)=0,LEN(F14)=0,LEN(I14)=0,LEN(J14)=0),"НЕ ЗАПОЛНЕНО: документ, номер, стоимость, статус и оплаты (ноль числом)",IF(COUNTIF($N$2:$N$5,F14)<>1,"ОШИБКА: неизвестный статус акта",IF(OR(NOT(ISNUMBER(E14)),NOT(ISNUMBER(I14)),NOT(ISNUMBER(J14))),"ОШИБКА: стоимость и оплаты должны быть числами",IF(OR(E14<0,I14<0,J14<0),"ОШИБКА: отрицательная сумма",IF(I14+J14>E14+0.01,"ОШИБКА: погашение аванса и оплата превышают стоимость акта.",IF(AND(F14<>"подписан обеими сторонами",I14>0),"ОШИБКА: погашение аванса отнесено к акту, не подписанному обеими сторонами.",IF(AND(F14<>"подписан обеими сторонами",OR(LEN(G14)=0,LEN(H14)=0)),"НЕ ЗАПОЛНЕНО: дата и подтверждение передачи акта",IF(AND(F14<>"подписан обеими сторонами",OR(NOT(ISNUMBER(G14)),G14<=0)),"ОШИБКА: дата передачи должна быть датой Excel","строка заполнена")))))))))
A15: =IF(C15="","",ROW()-5) | K15: =IF(L15="строка заполнена",ROUND(E15-I15-J15,2),"") | L15: =IF(COUNTA(B15:J15)=0,"",IF(OR(LEN(B15)=0,LEN(C15)=0,LEN(E15)=0,LEN(F15)=0,LEN(I15)=0,LEN(J15)=0),"НЕ ЗАПОЛНЕНО: документ, номер, стоимость, статус и оплаты (ноль числом)",IF(COUNTIF($N$2:$N$5,F15)<>1,"ОШИБКА: неизвестный статус акта",IF(OR(NOT(ISNUMBER(E15)),NOT(ISNUMBER(I15)),NOT(ISNUMBER(J15))),"ОШИБКА: стоимость и оплаты должны быть числами",IF(OR(E15<0,I15<0,J15<0),"ОШИБКА: отрицательная сумма",IF(I15+J15>E15+0.01,"ОШИБКА: погашение аванса и оплата превышают стоимость акта.",IF(AND(F15<>"подписан обеими сторонами",I15>0),"ОШИБКА: погашение аванса отнесено к акту, не подписанному обеими сторонами.",IF(AND(F15<>"подписан обеими сторонами",OR(LEN(G15)=0,LEN(H15)=0)),"НЕ ЗАПОЛНЕНО: дата и подтверждение передачи акта",IF(AND(F15<>"подписан обеими сторонами",OR(NOT(ISNUMBER(G15)),G15<=0)),"ОШИБКА: дата передачи должна быть датой Excel","строка заполнена")))))))))
A16: =IF(C16="","",ROW()-5) | K16: =IF(L16="строка заполнена",ROUND(E16-I16-J16,2),"") | L16: =IF(COUNTA(B16:J16)=0,"",IF(OR(LEN(B16)=0,LEN(C16)=0,LEN(E16)=0,LEN(F16)=0,LEN(I16)=0,LEN(J16)=0),"НЕ ЗАПОЛНЕНО: документ, номер, стоимость, статус и оплаты (ноль числом)",IF(COUNTIF($N$2:$N$5,F16)<>1,"ОШИБКА: неизвестный статус акта",IF(OR(NOT(ISNUMBER(E16)),NOT(ISNUMBER(I16)),NOT(ISNUMBER(J16))),"ОШИБКА: стоимость и оплаты должны быть числами",IF(OR(E16<0,I16<0,J16<0),"ОШИБКА: отрицательная сумма",IF(I16+J16>E16+0.01,"ОШИБКА: погашение аванса и оплата превышают стоимость акта.",IF(AND(F16<>"подписан обеими сторонами",I16>0),"ОШИБКА: погашение аванса отнесено к акту, не подписанному обеими сторонами.",IF(AND(F16<>"подписан обеими сторонами",OR(LEN(G16)=0,LEN(H16)=0)),"НЕ ЗАПОЛНЕНО: дата и подтверждение передачи акта",IF(AND(F16<>"подписан обеими сторонами",OR(NOT(ISNUMBER(G16)),G16<=0)),"ОШИБКА: дата передачи должна быть датой Excel","строка заполнена")))))))))
A17: =IF(C17="","",ROW()-5) | K17: =IF(L17="строка заполнена",ROUND(E17-I17-J17,2),"") | L17: =IF(COUNTA(B17:J17)=0,"",IF(OR(LEN(B17)=0,LEN(C17)=0,LEN(E17)=0,LEN(F17)=0,LEN(I17)=0,LEN(J17)=0),"НЕ ЗАПОЛНЕНО: документ, номер, стоимость, статус и оплаты (ноль числом)",IF(COUNTIF($N$2:$N$5,F17)<>1,"ОШИБКА: неизвестный статус акта",IF(OR(NOT(ISNUMBER(E17)),NOT(ISNUMBER(I17)),NOT(ISNUMBER(J17))),"ОШИБКА: стоимость и оплаты должны быть числами",IF(OR(E17<0,I17<0,J17<0),"ОШИБКА: отрицательная сумма",IF(I17+J17>E17+0.01,"ОШИБКА: погашение аванса и оплата превышают стоимость акта.",IF(AND(F17<>"подписан обеими сторонами",I17>0),"ОШИБКА: погашение аванса отнесено к акту, не подписанному обеими сторонами.",IF(AND(F17<>"подписан обеими сторонами",OR(LEN(G17)=0,LEN(H17)=0)),"НЕ ЗАПОЛНЕНО: дата и подтверждение передачи акта",IF(AND(F17<>"подписан обеими сторонами",OR(NOT(ISNUMBER(G17)),G17<=0)),"ОШИБКА: дата передачи должна быть датой Excel","строка заполнена")))))))))
... A45: =IF(C45="","",ROW()-5) | K45: =IF(L45="строка заполнена",ROUND(E45-I45-J45,2),"") | L45: =IF(COUNTA(B45:J45)=0,"",IF(OR(LEN(B45)=0,LEN(C45)=0,LEN(E45)=0,LEN(F45)=0,LEN(I45)=0,LEN(J45)=0),"НЕ ЗАПОЛНЕНО: документ, номер, стоимость, статус и оплаты (ноль числом)",IF(COUNTIF($N$2:$N$5,F45)<>1,"ОШИБКА: неизвестный статус акта",IF(OR(NOT(ISNUMBER(E45)),NOT(ISNUMBER(I45)),NOT(ISNUMBER(J45))),"ОШИБКА: стоимость и оплаты должны быть числами",IF(OR(E45<0,I45<0,J45<0),"ОШИБКА: отрицательная сумма",IF(I45+J45>E45+0.01,"ОШИБКА: погашение аванса и оплата превышают стоимость акта.",IF(AND(F45<>"подписан обеими сторонами",I45>0),"ОШИБКА: погашение аванса отнесено к акту, не подписанному обеими сторонами.",IF(AND(F45<>"подписан обеими сторонами",OR(LEN(G45)=0,LEN(H45)=0)),"НЕ ЗАПОЛНЕНО: дата и подтверждение передачи акта",IF(AND(F45<>"подписан обеими сторонами",OR(NOT(ISNUMBER(G45)),G45<=0)),"ОШИБКА: дата передачи должна быть датой Excel","строка заполнена")))))))))
A46: Итоги
A47: Всего актов внесено | E47: =COUNTIF(E6:E45,">0")
A48: Стоимость по актам, подписанным обеими сторонами | E48: =SUMIF(F6:F45,"подписан обеими сторонами",E6:E45)
A49: Стоимость по актам переданным, но не подписанным | E49: =SUMIF(F6:F45,"передан, не подписан",E6:E45)
A50: Стоимость по актам, подписанным односторонне | E50: =SUMIF(F6:F45,"подписан односторонне",E6:E45)
A51: Стоимость по актам, на которые получен мотивированный отказ | E51: =SUMIF(F6:F45,"получен мотивированный отказ",E6:E45)
A52: Погашение аванса подписанными актами | E52: =SUMIFS(I6:I45,F6:F45,"подписан обеими сторонами")
A53: Оплачено деньгами по всем актам | E53: =SUM(J6:J45)
A54: Не оплачено по подписанным актам | E54: =SUMIFS(K6:K45,F6:F45,"подписан обеими сторонами")
A55: Строк с ошибками или незаполненными данными | E55: =SUMPRODUCT(--(LEFT(L6:L45,6)="ОШИБКА"))+SUMPRODUCT(--(LEFT(L6:L45,12)="НЕ ЗАПОЛНЕНО"))
A57: Не оплачено = стоимость − погашение аванса − денежная оплата. Незавершённая строка блокирует итог сальдо; её данные нужно проверить, а не удалять из расчёта.

Sheet Встречное
A1: Реестр документально подтверждённых встречных сумм
A3: Включайте документально подтверждённые материалы, расходы и удержания. Сопоставьте каждую позицию с реестром актов и исключите повторный учёт. Укажите основание, сумму и реквизиты подтверждающего документа.
A5: № | B5: Основание | C5: Что именно | D5: Сумма | E5: Чем подтверждено | F5: Документ подписан второй стороной | G5: Проверка
A6: =IF(C6="","",ROW()-5) | G6: =IF(COUNTA(B6:F6)=0,"",IF(OR(LEN(B6)=0,LEN(C6)=0,LEN(D6)=0,LEN(E6)=0,LEN(F6)=0),"НЕ ЗАПОЛНЕНО: основание, описание, сумма, документ и подпись",IF(NOT(OR(B6="материалы переданы генподрядчику",B6="материалы и оборудование остались на объекте",B6="затраты на мобилизацию и демобилизацию",B6="гарантийное удержание из оплаченных актов",B6="иное")),"ОШИБКА: неизвестное основание встречной суммы",IF(NOT(ISNUMBER(D6)),"ОШИБКА: сумма должна быть числом",IF(D6<0,"ОШИБКА: отрицательная сумма",IF(AND(F6<>"да",F6<>"нет"),"ОШИБКА: подпись — выберите да или нет",IF(F6="нет","ПРОВЕРЬТЕ: самостоятельное основание и доказательства","строка заполнена")))))))
A7: =IF(C7="","",ROW()-5) | G7: =IF(COUNTA(B7:F7)=0,"",IF(OR(LEN(B7)=0,LEN(C7)=0,LEN(D7)=0,LEN(E7)=0,LEN(F7)=0),"НЕ ЗАПОЛНЕНО: основание, описание, сумма, документ и подпись",IF(NOT(OR(B7="материалы переданы генподрядчику",B7="материалы и оборудование остались на объекте",B7="затраты на мобилизацию и демобилизацию",B7="гарантийное удержание из оплаченных актов",B7="иное")),"ОШИБКА: неизвестное основание встречной суммы",IF(NOT(ISNUMBER(D7)),"ОШИБКА: сумма должна быть числом",IF(D7<0,"ОШИБКА: отрицательная сумма",IF(AND(F7<>"да",F7<>"нет"),"ОШИБКА: подпись — выберите да или нет",IF(F7="нет","ПРОВЕРЬТЕ: самостоятельное основание и доказательства","строка заполнена")))))))
A8: =IF(C8="","",ROW()-5) | G8: =IF(COUNTA(B8:F8)=0,"",IF(OR(LEN(B8)=0,LEN(C8)=0,LEN(D8)=0,LEN(E8)=0,LEN(F8)=0),"НЕ ЗАПОЛНЕНО: основание, описание, сумма, документ и подпись",IF(NOT(OR(B8="материалы переданы генподрядчику",B8="материалы и оборудование остались на объекте",B8="затраты на мобилизацию и демобилизацию",B8="гарантийное удержание из оплаченных актов",B8="иное")),"ОШИБКА: неизвестное основание встречной суммы",IF(NOT(ISNUMBER(D8)),"ОШИБКА: сумма должна быть числом",IF(D8<0,"ОШИБКА: отрицательная сумма",IF(AND(F8<>"да",F8<>"нет"),"ОШИБКА: подпись — выберите да или нет",IF(F8="нет","ПРОВЕРЬТЕ: самостоятельное основание и доказательства","строка заполнена")))))))
A9: =IF(C9="","",ROW()-5) | G9: =IF(COUNTA(B9:F9)=0,"",IF(OR(LEN(B9)=0,LEN(C9)=0,LEN(D9)=0,LEN(E9)=0,LEN(F9)=0),"НЕ ЗАПОЛНЕНО: основание, описание, сумма, документ и подпись",IF(NOT(OR(B9="материалы переданы генподрядчику",B9="материалы и оборудование остались на объекте",B9="затраты на мобилизацию и демобилизацию",B9="гарантийное удержание из оплаченных актов",B9="иное")),"ОШИБКА: неизвестное основание встречной суммы",IF(NOT(ISNUMBER(D9)),"ОШИБКА: сумма должна быть числом",IF(D9<0,"ОШИБКА: отрицательная сумма",IF(AND(F9<>"да",F9<>"нет"),"ОШИБКА: подпись — выберите да или нет",IF(F9="нет","ПРОВЕРЬТЕ: самостоятельное основание и доказательства","строка заполнена")))))))
A10: =IF(C10="","",ROW()-5) | G10: =IF(COUNTA(B10:F10)=0,"",IF(OR(LEN(B10)=0,LEN(C10)=0,LEN(D10)=0,LEN(E10)=0,LEN(F10)=0),"НЕ ЗАПОЛНЕНО: основание, описание, сумма, документ и подпись",IF(NOT(OR(B10="материалы переданы генподрядчику",B10="материалы и оборудование остались на объекте",B10="затраты на мобилизацию и демобилизацию",B10="гарантийное удержание из оплаченных актов",B10="иное")),"ОШИБКА: неизвестное основание встречной суммы",IF(NOT(ISNUMBER(D10)),"ОШИБКА: сумма должна быть числом",IF(D10<0,"ОШИБКА: отрицательная сумма",IF(AND(F10<>"да",F10<>"нет"),"ОШИБКА: подпись — выберите да или нет",IF(F10="нет","ПРОВЕРЬТЕ: самостоятельное основание и доказательства","строка заполнена")))))))
A11: =IF(C11="","",ROW()-5) | G11: =IF(COUNTA(B11:F11)=0,"",IF(OR(LEN(B11)=0,LEN(C11)=0,LEN(D11)=0,LEN(E11)=0,LEN(F11)=0),"НЕ ЗАПОЛНЕНО: основание, описание, сумма, документ и подпись",IF(NOT(OR(B11="материалы переданы генподрядчику",B11="материалы и оборудование остались на объекте",B11="затраты на мобилизацию и демобилизацию",B11="гарантийное удержание из оплаченных актов",B11="иное")),"ОШИБКА: неизвестное основание встречной суммы",IF(NOT(ISNUMBER(D11)),"ОШИБКА: сумма должна быть числом",IF(D11<0,"ОШИБКА: отрицательная сумма",IF(AND(F11<>"да",F11<>"нет"),"ОШИБКА: подпись — выберите да или нет",IF(F11="нет","ПРОВЕРЬТЕ: самостоятельное основание и доказательства","строка заполнена")))))))
A12: =IF(C12="","",ROW()-5) | G12: =IF(COUNTA(B12:F12)=0,"",IF(OR(LEN(B12)=0,LEN(C12)=0,LEN(D12)=0,LEN(E12)=0,LEN(F12)=0),"НЕ ЗАПОЛНЕНО: основание, описание, сумма, документ и подпись",IF(NOT(OR(B12="материалы переданы генподрядчику",B12="материалы и оборудование остались на объекте",B12="затраты на мобилизацию и демобилизацию",B12="гарантийное удержание из оплаченных актов",B12="иное")),"ОШИБКА: неизвестное основание встречной суммы",IF(NOT(ISNUMBER(D12)),"ОШИБКА: сумма должна быть числом",IF(D12<0,"ОШИБКА: отрицательная сумма",IF(AND(F12<>"да",F12<>"нет"),"ОШИБКА: подпись — выберите да или нет",IF(F12="нет","ПРОВЕРЬТЕ: самостоятельное основание и доказательства","строка заполнена")))))))
A13: =IF(C13="","",ROW()-5) | G13: =IF(COUNTA(B13:F13)=0,"",IF(OR(LEN(B13)=0,LEN(C13)=0,LEN(D13)=0,LEN(E13)=0,LEN(F13)=0),"НЕ ЗАПОЛНЕНО: основание, описание, сумма, документ и подпись",IF(NOT(OR(B13="материалы переданы генподрядчику",B13="материалы и оборудование остались на объекте",B13="затраты на мобилизацию и демобилизацию",B13="гарантийное удержание из оплаченных актов",B13="иное")),"ОШИБКА: неизвестное основание встречной суммы",IF(NOT(ISNUMBER(D13)),"ОШИБКА: сумма должна быть числом",IF(D13<0,"ОШИБКА: отрицательная сумма",IF(AND(F13<>"да",F13<>"нет"),"ОШИБКА: подпись — выберите да или нет",IF(F13="нет","ПРОВЕРЬТЕ: самостоятельное основание и доказательства","строка заполнена")))))))
A14: =IF(C14="","",ROW()-5) | G14: =IF(COUNTA(B14:F14)=0,"",IF(OR(LEN(B14)=0,LEN(C14)=0,LEN(D14)=0,LEN(E14)=0,LEN(F14)=0),"НЕ ЗАПОЛНЕНО: основание, описание, сумма, документ и подпись",IF(NOT(OR(B14="материалы переданы генподрядчику",B14="материалы и оборудование остались на объекте",B14="затраты на мобилизацию и демобилизацию",B14="гарантийное удержание из оплаченных актов",B14="иное")),"ОШИБКА: неизвестное основание встречной суммы",IF(NOT(ISNUMBER(D14)),"ОШИБКА: сумма должна быть числом",IF(D14<0,"ОШИБКА: отрицательная сумма",IF(AND(F14<>"да",F14<>"нет"),"ОШИБКА: подпись — выберите да или нет",IF(F14="нет","ПРОВЕРЬТЕ: самостоятельное основание и доказательства","строка заполнена")))))))
A15: =IF(C15="","",ROW()-5) | G15: =IF(COUNTA(B15:F15)=0,"",IF(OR(LEN(B15)=0,LEN(C15)=0,LEN(D15)=0,LEN(E15)=0,LEN(F15)=0),"НЕ ЗАПОЛНЕНО: основание, описание, сумма, документ и подпись",IF(NOT(OR(B15="материалы переданы генподрядчику",B15="материалы и оборудование остались на объекте",B15="затраты на мобилизацию и демобилизацию",B15="гарантийное удержание из оплаченных актов",B15="иное")),"ОШИБКА: неизвестное основание встречной суммы",IF(NOT(ISNUMBER(D15)),"ОШИБКА: сумма должна быть числом",IF(D15<0,"ОШИБКА: отрицательная сумма",IF(AND(F15<>"да",F15<>"нет"),"ОШИБКА: подпись — выберите да или нет",IF(F15="нет","ПРОВЕРЬТЕ: самостоятельное основание и доказательства","строка заполнена")))))))
A16: =IF(C16="","",ROW()-5) | G16: =IF(COUNTA(B16:F16)=0,"",IF(OR(LEN(B16)=0,LEN(C16)=0,LEN(D16)=0,LEN(E16)=0,LEN(F16)=0),"НЕ ЗАПОЛНЕНО: основание, описание, сумма, документ и подпись",IF(NOT(OR(B16="материалы переданы генподрядчику",B16="материалы и оборудование остались на объекте",B16="затраты на мобилизацию и демобилизацию",B16="гарантийное удержание из оплаченных актов",B16="иное")),"ОШИБКА: неизвестное основание встречной суммы",IF(NOT(ISNUMBER(D16)),"ОШИБКА: сумма должна быть числом",IF(D16<0,"ОШИБКА: отрицательная сумма",IF(AND(F16<>"да",F16<>"нет"),"ОШИБКА: подпись — выберите да или нет",IF(F16="нет","ПРОВЕРЬТЕ: самостоятельное основание и доказательства","строка заполнена")))))))
A17: =IF(C17="","",ROW()-5) | G17: =IF(COUNTA(B17:F17)=0,"",IF(OR(LEN(B17)=0,LEN(C17)=0,LEN(D17)=0,LEN(E17)=0,LEN(F17)=0),"НЕ ЗАПОЛНЕНО: основание, описание, сумма, документ и подпись",IF(NOT(OR(B17="материалы переданы генподрядчику",B17="материалы и оборудование остались на объекте",B17="затраты на мобилизацию и демобилизацию",B17="гарантийное удержание из оплаченных актов",B17="иное")),"ОШИБКА: неизвестное основание встречной суммы",IF(NOT(ISNUMBER(D17)),"ОШИБКА: сумма должна быть числом",IF(D17<0,"ОШИБКА: отрицательная сумма",IF(AND(F17<>"да",F17<>"нет"),"ОШИБКА: подпись — выберите да или нет",IF(F17="нет","ПРОВЕРЬТЕ: самостоятельное основание и доказательства","строка заполнена")))))))
... A30: =IF(C30="","",ROW()-5) | G30: =IF(COUNTA(B30:F30)=0,"",IF(OR(LEN(B30)=0,LEN(C30)=0,LEN(D30)=0,LEN(E30)=0,LEN(F30)=0),"НЕ ЗАПОЛНЕНО: основание, описание, сумма, документ и подпись",IF(NOT(OR(B30="материалы переданы генподрядчику",B30="материалы и оборудование остались на объекте",B30="затраты на мобилизацию и демобилизацию",B30="гарантийное удержание из оплаченных актов",B30="иное")),"ОШИБКА: неизвестное основание встречной суммы",IF(NOT(ISNUMBER(D30)),"ОШИБКА: сумма должна быть числом",IF(D30<0,"ОШИБКА: отрицательная сумма",IF(AND(F30<>"да",F30<>"нет"),"ОШИБКА: подпись — выберите да или нет",IF(F30="нет","ПРОВЕРЬТЕ: самостоятельное основание и доказательства","строка заполнена")))))))
A31: Итоги по основаниям
A32: материалы переданы генподрядчику | D32: =SUMIF(B6:B30,"материалы переданы генподрядчику",D6:D30)
A33: материалы и оборудование остались на объекте | D33: =SUMIF(B6:B30,"материалы и оборудование остались на объекте",D6:D30)
A34: затраты на мобилизацию и демобилизацию | D34: =SUMIF(B6:B30,"затраты на мобилизацию и демобилизацию",D6:D30)
A35: гарантийное удержание из оплаченных актов | D35: =SUMIF(B6:B30,"гарантийное удержание из оплаченных актов",D6:D30)
A36: иное | D36: =SUMIF(B6:B30,"иное",D6:D30)
A37: Итого заявляется встречного | D37: =SUM(D6:D30)
A38: Строк с ошибками или незаполненными данными | D38: =SUMPRODUCT(--(LEFT(G6:G30,6)="ОШИБКА"))+SUMPRODUCT(--(LEFT(G6:G30,12)="НЕ ЗАПОЛНЕНО"))
A40: По гарантийному удержанию укажите сумму, основание, договорное условие и срок возврата. Сверьте, что эта сумма не учтена повторно в задолженности по актам. Если срок возврата не наступил, отразите это в расчёте и ответе на требование.
A41: Для затрат на объект приложите первичные документы и отдельно проверьте договорное основание их включения в расчёт.

Sheet Сальдо
A1: Сальдо расчётов по договору
A3: Если расчёт не завершён, итог не выводится. Исправьте ошибки и пустые обязательные поля. Правовое основание каждой заявляемой суммы проверяйте отдельно.
A5: Поступило от генподрядчика
A6: Аванс получен всего | B6: ='Договор и аванс'!B6 | C6: лист «Договор и аванс»
A7: Оплачено деньгами по актам | B7: =SUM('Выполнено'!J6:J45) | C7: лист «Выполнено», колонка «Оплачено деньгами», все строки
A8: Итого поступило | B8: =IF(AND(ISNUMBER(B6),ISNUMBER(B7)),ROUND(B6+B7,2),"")
A10: Принято работ
A11: Стоимость работ по актам, подписанным обеими сторонами | B11: =SUMIF('Выполнено'!F6:F45,"подписан обеими сторонами",'Выполнено'!E6:E45) | C11: часть выполненного, подтверждённая обеими сторонами
A12: В том числе погашение аванса | B12: =SUMIFS('Выполнено'!I6:I45,'Выполнено'!F6:F45,"подписан обеими сторонами")
A13: в том числе оплачено деньгами | B13: =SUMIFS('Выполнено'!J6:J45,'Выполнено'!F6:F45,"подписан обеими сторонами")
A14: не оплачено по подписанным актам | B14: =ROUND(B11-B12-B13,2) | C14: задолженность генподрядчика перед вами по документам, подписанным обеими сторонами
A16: Не закрытая актами часть
A17: Аванс, не закрытый двусторонними актами | B17: ='Договор и аванс'!B17 | C17: Разница между фактически полученным авансом и его погашением по двусторонним актам. Сопоставьте её с основанием и размером требования о возврате.
A19: Документально подтверждённые встречные суммы
A20: Неоплаченный остаток: акты переданы, не подписаны | B20: =SUMIF('Выполнено'!F6:F45,"передан, не подписан",'Выполнено'!K6:K45) | C20: Стоимость за вычетом отнесённой денежной оплаты. Проверьте объём, передачу и основание требования.
A21: Неоплаченный остаток: односторонние акты | B21: =SUMIF('Выполнено'!F6:F45,"подписан односторонне",'Выполнено'!K6:K45) | C21: Стоимость за вычетом отнесённой денежной оплаты. Статус акта и основания по п. 4 ст. 753 ГК РФ проверяются отдельно.
A22: Материалы и оборудование | B22: =SUMIF('Встречное'!B6:B30,"материалы переданы генподрядчику",'Встречное'!D6:D30)+SUMIF('Встречное'!B6:B30,"материалы и оборудование остались на объекте",'Встречное'!D6:D30)
A23: Затраты на мобилизацию и демобилизацию | B23: =SUMIF('Встречное'!B6:B30,"затраты на мобилизацию и демобилизацию",'Встречное'!D6:D30) | C23: Проверьте основание прекращения договора и документы о фактически понесённых расходах.
A24: Гарантийное удержание из оплаченных актов | B24: =SUMIF('Встречное'!B6:B30,"гарантийное удержание из оплаченных актов",'Встречное'!D6:D30) | C24: Укажите договорное основание, событие и срок возврата удержания.
A25: Иное | B25: =SUMIF('Встречное'!B6:B30,"иное",'Встречное'!D6:D30)
A26: Задолженность по принятым и не оплаченным работам | B26: =B14 | C26: из блока «Принято работ»
A27: Итого заявляется против возврата | B27: =ROUND(SUM(B20:B26),2)
A29: Итог
A30: Требуют вернуть | B30: ='Договор и аванс'!B11 | C30: из требования
A31: Не закрыто двусторонними актами | B31: =B17 | C31: Проверьте основание возврата с учётом условий прекращения и фактического исполнения договора.
A32: Сальдо с учётом заявленного встречного | B32: =IF('Договор и аванс'!B19<>"заполнено","",IF(OR('Выполнено'!E55>0,'Встречное'!D38>0,B12>B6+0.01,B37<>"Расхождений не выявлено"),"",ROUND(B17-B27,2))) | C32: Положительное сальдо — расчётная сумма к возврату; отрицательное — расчётная задолженность перед Субподрядчиком. Каждую встречную сумму подтвердите документами.
A33: Направление сальдо | B33: =IF(NOT(ISNUMBER(B32)),"Расчёт не завершён",IF(B32>0,"к возврату генподрядчику",IF(B32<0,"К оплате Субподрядчику","ноль")))
A34: Расхождение между требованием и незакрытой частью | B34: =IF(AND(ISNUMBER(B30),ISNUMBER(B31)),ROUND(B30-B31,2),"") | C34: Разница между заявленным требованием и авансом, не погашенным по двусторонним актам.
A36: Проверки
A37: Сальдо сходится двумя способами | B37: =IFERROR(IF(ABS(ROUND(B6+B7-B11-SUMIF('Выполнено'!F6:F45,"передан, не подписан",'Выполнено'!E6:E45)-SUMIF('Выполнено'!F6:F45,"подписан односторонне",'Выполнено'!E6:E45)-SUM(B22:B25),2)-ROUND(B17-B27,2))<0.01,"Расхождений не выявлено","ПРОВЕРЬТЕ: отнесение оплат и погашение аванса"),"ПРОВЕРЬТЕ: числовые исходные данные") | C37: Сверка поступлений, стоимости включённых актов и встречных сумм. Платежи по исключённым актам и погашение сверх аванса требуют разбора.
A38: Ошибки в реестре «Выполнено» | B38: =IF('Выполнено'!E55=0,"нет","ПРОВЕРЬТЕ: незавершённых/ошибочных строк — "&'Выполнено'!E55) | C38: колонка «Проверка» на листе «Выполнено»
A39: Ошибки в реестре «Встречное» | B39: =IF('Встречное'!D38=0,"нет","ПРОВЕРЬТЕ: незавершённых/ошибочных строк — "&'Встречное'!D38) | C39: Укажите подтверждающий документ для каждой включённой суммы.
A40: Заполнение листа «Договор и аванс» | B40: ='Договор и аванс'!B19
A41: Требование больше полученного аванса | B41: =IF(B30>B6+0.01,"ПРОВЕРЬТЕ: сумма требования превышает полученный аванс.","нет") | C41: Сверьте размер требования с фактически полученным авансом и составом поступлений.
A42: Есть акты, переданные без подтверждения передачи | B42: =IF(COUNTIFS('Выполнено'!F6:F45,"передан, не подписан",'Выполнено'!H6:H45,"")=0,"нет","ПРОВЕРЬТЕ: неподписанных актов без доказательства передачи — "&COUNTIFS('Выполнено'!F6:F45,"передан, не подписан",'Выполнено'!H6:H45,"")) | C42: Подтвердите передачу актов описью, квитанцией ЭДО, почтовыми документами или отметкой получателя.
A44: Сопоставьте расчётное сальдо с требованием второй стороны. По каждому расхождению укажите сумму, основание и подтверждающий документ. Разделите согласованные позиции и спорные требования для подготовки ответа.

Sheet Акт сверки
A1: Акт сверки взаимных расчётов — печатная форма
A3: Показатели акта сверки связаны с исходными листами. Исправления сумм вносите в соответствующий реестр, затем повторно проверьте итоговую форму.
A4: Подписывайте акт сверки после сопоставления актов и платежей с расчётом обеих сторон.
A6: АКТ СВЕРКИ ВЗАИМНЫХ РАСЧЁТОВ
A7: по договору субподряда № ________ от __________ по состоянию на __________
A8: Субподрядчик: {{НАИМЕНОВАНИЕ_СУБПОДРЯДЧИКА}}. Генподрядчик: {{НАИМЕНОВАНИЕ_ГЕНПОДРЯДЧИКА}}.
A9: По данным Субподрядчика
A10: Основание | B10: Дебет (за генподрядчиком) | C10: Кредит (за субподрядчиком) | D10: Подтверждающие документы
A11: Сальдо на начало расчётов | B11: 0 | C11: 0 | D11: {{ОСНОВАНИЕ_НАЧАЛЬНОГО_САЛЬДО}}
A12: Работы приняты по актам, подписанным обеими сторонами | B12: ='Сальдо'!B11 | C12: 0 | D12: {{НОМЕРА_ДАТЫ_АКТОВ}}
A13: Получен аванс | B13: 0 | C13: ='Сальдо'!B6 | D13: {{ПЛАТЕЖИ_АВАНСА}}
A14: Оплачено деньгами по актам | B14: 0 | C14: ='Сальдо'!B7 | D14: {{ПЛАТЕЖИ_ЗА_РАБОТЫ}}
A15: Обороты за период | B15: =ROUND(SUM(B11:B14),2) | C15: =ROUND(SUM(C11:C14),2)
A16: Сальдо на конец периода | B16: =IF(NOT(ISNUMBER('Сальдо'!B32)),"",ROUND(B15-C15,2)) | D16: Положительное сальдо — задолженность Генподрядчика перед Субподрядчиком; отрицательное — задолженность Субподрядчика.
A18: =IF(NOT(ISNUMBER(B16)),"Расчёт не завершён: проверьте исходные данные",IF(B16<0,"По данным Субподрядчика на указанную дату за Субподрядчиком числится задолженность в размере, руб.:","По данным Субподрядчика на указанную дату за Генподрядчиком числится задолженность в размере, руб.:")) | D18: =IF(NOT(ISNUMBER(B16)),"",ROUND(MAX(B16,-B16),2))
A19: Отдельно, вне сальдо настоящего акта, Субподрядчик заявляет о наличии выполненных и переданных работ, акты по которым Генподрядчиком не подписаны, а также о затратах и удержаниях, перечисленных в приложении к настоящему акту. Настоящий акт составлен по данным одной стороны и не является признанием сумм, в нём не отражённых.
A21: От Субподрядчика {{ДОЛЖНОСТЬ_ФИО_ПОЛНОМОЧИЯ}} | C21: От Генподрядчика {{ДОЛЖНОСТЬ_ФИО_ПОЛНОМОЧИЯ}}
A22: _______________ / ______________ / | C22: _______________ / ______________ /
A23: М.П. | C23: М.П.
A25: Направьте акт по согласованному договорному каналу. Сохраните подписанный экземпляр, подтверждение направления, получения и ответ второй стороны.

Sheet Пример заполнения
A1: Пример заполнения — цифры условные
A3: Учебный пример отражает порядок заполнения. Рабочий расчёт составьте по документам исполнения договора и платежам.
A5: Лист «Договор и аванс»
A6: Цена работ по договору | B6: 12 000 000,00
A7: Аванс получен всего | B7: 3 600 000,00
A8: Основание прекращения договора | B8: Отказ Генподрядчика от исполнения договора; нарушения Субподрядчика в уведомлении не указаны.
A9: Сумма, которую требуют вернуть | B9: 3 600 000,00
A10: Заявленное требование о возврате сопоставляется с выполнением, погашением аванса и документально подтверждёнными встречными суммами.
A11: Лист «Выполнено»
A12: КС-2 № 1, подписан обеими сторонами | B12: Стоимость 2 000 000,00; погашение аванса 600 000,00; оплата 1 400 000,00.
A13: КС-2 № 2, подписан обеими сторонами | B13: Стоимость 1 500 000,00; погашение аванса 450 000,00; оплата 950 000,00.
A14: КС-2 № 3, передан, не подписан | B14: Стоимость 1 100 000,00; передача подтверждена описью и почтовым идентификатором.
A15: Лист «Встречное»
A16: Материалы оставлены на объекте | B16: 480 000,00, накладная подписана прорабом генподрядчика
A17: Гарантийное удержание из оплаченных актов | B17: 175 000,00
A18: Расчётные показатели листа «Сальдо»
A19: Погашение аванса по двусторонним актам | B19: 1 050 000,00
A20: Аванс, не закрытый двусторонними актами | B20: 2 550 000,00
A21: Не оплачено по подписанным актам | B21: 100 000,00
A22: Итого заявляется против возврата | B22: 1 100 000 + 480 000 + 175 000 + 100 000 = 1 855 000,00
A23: Сальдо с учётом заявленного встречного | B23: 695 000,00 к возврату
A24: Расхождение между требованием и незакрытой частью | B24: 1 050 000,00
A25: Расхождение расчётов переносите в ответ с приложением актов и платежей.
